Workbook

Sheet Master Summary
A1: Name | B1: Total Hours | C1: Visual Design | D1: Backend | E1: Web Mobile | F1: Wireframe | G1: Sheet Name
A2: Project Management
A3: Team | B3: Overall
A4: UI/UX Lead | B4: =ROUND((min(F46, G46) * (B$39 / 8)) * 40)
A5: UI/UX Review | B5: =ROUND(B6 * 10%)
A6: Design Hours (Wireframe + Visual Design) | B6: =ROUND(SUM(E55,F55))
A7: UI/UX BA | B7: =ROUND((min(F46, G46) * (B$38 / 8)) * 40)
A8: UI/UX UAT | B8: =(((min(F46, G46) / 2 ) / 2) * 40)
A9: UI/UX Documentation | B9: 0
A10: Development Hours (Web/Mobile + Backend) | B10: =ROUND(SUM(C55,D55))
A11: BA | B11: =ROUND((max(min(B46, C46), min(D46, E46)) * (B$35 / 8)) * 40)
A12: QA | B12: =ROUND((max(min(B46, C46), min(D46, E46)) * (B$37 / 8)) * 40)
A13: UAT | B13: =(((max(min(B46, C46), min(D46, E46)) / 2 ) / 2) * 40)
A14: Lead | B14: =ROUND((max(min(B46, C46), min(D46, E46)) * (B$36 / 8)) * 40)
A15: Documentation | B15: 20
A16: Deployment | B16: 80
A17: Overall | B17: =SUM(B4:B16)
A22: Team Size
A23: Name | B23: Role | C23: Count
A24: Fe | B24: SE | C24: 1
A25: Fe | B25: SSE | C25: 1
A26: Be | B26: SSE | C26: 1
A27: Be | B27: SE | C27: 1
A28: Ux | B28: UIUX_DESIGNER | C28: 0
A33: Team Hours
A34: Team | B34: Hr / Day
A35: ba | B35: 3
A36: lead | B36: 4
A37: qa | B37: 4
A38: uiux_ba | B38: 2
A39: uiux_lead | B39: 1
A44: Project Development Time Line
A45: App Name | B45: FE Min | C45: FE Max | D45: BE Min | E45: BE Max | F45: Design Min | G45: Design Max
A46: Over All | B46: =Round(IFERROR((SUM(C55)/ (SUM(C$24:C25) * 40))), 0) | C46: =Round(IFERROR((SUM(C55)/ (SUM(C$24:C25) * 35))), 0) | D46: =Round(IFERROR((SUM(D55)/ (SUM(C26:C27) * 40))), 0) | E46: =Round(IFERROR((SUM(D55)/ (SUM(C26:C27) * 35))), 0) | F46: =Round(IFERROR((SUM(E55:F55)/ (SUM(C28) * 40))), 0) | G46: =Round(IFERROR((SUM(E55:F55)/ (SUM(C28) * 35))), 0)
A51: App Wise Phase Estimation
A52: Name | B52: Sheet Name | C52: Web/Mobile | D52: Backend | E52: Visual Design | F52: Wireframes | G52: Total Hours
A53: Web App | B53: Web App - Summary | C53: =INDIRECT("'"&B53&"'!F18") | D53: =INDIRECT("'"&B53&"'!F19") | E53: =INDIRECT("'"&B53&"'!F12") | F53: =INDIRECT("'"&B53&"'!F11") | G53: =sum(C53:F53)
A54: Admin Panel | B54: Admin Panel - Summary | C54: =INDIRECT("'"&B54&"'!F18") | D54: =INDIRECT("'"&B54&"'!F19") | E54: =INDIRECT("'"&B54&"'!F12") | F54: =INDIRECT("'"&B54&"'!F11") | G54: =sum(C54:F54)
A55: Sub Total | C55: =SUM(C48:C54) | D55: =SUM(D48:D54) | E55: =SUM(E48:E54) | F55: =SUM(F48:F54) | G55: =sum(C55:F55)

Sheet Web App - Dev
A1: Module Name | B1: Feature | C1: Sub-Feature | D1: Description | E1: Reference Link | F1: Assumption | G1: Queries | H1: Prototype Link | I1: What to do? | J1: How to do? | K1: Complexity | L1: Priority | M1: Frequency | N1: Design Available | O1: Required Development | P1: NPM Packages | Q1: Wireframes Story Points | R1: =SUM(R2:R1006) | S1: Visual Design Story Points | T1: =SUM(T2:T1006) | U1: Frontend Story Points | V1: =SUM(V2:V1006) | W1: Integration Story Points | X1: =SUM(X2:X1006) | Y1: Backend Story Points | Z1: =SUM(Z2:Z1006) | AA1: =SUM(AA2:AA1006) | AB1: T-Shirt Size | AC1: Tags | AD1: Screen Patterns | AE1: Feature Categories
A2: Non Functional | B2: Boilerplate | K2: Simple | L2: Must Have | R2: =Ifs( (Q2 = 'Points-Table'!$A$4), 'Points-Table'!$C$4, (Q2 = 'Points-Table'!$A$5), 'Points-Table'!$C$5, (Q2 = 'Points-Table'!$A$6), 'Points-Table'!$C$6, (Q2 = 'Points-Table'!$A$7), 'Points-Table'!$C$7, (Q2 = 'Points-Table'!$A$8), 'Points-Table'!$C$8, (Q2 = 'Points-Table'!$A$9), 'Points-Table'!$C$9, (Q2 = 'Points-Table'!$A$10), 'Points-Table'!$C$10, (Q2 = 'Points-Table'!$A$11), 'Points-Table'!$C$11, (Q2 = 'Points-Table'!$A$12), 'Points-Table'!$C$12, (Q2 = 'Points-Table'!$A$13), 'Points-Table'!$C$13, true, 0 ) | T2: =Ifs( (S2 = 'Points-Table'!$A$4), 'Points-Table'!$C$4, (S2 = 'Points-Table'!$A$5), 'Points-Table'!$C$5, (S2 = 'Points-Table'!$A$6), 'Points-Table'!$C$6, (S2 = 'Points-Table'!$A$7), 'Points-Table'!$C$7, (S2 = 'Points-Table'!$A$8), 'Points-Table'!$C$8, (S2 = 'Points-Table'!$A$9), 'Points-Table'!$C$9, (S2 = 'Points-Table'!$A$10), 'Points-Table'!$C$10, (S2 = 'Points-Table'!$A$11), 'Points-Table'!$C$11, (S2 = 'Points-Table'!$A$12), 'Points-Table'!$C$12, (S2 = 'Points-Table'!$A$13), 'Points-Table'!$C$13, true, 0 ) | U2: 21 | V2: =Ifs( (U2 = 'Points-Table'!$A$4), 'Points-Table'!$C$4, (U2 = 'Points-Table'!$A$5), 'Points-Table'!$C$5, (U2 = 'Points-Table'!$A$6), 'Points-Table'!$C$6, (U2 = 'Points-Table'!$A$7), 'Points-Table'!$C$7, (U2 = 'Points-Table'!$A$8), 'Points-Table'!$C$8, (U2 = 'Points-Table'!$A$9), 'Points-Table'!$C$9, (U2 = 'Points-Table'!$A$10), 'Points-Table'!$C$10, (U2 = 'Points-Table'!$A$11), 'Points-Table'!$C$11, (U2 = 'Points-Table'!$A$12), 'Points-Table'!$C$12, (U2 = 'Points-Table'!$A$13), 'Points-Table'!$C$13, true, 0 ) | W2: 5 | X2: =Ifs( (W2 = 'Points-Table'!$A$4), 'Points-Table'!$C$4, (W2 = 'Points-Table'!$A$5), 'Points-Table'!$C$5, (W2 = 'Points-Table'!$A$6), 'Points-Table'!$C$6, (W2 = 'Points-Table'!$A$7), 'Points-Table'!$C$7, (W2 = 'Points-Table'!$A$8), 'Points-Table'!$C$8, (W2 = 'Points-Table'!$A$9), 'Points-Table'!$C$9, (W2 = 'Points-Table'!$A$10), 'Points-Table'!$C$10, (W2 = 'Points-Table'!$A$11), 'Points-Table'!$C$11, (W2 = 'Points-Table'!$A$12), 'Points-Table'!$C$12, (W2 = 'Points-Table'!$A$13), 'Points-Table'!$C$13, true, 0 ) | Y2: 21 | Z2: =Ifs( (Y2 = 'Points-Table'!$A$4), 'Points-Table'!$C$4, (Y2 = 'Points-Table'!$A$5), 'Points-Table'!$C$5, (Y2 = 'Points-Table'!$A$6), 'Points-Table'!$C$6, (Y2 = 'Points-Table'!$A$7), 'Points-Table'!$C$7, (Y2 = 'Points-Table'!$A$8), 'Points-Table'!$C$8, (Y2 = 'Points-Table'!$A$9), 'Points-Table'!$C$9, (Y2 = 'Points-Table'!$A$10), 'Points-Table'!$C$10, (Y2 = 'Points-Table'!$A$11), 'Points-Table'!$C$11, (Y2 = 'Points-Table'!$A$12), 'Points-Table'!$C$12, (Y2 = 'Points-Table'!$A$13), 'Points-Table'!$C$13, true, 0 ) | AA2: =SUM(V2,X2,Z2) | AB2: =Ifs( ISBETWEEN(AA2, 0, 'Points-Table'!C$20, TRUE, False), 'Points-Table'!A$20, ISBETWEEN(AA2, 'Points-Table'!C$20, 'Points-Table'!C$21, TRUE, False), 'Points-Table'!A$21, ISBETWEEN(AA2, 'Points-Table'!C$22, 10000, TRUE, TRUE), 'Points-Table'!A$22, true, 0)
A3: Non Functional | B3: ERD | F3: db planning, relation mapping & verification with client | K3: Simple | L3: Must Have | R3: =Ifs( (Q3 = 'Points-Table'!$A$4), 'Points-Table'!$C$4, (Q3 = 'Points-Table'!$A$5), 'Points-Table'!$C$5, (Q3 = 'Points-Table'!$A$6), 'Points-Table'!$C$6, (Q3 = 'Points-Table'!$A$7), 'Points-Table'!$C$7, (Q3 = 'Points-Table'!$A$8), 'Points-Table'!$C$8, (Q3 = 'Points-Table'!$A$9), 'Points-Table'!$C$9, (Q3 = 'Points-Table'!$A$10), 'Points-Table'!$C$10, (Q3 = 'Points-Table'!$A$11), 'Points-Table'!$C$11, (Q3 = 'Points-Table'!$A$12), 'Points-Table'!$C$12, (Q3 = 'Points-Table'!$A$13), 'Points-Table'!$C$13, true, 0 ) | T3: =Ifs( (S3 = 'Points-Table'!$A$4), 'Points-Table'!$C$4, (S3 = 'Points-Table'!$A$5), 'Points-Table'!$C$5, (S3 = 'Points-Table'!$A$6), 'Points-Table'!$C$6, (S3 = 'Points-Table'!$A$7), 'Points-Table'!$C$7, (S3 = 'Points-Table'!$A$8), 'Points-Table'!$C$8, (S3 = 'Points-Table'!$A$9), 'Points-Table'!$C$9, (S3 = 'Points-Table'!$A$10), 'Points-Table'!$C$10, (S3 = 'Points-Table'!$A$11), 'Points-Table'!$C$11, (S3 = 'Points-Table'!$A$12), 'Points-Table'!$C$12, (S3 = 'Points-Table'!$A$13), 'Points-Table'!$C$13, true, 0 ) | U3: 0 | V3: =Ifs( (U3 = 'Points-Table'!$A$4), 'Points-Table'!$C$4, (U3 = 'Points-Table'!$A$5), 'Points-Table'!$C$5, (U3 = 'Points-Table'!$A$6), 'Points-Table'!$C$6, (U3 = 'Points-Table'!$A$7), 'Points-Table'!$C$7, (U3 = 'Points-Table'!$A$8), 'Points-Table'!$C$8, (U3 = 'Points-Table'!$A$9), 'Points-Table'!$C$9, (U3 = 'Points-Table'!$A$10), 'Points-Table'!$C$10, (U3 = 'Points-Table'!$A$11), 'Points-Table'!$C$11, (U3 = 'Points-Table'!$A$12), 'Points-Table'!$C$12, (U3 = 'Points-Table'!$A$13), 'Points-Table'!$C$13, true, 0 ) | W3: 0 | X3: =Ifs( (W3 = 'Points-Table'!$A$4), 'Points-Table'!$C$4, (W3 = 'Points-Table'!$A$5), 'Points-Table'!$C$5, (W3 = 'Points-Table'!$A$6), 'Points-Table'!$C$6, (W3 = 'Points-Table'!$A$7), 'Points-Table'!$C$7, (W3 = 'Points-Table'!$A$8), 'Points-Table'!$C$8, (W3 = 'Points-Table'!$A$9), 'Points-Table'!$C$9, (W3 = 'Points-Table'!$A$10), 'Points-Table'!$C$10, (W3 = 'Points-Table'!$A$11), 'Points-Table'!$C$11, (W3 = 'Points-Table'!$A$12), 'Points-Table'!$C$12, (W3 = 'Points-Table'!$A$13), 'Points-Table'!$C$13, true, 0 ) | Y3: 34 | Z3: =Ifs( (Y3 = 'Points-Table'!$A$4), 'Points-Table'!$C$4, (Y3 = 'Points-Table'!$A$5), 'Points-Table'!$C$5, (Y3 = 'Points-Table'!$A$6), 'Points-Table'!$C$6, (Y3 = 'Points-Table'!$A$7), 'Points-Table'!$C$7, (Y3 = 'Points-Table'!$A$8), 'Points-Table'!$C$8, (Y3 = 'Points-Table'!$A$9), 'Points-Table'!$C$9, (Y3 = 'Points-Table'!$A$10), 'Points-Table'!$C$10, (Y3 = 'Points-Table'!$A$11), 'Points-Table'!$C$11, (Y3 = 'Points-Table'!$A$12), 'Points-Table'!$C$12, (Y3 = 'Points-Table'!$A$13), 'Points-Table'!$C$13, true, 0 ) | AA3: =SUM(V3,X3,Z3) | AB3: =Ifs( ISBETWEEN(AA3, 0, 'Points-Table'!C$20, TRUE, False), 'Points-Table'!A$20, ISBETWEEN(AA3, 'Points-Table'!C$20, 'Points-Table'!C$21, TRUE, False), 'Points-Table'!A$21, ISBETWEEN(AA3, 'Points-Table'!C$22, 10000, TRUE, TRUE), 'Points-Table'!A$22, true, 0)
A4: Login | B4: Email ID | K4: Simple | L4: Must Have | Q4: 2 | R4: =Ifs( (Q4 = 'Points-Table'!$A$4), 'Points-Table'!$C$4, (Q4 = 'Points-Table'!$A$5), 'Points-Table'!$C$5, (Q4 = 'Points-Table'!$A$6), 'Points-Table'!$C$6, (Q4 = 'Points-Table'!$A$7), 'Points-Table'!$C$7, (Q4 = 'Points-Table'!$A$8), 'Points-Table'!$C$8, (Q4 = 'Points-Table'!$A$9), 'Points-Table'!$C$9, (Q4 = 'Points-Table'!$A$10), 'Points-Table'!$C$10, (Q4 = 'Points-Table'!$A$11), 'Points-Table'!$C$11, (Q4 = 'Points-Table'!$A$12), 'Points-Table'!$C$12, (Q4 = 'Points-Table'!$A$13), 'Points-Table'!$C$13, true, 0 ) | S4: 2 | T4: =Ifs( (S4 = 'Points-Table'!$A$4), 'Points-Table'!$C$4, (S4 = 'Points-Table'!$A$5), 'Points-Table'!$C$5, (S4 = 'Points-Table'!$A$6), 'Points-Table'!$C$6, (S4 = 'Points-Table'!$A$7), 'Points-Table'!$C$7, (S4 = 'Points-Table'!$A$8), 'Points-Table'!$C$8, (S4 = 'Points-Table'!$A$9), 'Points-Table'!$C$9, (S4 = 'Points-Table'!$A$10), 'Points-Table'!$C$10, (S4 = 'Points-Table'!$A$11), 'Points-Table'!$C$11, (S4 = 'Points-Table'!$A$12), 'Points-Table'!$C$12, (S4 = 'Points-Table'!$A$13), 'Points-Table'!$C$13, true, 0 ) | U4: 5 | V4: =Ifs( (U4 = 'Points-Table'!$A$4), 'Points-Table'!$C$4, (U4 = 'Points-Table'!$A$5), 'Points-Table'!$C$5, (U4 = 'Points-Table'!$A$6), 'Points-Table'!$C$6, (U4 = 'Points-Table'!$A$7), 'Points-Table'!$C$7, (U4 = 'Points-Table'!$A$8), 'Points-Table'!$C$8, (U4 = 'Points-Table'!$A$9), 'Points-Table'!$C$9, (U4 = 'Points-Table'!$A$10), 'Points-Table'!$C$10, (U4 = 'Points-Table'!$A$11), 'Points-Table'!$C$11, (U4 = 'Points-Table'!$A$12), 'Points-Table'!$C$12, (U4 = 'Points-Table'!$A$13), 'Points-Table'!$C$13, true, 0 ) | W4: 2 | X4: =Ifs( (W4 = 'Points-Table'!$A$4), 'Points-Table'!$C$4, (W4 = 'Points-Table'!$A$5), 'Points-Table'!$C$5, (W4 = 'Points-Table'!$A$6), 'Points-Table'!$C$6, (W4 = 'Points-Table'!$A$7), 'Points-Table'!$C$7, (W4 = 'Points-Table'!$A$8), 'Points-Table'!$C$8, (W4 = 'Points-Table'!$A$9), 'Points-Table'!$C$9, (W4 = 'Points-Table'!$A$10), 'Points-Table'!$C$10, (W4 = 'Points-Table'!$A$11), 'Points-Table'!$C$11, (W4 = 'Points-Table'!$A$12), 'Points-Table'!$C$12, (W4 = 'Points-Table'!$A$13), 'Points-Table'!$C$13, true, 0 ) | Y4: 5 | Z4: =Ifs( (Y4 = 'Points-Table'!$A$4), 'Points-Table'!$C$4, (Y4 = 'Points-Table'!$A$5), 'Points-Table'!$C$5, (Y4 = 'Points-Table'!$A$6), 'Points-Table'!$C$6, (Y4 = 'Points-Table'!$A$7), 'Points-Table'!$C$7, (Y4 = 'Points-Table'!$A$8), 'Points-Table'!$C$8, (Y4 = 'Points-Table'!$A$9), 'Points-Table'!$C$9, (Y4 = 'Points-Table'!$A$10), 'Points-Table'!$C$10, (Y4 = 'Points-Table'!$A$11), 'Points-Table'!$C$11, (Y4 = 'Points-Table'!$A$12), 'Points-Table'!$C$12, (Y4 = 'Points-Table'!$A$13), 'Points-Table'!$C$13, true, 0 ) | AA4: =SUM(V4,X4,Z4) | AB4: =Ifs( ISBETWEEN(AA4, 0, 'Points-Table'!C$20, TRUE, False), 'Points-Table'!A$20, ISBETWEEN(AA4, 'Points-Table'!C$20, 'Points-Table'!C$21, TRUE, False), 'Points-Table'!A$21, ISBETWEEN(AA4, 'Points-Table'!C$22, 10000, TRUE, TRUE), 'Points-Table'!A$22, true, 0)
A5: Login | B5: OTP | K5: Simple | L5: Must Have | R5: =Ifs( (Q5 = 'Points-Table'!$A$4), 'Points-Table'!$C$4, (Q5 = 'Points-Table'!$A$5), 'Points-Table'!$C$5, (Q5 = 'Points-Table'!$A$6), 'Points-Table'!$C$6, (Q5 = 'Points-Table'!$A$7), 'Points-Table'!$C$7, (Q5 = 'Points-Table'!$A$8), 'Points-Table'!$C$8, (Q5 = 'Points-Table'!$A$9), 'Points-Table'!$C$9, (Q5 = 'Points-Table'!$A$10), 'Points-Table'!$C$10, (Q5 = 'Points-Table'!$A$11), 'Points-Table'!$C$11, (Q5 = 'Points-Table'!$A$12), 'Points-Table'!$C$12, (Q5 = 'Points-Table'!$A$13), 'Points-Table'!$C$13, true, 0 ) | T5: =Ifs( (S5 = 'Points-Table'!$A$4), 'Points-Table'!$C$4, (S5 = 'Points-Table'!$A$5), 'Points-Table'!$C$5, (S5 = 'Points-Table'!$A$6), 'Points-Table'!$C$6, (S5 = 'Points-Table'!$A$7), 'Points-Table'!$C$7, (S5 = 'Points-Table'!$A$8), 'Points-Table'!$C$8, (S5 = 'Points-Table'!$A$9), 'Points-Table'!$C$9, (S5 = 'Points-Table'!$A$10), 'Points-Table'!$C$10, (S5 = 'Points-Table'!$A$11), 'Points-Table'!$C$11, (S5 = 'Points-Table'!$A$12), 'Points-Table'!$C$12, (S5 = 'Points-Table'!$A$13), 'Points-Table'!$C$13, true, 0 ) | U5: 3 | V5: =Ifs( (U5 = 'Points-Table'!$A$4), 'Points-Table'!$C$4, (U5 = 'Points-Table'!$A$5), 'Points-Table'!$C$5, (U5 = 'Points-Table'!$A$6), 'Points-Table'!$C$6, (U5 = 'Points-Table'!$A$7), 'Points-Table'!$C$7, (U5 = 'Points-Table'!$A$8), 'Points-Table'!$C$8, (U5 = 'Points-Table'!$A$9), 'Points-Table'!$C$9, (U5 = 'Points-Table'!$A$10), 'Points-Table'!$C$10, (U5 = 'Points-Table'!$A$11), 'Points-Table'!$C$11, (U5 = 'Points-Table'!$A$12), 'Points-Table'!$C$12, (U5 = 'Points-Table'!$A$13), 'Points-Table'!$C$13, true, 0 ) | W5: 2 | X5: =Ifs( (W5 = 'Points-Table'!$A$4), 'Points-Table'!$C$4, (W5 = 'Points-Table'!$A$5), 'Points-Table'!$C$5, (W5 = 'Points-Table'!$A$6), 'Points-Table'!$C$6, (W5 = 'Points-Table'!$A$7), 'Points-Table'!$C$7, (W5 = 'Points-Table'!$A$8), 'Points-Table'!$C$8, (W5 = 'Points-Table'!$A$9), 'Points-Table'!$C$9, (W5 = 'Points-Table'!$A$10), 'Points-Table'!$C$10, (W5 = 'Points-Table'!$A$11), 'Points-Table'!$C$11, (W5 = 'Points-Table'!$A$12), 'Points-Table'!$C$12, (W5 = 'Points-Table'!$A$13), 'Points-Table'!$C$13, true, 0 ) | Y5: 3 | Z5: =Ifs( (Y5 = 'Points-Table'!$A$4), 'Points-Table'!$C$4, (Y5 = 'Points-Table'!$A$5), 'Points-Table'!$C$5, (Y5 = 'Points-Table'!$A$6), 'Points-Table'!$C$6, (Y5 = 'Points-Table'!$A$7), 'Points-Table'!$C$7, (Y5 = 'Points-Table'!$A$8), 'Points-Table'!$C$8, (Y5 = 'Points-Table'!$A$9), 'Points-Table'!$C$9, (Y5 = 'Points-Table'!$A$10), 'Points-Table'!$C$10, (Y5 = 'Points-Table'!$A$11), 'Points-Table'!$C$11, (Y5 = 'Points-Table'!$A$12), 'Points-Table'!$C$12, (Y5 = 'Points-Table'!$A$13), 'Points-Table'!$C$13, true, 0 ) | AA5: =SUM(V5,X5,Z5) | AB5: =Ifs( ISBETWEEN(AA5, 0, 'Points-Table'!C$20, TRUE, False), 'Points-Table'!A$20, ISBETWEEN(AA5, 'Points-Table'!C$20, 'Points-Table'!C$21, TRUE, False), 'Points-Table'!A$21, ISBETWEEN(AA5, 'Points-Table'!C$22, 10000, TRUE, TRUE), 'Points-Table'!A$22, true, 0)
A6: Login | B6: Login with SSO | F6: will try to reutilize the sso flow of admin end as base layer | K6: Simple | L6: Must Have | R6: =Ifs( (Q6 = 'Points-Table'!$A$4), 'Points-Table'!$C$4, (Q6 = 'Points-Table'!$A$5), 'Points-Table'!$C$5, (Q6 = 'Points-Table'!$A$6), 'Points-Table'!$C$6, (Q6 = 'Points-Table'!$A$7), 'Points-Table'!$C$7, (Q6 = 'Points-Table'!$A$8), 'Points-Table'!$C$8, (Q6 = 'Points-Table'!$A$9), 'Points-Table'!$C$9, (Q6 = 'Points-Table'!$A$10), 'Points-Table'!$C$10, (Q6 = 'Points-Table'!$A$11), 'Points-Table'!$C$11, (Q6 = 'Points-Table'!$A$12), 'Points-Table'!$C$12, (Q6 = 'Points-Table'!$A$13), 'Points-Table'!$C$13, true, 0 ) | T6: =Ifs( (S6 = 'Points-Table'!$A$4), 'Points-Table'!$C$4, (S6 = 'Points-Table'!$A$5), 'Points-Table'!$C$5, (S6 = 'Points-Table'!$A$6), 'Points-Table'!$C$6, (S6 = 'Points-Table'!$A$7), 'Points-Table'!$C$7, (S6 = 'Points-Table'!$A$8), 'Points-Table'!$C$8, (S6 = 'Points-Table'!$A$9), 'Points-Table'!$C$9, (S6 = 'Points-Table'!$A$10), 'Points-Table'!$C$10, (S6 = 'Points-Table'!$A$11), 'Points-Table'!$C$11, (S6 = 'Points-Table'!$A$12), 'Points-Table'!$C$12, (S6 = 'Points-Table'!$A$13), 'Points-Table'!$C$13, true, 0 ) | U6: 1 | V6: =Ifs( (U6 = 'Points-Table'!$A$4), 'Points-Table'!$C$4, (U6 = 'Points-Table'!$A$5), 'Points-Table'!$C$5, (U6 = 'Points-Table'!$A$6), 'Points-Table'!$C$6, (U6 = 'Points-Table'!$A$7), 'Points-Table'!$C$7, (U6 = 'Points-Table'!$A$8), 'Points-Table'!$C$8, (U6 = 'Points-Table'!$A$9), 'Points-Table'!$C$9, (U6 = 'Points-Table'!$A$10), 'Points-Table'!$C$10, (U6 = 'Points-Table'!$A$11), 'Points-Table'!$C$11, (U6 = 'Points-Table'!$A$12), 'Points-Table'!$C$12, (U6 = 'Points-Table'!$A$13), 'Points-Table'!$C$13, true, 0 ) | W6: 5 | X6: =Ifs( (W6 = 'Points-Table'!$A$4), 'Points-Table'!$C$4, (W6 = 'Points-Table'!$A$5), 'Points-Table'!$C$5, (W6 = 'Points-Table'!$A$6), 'Points-Table'!$C$6, (W6 = 'Points-Table'!$A$7), 'Points-Table'!$C$7, (W6 = 'Points-Table'!$A$8), 'Points-Table'!$C$8, (W6 = 'Points-Table'!$A$9), 'Points-Table'!$C$9, (W6 = 'Points-Table'!$A$10), 'Points-Table'!$C$10, (W6 = 'Points-Table'!$A$11), 'Points-Table'!$C$11, (W6 = 'Points-Table'!$A$12), 'Points-Table'!$C$12, (W6 = 'Points-Table'!$A$13), 'Points-Table'!$C$13, true, 0 ) | Y6: 5 | Z6: =Ifs( (Y6 = 'Points-Table'!$A$4), 'Points-Table'!$C$4, (Y6 = 'Points-Table'!$A$5), 'Points-Table'!$C$5, (Y6 = 'Points-Table'!$A$6), 'Points-Table'!$C$6, (Y6 = 'Points-Table'!$A$7), 'Points-Table'!$C$7, (Y6 = 'Points-Table'!$A$8), 'Points-Table'!$C$8, (Y6 = 'Points-Table'!$A$9), 'Points-Table'!$C$9, (Y6 = 'Points-Table'!$A$10), 'Points-Table'!$C$10, (Y6 = 'Points-Table'!$A$11), 'Points-Table'!$C$11, (Y6 = 'Points-Table'!$A$12), 'Points-Table'!$C$12, (Y6 = 'Points-Table'!$A$13), 'Points-Table'!$C$13, true, 0 ) | AA6: =SUM(V6,X6,Z6) | AB6: =Ifs( ISBETWEEN(AA6, 0, 'Points-Table'!C$20, TRUE, False), 'Points-Table'!A$20, ISBETWEEN(AA6, 'Points-Table'!C$20, 'Points-Table'!C$21, TRUE, False), 'Points-Table'!A$21, ISBETWEEN(AA6, 'Points-Table'!C$22, 10000, TRUE, TRUE), 'Points-Table'!A$22, true, 0)
A7: Policies rule Validation checks engine | B7: payment policy rule | D7: pre-pay checks & post pay autocharge user for remaining balance cron setup | F7: this will include pre payment rule check, post autocharge with specified date, specified amount if selected, autopay attempts fails then admin will sort this out on ground | K7: Simple | L7: Must Have | R7: =Ifs( (Q7 = 'Points-Table'!$A$4), 'Points-Table'!$C$4, (Q7 = 'Points-Table'!$A$5), 'Points-Table'!$C$5, (Q7 = 'Points-Table'!$A$6), 'Points-Table'!$C$6, (Q7 = 'Points-Table'!$A$7), 'Points-Table'!$C$7, (Q7 = 'Points-Table'!$A$8), 'Points-Table'!$C$8, (Q7 = 'Points-Table'!$A$9), 'Points-Table'!$C$9, (Q7 = 'Points-Table'!$A$10), 'Points-Table'!$C$10, (Q7 = 'Points-Table'!$A$11), 'Points-Table'!$C$11, (Q7 = 'Points-Table'!$A$12), 'Points-Table'!$C$12, (Q7 = 'Points-Table'!$A$13), 'Points-Table'!$C$13, true, 0 ) | T7: =Ifs( (S7 = 'Points-Table'!$A$4), 'Points-Table'!$C$4, (S7 = 'Points-Table'!$A$5), 'Points-Table'!$C$5, (S7 = 'Points-Table'!$A$6), 'Points-Table'!$C$6, (S7 = 'Points-Table'!$A$7), 'Points-Table'!$C$7, (S7 = 'Points-Table'!$A$8), 'Points-Table'!$C$8, (S7 = 'Points-Table'!$A$9), 'Points-Table'!$C$9, (S7 = 'Points-Table'!$A$10), 'Points-Table'!$C$10, (S7 = 'Points-Table'!$A$11), 'Points-Table'!$C$11, (S7 = 'Points-Table'!$A$12), 'Points-Table'!$C$12, (S7 = 'Points-Table'!$A$13), 'Points-Table'!$C$13, true, 0 ) | U7: 0 | V7: =Ifs( (U7 = 'Points-Table'!$A$4), 'Points-Table'!$C$4, (U7 = 'Points-Table'!$A$5), 'Points-Table'!$C$5, (U7 = 'Points-Table'!$A$6), 'Points-Table'!$C$6, (U7 = 'Points-Table'!$A$7), 'Points-Table'!$C$7, (U7 = 'Points-Table'!$A$8), 'Points-Table'!$C$8, (U7 = 'Points-Table'!$A$9), 'Points-Table'!$C$9, (U7 = 'Points-Table'!$A$10), 'Points-Table'!$C$10, (U7 = 'Points-Table'!$A$11), 'Points-Table'!$C$11, (U7 = 'Points-Table'!$A$12), 'Points-Table'!$C$12, (U7 = 'Points-Table'!$A$13), 'Points-Table'!$C$13, true, 0 ) | W7: 2 | X7: =Ifs( (W7 = 'Points-Table'!$A$4), 'Points-Table'!$C$4, (W7 = 'Points-Table'!$A$5), 'Points-Table'!$C$5, (W7 = 'Points-Table'!$A$6), 'Points-Table'!$C$6, (W7 = 'Points-Table'!$A$7), 'Points-Table'!$C$7, (W7 = 'Points-Table'!$A$8), 'Points-Table'!$C$8, (W7 = 'Points-Table'!$A$9), 'Points-Table'!$C$9, (W7 = 'Points-Table'!$A$10), 'Points-Table'!$C$10, (W7 = 'Points-Table'!$A$11), 'Points-Table'!$C$11, (W7 = 'Points-Table'!$A$12), 'Points-Table'!$C$12, (W7 = 'Points-Table'!$A$13), 'Points-Table'!$C$13, true, 0 ) | Y7: 21 | Z7: =Ifs( (Y7 = 'Points-Table'!$A$4), 'Points-Table'!$C$4, (Y7 = 'Points-Table'!$A$5), 'Points-Table'!$C$5, (Y7 = 'Points-Table'!$A$6), 'Points-Table'!$C$6, (Y7 = 'Points-Table'!$A$7), 'Points-Table'!$C$7, (Y7 = 'Points-Table'!$A$8), 'Points-Table'!$C$8, (Y7 = 'Points-Table'!$A$9), 'Points-Table'!$C$9, (Y7 = 'Points-Table'!$A$10), 'Points-Table'!$C$10, (Y7 = 'Points-Table'!$A$11), 'Points-Table'!$C$11, (Y7 = 'Points-Table'!$A$12), 'Points-Table'!$C$12, (Y7 = 'Points-Table'!$A$13), 'Points-Table'!$C$13, true, 0 ) | AA7: =SUM(V7,X7,Z7) | AB7: =Ifs( ISBETWEEN(AA7, 0, 'Points-Table'!C$20, TRUE, False), 'Points-Table'!A$20, ISBETWEEN(AA7, 'Points-Table'!C$20, 'Points-Table'!C$21, TRUE, False), 'Points-Table'!A$21, ISBETWEEN(AA7, 'Points-Table'!C$22, 10000, TRUE, TRUE), 'Points-Table'!A$22, true, 0)
A8: Policies rule Validation checks engine | B8: cancellation policy rule check + charge the penalty amount as per rule | D8: check cancellation restrictions, post cancellation charge penalty % amount as per rule | K8: Simple | L8: Must Have | R8: =Ifs( (Q8 = 'Points-Table'!$A$4), 'Points-Table'!$C$4, (Q8 = 'Points-Table'!$A$5), 'Points-Table'!$C$5, (Q8 = 'Points-Table'!$A$6), 'Points-Table'!$C$6, (Q8 = 'Points-Table'!$A$7), 'Points-Table'!$C$7, (Q8 = 'Points-Table'!$A$8), 'Points-Table'!$C$8, (Q8 = 'Points-Table'!$A$9), 'Points-Table'!$C$9, (Q8 = 'Points-Table'!$A$10), 'Points-Table'!$C$10, (Q8 = 'Points-Table'!$A$11), 'Points-Table'!$C$11, (Q8 = 'Points-Table'!$A$12), 'Points-Table'!$C$12, (Q8 = 'Points-Table'!$A$13), 'Points-Table'!$C$13, true, 0 ) | T8: =Ifs( (S8 = 'Points-Table'!$A$4), 'Points-Table'!$C$4, (S8 = 'Points-Table'!$A$5), 'Points-Table'!$C$5, (S8 = 'Points-Table'!$A$6), 'Points-Table'!$C$6, (S8 = 'Points-Table'!$A$7), 'Points-Table'!$C$7, (S8 = 'Points-Table'!$A$8), 'Points-Table'!$C$8, (S8 = 'Points-Table'!$A$9), 'Points-Table'!$C$9, (S8 = 'Points-Table'!$A$10), 'Points-Table'!$C$10, (S8 = 'Points-Table'!$A$11), 'Points-Table'!$C$11, (S8 = 'Points-Table'!$A$12), 'Points-Table'!$C$12, (S8 = 'Points-Table'!$A$13), 'Points-Table'!$C$13, true, 0 ) | U8: 0 | V8: =Ifs( (U8 = 'Points-Table'!$A$4), 'Points-Table'!$C$4, (U8 = 'Points-Table'!$A$5), 'Points-Table'!$C$5, (U8 = 'Points-Table'!$A$6), 'Points-Table'!$C$6, (U8 = 'Points-Table'!$A$7), 'Points-Table'!$C$7, (U8 = 'Points-Table'!$A$8), 'Points-Table'!$C$8, (U8 = 'Points-Table'!$A$9), 'Points-Table'!$C$9, (U8 = 'Points-Table'!$A$10), 'Points-Table'!$C$10, (U8 = 'Points-Table'!$A$11), 'Points-Table'!$C$11, (U8 = 'Points-Table'!$A$12), 'Points-Table'!$C$12, (U8 = 'Points-Table'!$A$13), 'Points-Table'!$C$13, true, 0 ) | W8: 2 | X8: =Ifs( (W8 = 'Points-Table'!$A$4), 'Points-Table'!$C$4, (W8 = 'Points-Table'!$A$5), 'Points-Table'!$C$5, (W8 = 'Points-Table'!$A$6), 'Points-Table'!$C$6, (W8 = 'Points-Table'!$A$7), 'Points-Table'!$C$7, (W8 = 'Points-Table'!$A$8), 'Points-Table'!$C$8, (W8 = 'Points-Table'!$A$9), 'Points-Table'!$C$9, (W8 = 'Points-Table'!$A$10), 'Points-Table'!$C$10, (W8 = 'Points-Table'!$A$11), 'Points-Table'!$C$11, (W8 = 'Points-Table'!$A$12), 'Points-Table'!$C$12, (W8 = 'Points-Table'!$A$13), 'Points-Table'!$C$13, true, 0 ) | Y8: 13 | Z8: =Ifs( (Y8 = 'Points-Table'!$A$4), 'Points-Table'!$C$4, (Y8 = 'Points-Table'!$A$5), 'Points-Table'!$C$5, (Y8 = 'Points-Table'!$A$6), 'Points-Table'!$C$6, (Y8 = 'Points-Table'!$A$7), 'Points-Table'!$C$7, (Y8 = 'Points-Table'!$A$8), 'Points-Table'!$C$8, (Y8 = 'Points-Table'!$A$9), 'Points-Table'!$C$9, (Y8 = 'Points-Table'!$A$10), 'Points-Table'!$C$10, (Y8 = 'Points-Table'!$A$11), 'Points-Table'!$C$11, (Y8 = 'Points-Table'!$A$12), 'Points-Table'!$C$12, (Y8 = 'Points-Table'!$A$13), 'Points-Table'!$C$13, true, 0 ) | AA8: =SUM(V8,X8,Z8) | AB8: =Ifs( ISBETWEEN(AA8, 0, 'Points-Table'!C$20, TRUE, False), 'Points-Table'!A$20, ISBETWEEN(AA8, 'Points-Table'!C$20, 'Points-Table'!C$21, TRUE, False), 'Points-Table'!A$21, ISBETWEEN(AA8, 'Points-Table'!C$22, 10000, TRUE, TRUE), 'Points-Table'!A$22, true, 0)
A9: Policies rule Validation checks engine | B9: minimum room night & multiple room booking rule | K9: Simple | L9: Must Have | R9: =Ifs( (Q9 = 'Points-Table'!$A$4), 'Points-Table'!$C$4, (Q9 = 'Points-Table'!$A$5), 'Points-Table'!$C$5, (Q9 = 'Points-Table'!$A$6), 'Points-Table'!$C$6, (Q9 = 'Points-Table'!$A$7), 'Points-Table'!$C$7, (Q9 = 'Points-Table'!$A$8), 'Points-Table'!$C$8, (Q9 = 'Points-Table'!$A$9), 'Points-Table'!$C$9, (Q9 = 'Points-Table'!$A$10), 'Points-Table'!$C$10, (Q9 = 'Points-Table'!$A$11), 'Points-Table'!$C$11, (Q9 = 'Points-Table'!$A$12), 'Points-Table'!$C$12, (Q9 = 'Points-Table'!$A$13), 'Points-Table'!$C$13, true, 0 ) | T9: =Ifs( (S9 = 'Points-Table'!$A$4), 'Points-Table'!$C$4, (S9 = 'Points-Table'!$A$5), 'Points-Table'!$C$5, (S9 = 'Points-Table'!$A$6), 'Points-Table'!$C$6, (S9 = 'Points-Table'!$A$7), 'Points-Table'!$C$7, (S9 = 'Points-Table'!$A$8), 'Points-Table'!$C$8, (S9 = 'Points-Table'!$A$9), 'Points-Table'!$C$9, (S9 = 'Points-Table'!$A$10), 'Points-Table'!$C$10, (S9 = 'Points-Table'!$A$11), 'Points-Table'!$C$11, (S9 = 'Points-Table'!$A$12), 'Points-Table'!$C$12, (S9 = 'Points-Table'!$A$13), 'Points-Table'!$C$13, true, 0 ) | U9: 0 | V9: =Ifs( (U9 = 'Points-Table'!$A$4), 'Points-Table'!$C$4, (U9 = 'Points-Table'!$A$5), 'Points-Table'!$C$5, (U9 = 'Points-Table'!$A$6), 'Points-Table'!$C$6, (U9 = 'Points-Table'!$A$7), 'Points-Table'!$C$7, (U9 = 'Points-Table'!$A$8), 'Points-Table'!$C$8, (U9 = 'Points-Table'!$A$9), 'Points-Table'!$C$9, (U9 = 'Points-Table'!$A$10), 'Points-Table'!$C$10, (U9 = 'Points-Table'!$A$11), 'Points-Table'!$C$11, (U9 = 'Points-Table'!$A$12), 'Points-Table'!$C$12, (U9 = 'Points-Table'!$A$13), 'Points-Table'!$C$13, true, 0 ) | W9: 2 | X9: =Ifs( (W9 = 'Points-Table'!$A$4), 'Points-Table'!$C$4, (W9 = 'Points-Table'!$A$5), 'Points-Table'!$C$5, (W9 = 'Points-Table'!$A$6), 'Points-Table'!$C$6, (W9 = 'Points-Table'!$A$7), 'Points-Table'!$C$7, (W9 = 'Points-Table'!$A$8), 'Points-Table'!$C$8, (W9 = 'Points-Table'!$A$9), 'Points-Table'!$C$9, (W9 = 'Points-Table'!$A$10), 'Points-Table'!$C$10, (W9 = 'Points-Table'!$A$11), 'Points-Table'!$C$11, (W9 = 'Points-Table'!$A$12), 'Points-Table'!$C$12, (W9 = 'Points-Table'!$A$13), 'Points-Table'!$C$13, true, 0 ) | Y9: 5 | Z9: =Ifs( (Y9 = 'Points-Table'!$A$4), 'Points-Table'!$C$4, (Y9 = 'Points-Table'!$A$5), 'Points-Table'!$C$5, (Y9 = 'Points-Table'!$A$6), 'Points-Table'!$C$6, (Y9 = 'Points-Table'!$A$7), 'Points-Table'!$C$7, (Y9 = 'Points-Table'!$A$8), 'Points-Table'!$C$8, (Y9 = 'Points-Table'!$A$9), 'Points-Table'!$C$9, (Y9 = 'Points-Table'!$A$10), 'Points-Table'!$C$10, (Y9 = 'Points-Table'!$A$11), 'Points-Table'!$C$11, (Y9 = 'Points-Table'!$A$12), 'Points-Table'!$C$12, (Y9 = 'Points-Table'!$A$13), 'Points-Table'!$C$13, true, 0 ) | AA9: =SUM(V9,X9,Z9) | AB9: =Ifs( ISBETWEEN(AA9, 0, 'Points-Table'!C$20, TRUE, False), 'Points-Table'!A$20, ISBETWEEN(AA9, 'Points-Table'!C$20, 'Points-Table'!C$21, TRUE, False), 'Points-Table'!A$21, ISBETWEEN(AA9, 'Points-Table'!C$22, 10000, TRUE, TRUE), 'Points-Table'!A$22, true, 0)
A10: Policies rule Validation checks engine | B10: hotel operational & custom text policy rulle | F10: these are only be shown as preview text during booking journey no system rule checks needed | K10: Simple | L10: Must Have | R10: =Ifs( (Q10 = 'Points-Table'!$A$4), 'Points-Table'!$C$4, (Q10 = 'Points-Table'!$A$5), 'Points-Table'!$C$5, (Q10 = 'Points-Table'!$A$6), 'Points-Table'!$C$6, (Q10 = 'Points-Table'!$A$7), 'Points-Table'!$C$7, (Q10 = 'Points-Table'!$A$8), 'Points-Table'!$C$8, (Q10 = 'Points-Table'!$A$9), 'Points-Table'!$C$9, (Q10 = 'Points-Table'!$A$10), 'Points-Table'!$C$10, (Q10 = 'Points-Table'!$A$11), 'Points-Table'!$C$11, (Q10 = 'Points-Table'!$A$12), 'Points-Table'!$C$12, (Q10 = 'Points-Table'!$A$13), 'Points-Table'!$C$13, true, 0 ) | T10: =Ifs( (S10 = 'Points-Table'!$A$4), 'Points-Table'!$C$4, (S10 = 'Points-Table'!$A$5), 'Points-Table'!$C$5, (S10 = 'Points-Table'!$A$6), 'Points-Table'!$C$6, (S10 = 'Points-Table'!$A$7), 'Points-Table'!$C$7, (S10 = 'Points-Table'!$A$8), 'Points-Table'!$C$8, (S10 = 'Points-Table'!$A$9), 'Points-Table'!$C$9, (S10 = 'Points-Table'!$A$10), 'Points-Table'!$C$10, (S10 = 'Points-Table'!$A$11), 'Points-Table'!$C$11, (S10 = 'Points-Table'!$A$12), 'Points-Table'!$C$12, (S10 = 'Points-Table'!$A$13), 'Points-Table'!$C$13, true, 0 ) | U10: 0 | V10: =Ifs( (U10 = 'Points-Table'!$A$4), 'Points-Table'!$C$4, (U10 = 'Points-Table'!$A$5), 'Points-Table'!$C$5, (U10 = 'Points-Table'!$A$6), 'Points-Table'!$C$6, (U10 = 'Points-Table'!$A$7), 'Points-Table'!$C$7, (U10 = 'Points-Table'!$A$8), 'Points-Table'!$C$8, (U10 = 'Points-Table'!$A$9), 'Points-Table'!$C$9, (U10 = 'Points-Table'!$A$10), 'Points-Table'!$C$10, (U10 = 'Points-Table'!$A$11), 'Points-Table'!$C$11, (U10 = 'Points-Table'!$A$12), 'Points-Table'!$C$12, (U10 = 'Points-Table'!$A$13), 'Points-Table'!$C$13, true, 0 ) | W10: 0 | X10: =Ifs( (W10 = 'Points-Table'!$A$4), 'Points-Table'!$C$4, (W10 = 'Points-Table'!$A$5), 'Points-Table'!$C$5, (W10 = 'Points-Table'!$A$6), 'Points-Table'!$C$6, (W10 = 'Points-Table'!$A$7), 'Points-Table'!$C$7, (W10 = 'Points-Table'!$A$8), 'Points-Table'!$C$8, (W10 = 'Points-Table'!$A$9), 'Points-Table'!$C$9, (W10 = 'Points-Table'!$A$10), 'Points-Table'!$C$10, (W10 = 'Points-Table'!$A$11), 'Points-Table'!$C$11, (W10 = 'Points-Table'!$A$12), 'Points-Table'!$C$12, (W10 = 'Points-Table'!$A$13), 'Points-Table'!$C$13, true, 0 ) | Y10: 0 | Z10: =Ifs( (Y10 = 'Points-Table'!$A$4), 'Points-Table'!$C$4, (Y10 = 'Points-Table'!$A$5), 'Points-Table'!$C$5, (Y10 = 'Points-Table'!$A$6), 'Points-Table'!$C$6, (Y10 = 'Points-Table'!$A$7), 'Points-Table'!$C$7, (Y10 = 'Points-Table'!$A$8), 'Points-Table'!$C$8, (Y10 = 'Points-Table'!$A$9), 'Points-Table'!$C$9, (Y10 = 'Points-Table'!$A$10), 'Points-Table'!$C$10, (Y10 = 'Points-Table'!$A$11), 'Points-Table'!$C$11, (Y10 = 'Points-Table'!$A$12), 'Points-Table'!$C$12, (Y10 = 'Points-Table'!$A$13), 'Points-Table'!$C$13, true, 0 ) | AA10: =SUM(V10,X10,Z10) | AB10: =Ifs( ISBETWEEN(AA10, 0, 'Points-Table'!C$20, TRUE, False), 'Points-Table'!A$20, ISBETWEEN(AA10, 'Points-Table'!C$20, 'Points-Table'!C$21, TRUE, False), 'Points-Table'!A$21, ISBETWEEN(AA10, 'Points-Table'!C$22, 10000, TRUE, TRUE), 'Points-Table'!A$22, true, 0)
A11: Lock & release inventory mechanism during cart creation | K11: Simple | L11: Must Have | R11: =Ifs( (Q11 = 'Points-Table'!$A$4), 'Points-Table'!$C$4, (Q11 = 'Points-Table'!$A$5), 'Points-Table'!$C$5, (Q11 = 'Points-Table'!$A$6), 'Points-Table'!$C$6, (Q11 = 'Points-Table'!$A$7), 'Points-Table'!$C$7, (Q11 = 'Points-Table'!$A$8), 'Points-Table'!$C$8, (Q11 = 'Points-Table'!$A$9), 'Points-Table'!$C$9, (Q11 = 'Points-Table'!$A$10), 'Points-Table'!$C$10, (Q11 = 'Points-Table'!$A$11), 'Points-Table'!$C$11, (Q11 = 'Points-Table'!$A$12), 'Points-Table'!$C$12, (Q11 = 'Points-Table'!$A$13), 'Points-Table'!$C$13, true, 0 ) | T11: =Ifs( (S11 = 'Points-Table'!$A$4), 'Points-Table'!$C$4, (S11 = 'Points-Table'!$A$5), 'Points-Table'!$C$5, (S11 = 'Points-Table'!$A$6), 'Points-Table'!$C$6, (S11 = 'Points-Table'!$A$7), 'Points-Table'!$C$7, (S11 = 'Points-Table'!$A$8), 'Points-Table'!$C$8, (S11 = 'Points-Table'!$A$9), 'Points-Table'!$C$9, (S11 = 'Points-Table'!$A$10), 'Points-Table'!$C$10, (S11 = 'Points-Table'!$A$11), 'Points-Table'!$C$11, (S11 = 'Points-Table'!$A$12), 'Points-Table'!$C$12, (S11 = 'Points-Table'!$A$13), 'Points-Table'!$C$13, true, 0 ) | U11: 3 | V11: =Ifs( (U11 = 'Points-Table'!$A$4), 'Points-Table'!$C$4, (U11 = 'Points-Table'!$A$5), 'Points-Table'!$C$5, (U11 = 'Points-Table'!$A$6), 'Points-Table'!$C$6, (U11 = 'Points-Table'!$A$7), 'Points-Table'!$C$7, (U11 = 'Points-Table'!$A$8), 'Points-Table'!$C$8, (U11 = 'Points-Table'!$A$9), 'Points-Table'!$C$9, (U11 = 'Points-Table'!$A$10), 'Points-Table'!$C$10, (U11 = 'Points-Table'!$A$11), 'Points-Table'!$C$11, (U11 = 'Points-Table'!$A$12), 'Points-Table'!$C$12, (U11 = 'Points-Table'!$A$13), 'Points-Table'!$C$13, true, 0 ) | W11: 5 | X11: =Ifs( (W11 = 'Points-Table'!$A$4), 'Points-Table'!$C$4, (W11 = 'Points-Table'!$A$5), 'Points-Table'!$C$5, (W11 = 'Points-Table'!$A$6), 'Points-Table'!$C$6, (W11 = 'Points-Table'!$A$7), 'Points-Table'!$C$7, (W11 = 'Points-Table'!$A$8), 'Points-Table'!$C$8, (W11 = 'Points-Table'!$A$9), 'Points-Table'!$C$9, (W11 = 'Points-Table'!$A$10), 'Points-Table'!$C$10, (W11 = 'Points-Table'!$A$11), 'Points-Table'!$C$11, (W11 = 'Points-Table'!$A$12), 'Points-Table'!$C$12, (W11 = 'Points-Table'!$A$13), 'Points-Table'!$C$13, true, 0 ) | Y11: 21 | Z11: =Ifs( (Y11 = 'Points-Table'!$A$4), 'Points-Table'!$C$4, (Y11 = 'Points-Table'!$A$5), 'Points-Table'!$C$5, (Y11 = 'Points-Table'!$A$6), 'Points-Table'!$C$6, (Y11 = 'Points-Table'!$A$7), 'Points-Table'!$C$7, (Y11 = 'Points-Table'!$A$8), 'Points-Table'!$C$8, (Y11 = 'Points-Table'!$A$9), 'Points-Table'!$C$9, (Y11 = 'Points-Table'!$A$10), 'Points-Table'!$C$10, (Y11 = 'Points-Table'!$A$11), 'Points-Table'!$C$11, (Y11 = 'Points-Table'!$A$12), 'Points-Table'!$C$12, (Y11 = 'Points-Table'!$A$13), 'Points-Table'!$C$13, true, 0 ) | AA11: =SUM(V11,X11,Z11) | AB11: =Ifs( ISBETWEEN(AA11, 0, 'Points-Table'!C$20, TRUE, False), 'Points-Table'!A$20, ISBETWEEN(AA11, 'Points-Table'!C$20, 'Points-Table'!C$21, TRUE, False), 'Points-Table'!A$21, ISBETWEEN(AA11, 'Points-Table'!C$22, 10000, TRUE, TRUE), 'Points-Table'!A$22, true, 0)
A12: Hotels List & Booking Flow | B12: Check in and check out date | K12: Simple | L12: Must Have | R12: =Ifs( (Q12 = 'Points-Table'!$A$4), 'Points-Table'!$C$4, (Q12 = 'Points-Table'!$A$5), 'Points-Table'!$C$5, (Q12 = 'Points-Table'!$A$6), 'Points-Table'!$C$6, (Q12 = 'Points-Table'!$A$7), 'Points-Table'!$C$7, (Q12 = 'Points-Table'!$A$8), 'Points-Table'!$C$8, (Q12 = 'Points-Table'!$A$9), 'Points-Table'!$C$9, (Q12 = 'Points-Table'!$A$10), 'Points-Table'!$C$10, (Q12 = 'Points-Table'!$A$11), 'Points-Table'!$C$11, (Q12 = 'Points-Table'!$A$12), 'Points-Table'!$C$12, (Q12 = 'Points-Table'!$A$13), 'Points-Table'!$C$13, true, 0 ) | T12: =Ifs( (S12 = 'Points-Table'!$A$4), 'Points-Table'!$C$4, (S12 = 'Points-Table'!$A$5), 'Points-Table'!$C$5, (S12 = 'Points-Table'!$A$6), 'Points-Table'!$C$6, (S12 = 'Points-Table'!$A$7), 'Points-Table'!$C$7, (S12 = 'Points-Table'!$A$8), 'Points-Table'!$C$8, (S12 = 'Points-Table'!$A$9), 'Points-Table'!$C$9, (S12 = 'Points-Table'!$A$10), 'Points-Table'!$C$10, (S12 = 'Points-Table'!$A$11), 'Points-Table'!$C$11, (S12 = 'Points-Table'!$A$12), 'Points-Table'!$C$12, (S12 = 'Points-Table'!$A$13), 'Points-Table'!$C$13, true, 0 ) | U12: 5 | V12: =Ifs( (U12 = 'Points-Table'!$A$4), 'Points-Table'!$C$4, (U12 = 'Points-Table'!$A$5), 'Points-Table'!$C$5, (U12 = 'Points-Table'!$A$6), 'Points-Table'!$C$6, (U12 = 'Points-Table'!$A$7), 'Points-Table'!$C$7, (U12 = 'Points-Table'!$A$8), 'Points-Table'!$C$8, (U12 = 'Points-Table'!$A$9), 'Points-Table'!$C$9, (U12 = 'Points-Table'!$A$10), 'Points-Table'!$C$10, (U12 = 'Points-Table'!$A$11), 'Points-Table'!$C$11, (U12 = 'Points-Table'!$A$12), 'Points-Table'!$C$12, (U12 = 'Points-Table'!$A$13), 'Points-Table'!$C$13, true, 0 ) | W12: 2 | X12: =Ifs( (W12 = 'Points-Table'!$A$4), 'Points-Table'!$C$4, (W12 = 'Points-Table'!$A$5), 'Points-Table'!$C$5, (W12 = 'Points-Table'!$A$6), 'Points-Table'!$C$6, (W12 = 'Points-Table'!$A$7), 'Points-Table'!$C$7, (W12 = 'Points-Table'!$A$8), 'Points-Table'!$C$8, (W12 = 'Points-Table'!$A$9), 'Points-Table'!$C$9, (W12 = 'Points-Table'!$A$10), 'Points-Table'!$C$10, (W12 = 'Points-Table'!$A$11), 'Points-Table'!$C$11, (W12 = 'Points-Table'!$A$12), 'Points-Table'!$C$12, (W12 = 'Points-Table'!$A$13), 'Points-Table'!$C$13, true, 0 ) | Y12: 3 | Z12: =Ifs( (Y12 = 'Points-Table'!$A$4), 'Points-Table'!$C$4, (Y12 = 'Points-Table'!$A$5), 'Points-Table'!$C$5, (Y12 = 'Points-Table'!$A$6), 'Points-Table'!$C$6, (Y12 = 'Points-Table'!$A$7), 'Points-Table'!$C$7, (Y12 = 'Points-Table'!$A$8), 'Points-Table'!$C$8, (Y12 = 'Points-Table'!$A$9), 'Points-Table'!$C$9, (Y12 = 'Points-Table'!$A$10), 'Points-Table'!$C$10, (Y12 = 'Points-Table'!$A$11), 'Points-Table'!$C$11, (Y12 = 'Points-Table'!$A$12), 'Points-Table'!$C$12, (Y12 = 'Points-Table'!$A$13), 'Points-Table'!$C$13, true, 0 ) | AA12: =SUM(V12,X12,Z12) | AB12: =Ifs( ISBETWEEN(AA12, 0, 'Points-Table'!C$20, TRUE, False), 'Points-Table'!A$20, ISBETWEEN(AA12, 'Points-Table'!C$20, 'Points-Table'!C$21, TRUE, False), 'Points-Table'!A$21, ISBETWEEN(AA12, 'Points-Table'!C$22, 10000, TRUE, TRUE), 'Points-Table'!A$22, true, 0)
A13: Hotels List & Booking Flow | B13: Search | Sort | Filter (Based on Events) | K13: Simple | L13: Must Have | Q13: 2 | R13: =Ifs( (Q13 = 'Points-Table'!$A$4), 'Points-Table'!$C$4, (Q13 = 'Points-Table'!$A$5), 'Points-Table'!$C$5, (Q13 = 'Points-Table'!$A$6), 'Points-Table'!$C$6, (Q13 = 'Points-Table'!$A$7), 'Points-Table'!$C$7, (Q13 = 'Points-Table'!$A$8), 'Points-Table'!$C$8, (Q13 = 'Points-Table'!$A$9), 'Points-Table'!$C$9, (Q13 = 'Points-Table'!$A$10), 'Points-Table'!$C$10, (Q13 = 'Points-Table'!$A$11), 'Points-Table'!$C$11, (Q13 = 'Points-Table'!$A$12), 'Points-Table'!$C$12, (Q13 = 'Points-Table'!$A$13), 'Points-Table'!$C$13, true, 0 ) | S13: 2 | T13: =Ifs( (S13 = 'Points-Table'!$A$4), 'Points-Table'!$C$4, (S13 = 'Points-Table'!$A$5), 'Points-Table'!$C$5, (S13 = 'Points-Table'!$A$6), 'Points-Table'!$C$6, (S13 = 'Points-Table'!$A$7), 'Points-Table'!$C$7, (S13 = 'Points-Table'!$A$8), 'Points-Table'!$C$8, (S13 = 'Points-Table'!$A$9), 'Points-Table'!$C$9, (S13 = 'Points-Table'!$A$10), 'Points-Table'!$C$10, (S13 = 'Points-Table'!$A$11), 'Points-Table'!$C$11, (S13 = 'Points-Table'!$A$12), 'Points-Table'!$C$12, (S13 = 'Points-Table'!$A$13), 'Points-Table'!$C$13, true, 0 ) | U13: 3 | V13: =Ifs( (U13 = 'Points-Table'!$A$4), 'Points-Table'!$C$4, (U13 = 'Points-Table'!$A$5), 'Points-Table'!$C$5, (U13 = 'Points-Table'!$A$6), 'Points-Table'!$C$6, (U13 = 'Points-Table'!$A$7), 'Points-Table'!$C$7, (U13 = 'Points-Table'!$A$8), 'Points-Table'!$C$8, (U13 = 'Points-Table'!$A$9), 'Points-Table'!$C$9, (U13 = 'Points-Table'!$A$10), 'Points-Table'!$C$10, (U13 = 'Points-Table'!$A$11), 'Points-Table'!$C$11, (U13 = 'Points-Table'!$A$12), 'Points-Table'!$C$12, (U13 = 'Points-Table'!$A$13), 'Points-Table'!$C$13, true, 0 ) | W13: 2 | X13: =Ifs( (W13 = 'Points-Table'!$A$4), 'Points-Table'!$C$4, (W13 = 'Points-Table'!$A$5), 'Points-Table'!$C$5, (W13 = 'Points-Table'!$A$6), 'Points-Table'!$C$6, (W13 = 'Points-Table'!$A$7), 'Points-Table'!$C$7, (W13 = 'Points-Table'!$A$8), 'Points-Table'!$C$8, (W13 = 'Points-Table'!$A$9), 'Points-Table'!$C$9, (W13 = 'Points-Table'!$A$10), 'Points-Table'!$C$10, (W13 = 'Points-Table'!$A$11), 'Points-Table'!$C$11, (W13 = 'Points-Table'!$A$12), 'Points-Table'!$C$12, (W13 = 'Points-Table'!$A$13), 'Points-Table'!$C$13, true, 0 ) | Y13: 5 | Z13: =Ifs( (Y13 = 'Points-Table'!$A$4), 'Points-Table'!$C$4, (Y13 = 'Points-Table'!$A$5), 'Points-Table'!$C$5, (Y13 = 'Points-Table'!$A$6), 'Points-Table'!$C$6, (Y13 = 'Points-Table'!$A$7), 'Points-Table'!$C$7, (Y13 = 'Points-Table'!$A$8), 'Points-Table'!$C$8, (Y13 = 'Points-Table'!$A$9), 'Points-Table'!$C$9, (Y13 = 'Points-Table'!$A$10), 'Points-Table'!$C$10, (Y13 = 'Points-Table'!$A$11), 'Points-Table'!$C$11, (Y13 = 'Points-Table'!$A$12), 'Points-Table'!$C$12, (Y13 = 'Points-Table'!$A$13), 'Points-Table'!$C$13, true, 0 ) | AA13: =SUM(V13,X13,Z13) | AB13: =Ifs( ISBETWEEN(AA13, 0, 'Points-Table'!C$20, TRUE, False), 'Points-Table'!A$20, ISBETWEEN(AA13, 'Points-Table'!C$20, 'Points-Table'!C$21, TRUE, False), 'Points-Table'!A$21, ISBETWEEN(AA13, 'Points-Table'!C$22, 10000, TRUE, TRUE), 'Points-Table'!A$22, true, 0)
A14: Hotels List & Booking Flow | B14: View Hotels List | C14: List View | K14: Simple | L14: Must Have | Q14: 5 | R14: =Ifs( (Q14 = 'Points-Table'!$A$4), 'Points-Table'!$C$4, (Q14 = 'Points-Table'!$A$5), 'Points-Table'!$C$5, (Q14 = 'Points-Table'!$A$6), 'Points-Table'!$C$6, (Q14 = 'Points-Table'!$A$7), 'Points-Table'!$C$7, (Q14 = 'Points-Table'!$A$8), 'Points-Table'!$C$8, (Q14 = 'Points-Table'!$A$9), 'Points-Table'!$C$9, (Q14 = 'Points-Table'!$A$10), 'Points-Table'!$C$10, (Q14 = 'Points-Table'!$A$11), 'Points-Table'!$C$11, (Q14 = 'Points-Table'!$A$12), 'Points-Table'!$C$12, (Q14 = 'Points-Table'!$A$13), 'Points-Table'!$C$13, true, 0 ) | S14: 5 | T14: =Ifs( (S14 = 'Points-Table'!$A$4), 'Points-Table'!$C$4, (S14 = 'Points-Table'!$A$5), 'Points-Table'!$C$5, (S14 = 'Points-Table'!$A$6), 'Points-Table'!$C$6, (S14 = 'Points-Table'!$A$7), 'Points-Table'!$C$7, (S14 = 'Points-Table'!$A$8), 'Points-Table'!$C$8, (S14 = 'Points-Table'!$A$9), 'Points-Table'!$C$9, (S14 = 'Points-Table'!$A$10), 'Points-Table'!$C$10, (S14 = 'Points-Table'!$A$11), 'Points-Table'!$C$11, (S14 = 'Points-Table'!$A$12), 'Points-Table'!$C$12, (S14 = 'Points-Table'!$A$13), 'Points-Table'!$C$13, true, 0 ) | U14: 5 | V14: =Ifs( (U14 = 'Points-Table'!$A$4), 'Points-Table'!$C$4, (U14 = 'Points-Table'!$A$5), 'Points-Table'!$C$5, (U14 = 'Points-Table'!$A$6), 'Points-Table'!$C$6, (U14 = 'Points-Table'!$A$7), 'Points-Table'!$C$7, (U14 = 'Points-Table'!$A$8), 'Points-Table'!$C$8, (U14 = 'Points-Table'!$A$9), 'Points-Table'!$C$9, (U14 = 'Points-Table'!$A$10), 'Points-Table'!$C$10, (U14 = 'Points-Table'!$A$11), 'Points-Table'!$C$11, (U14 = 'Points-Table'!$A$12), 'Points-Table'!$C$12, (U14 = 'Points-Table'!$A$13), 'Points-Table'!$C$13, true, 0 ) | W14: 3 | X14: =Ifs( (W14 = 'Points-Table'!$A$4), 'Points-Table'!$C$4, (W14 = 'Points-Table'!$A$5), 'Points-Table'!$C$5, (W14 = 'Points-Table'!$A$6), 'Points-Table'!$C$6, (W14 = 'Points-Table'!$A$7), 'Points-Table'!$C$7, (W14 = 'Points-Table'!$A$8), 'Points-Table'!$C$8, (W14 = 'Points-Table'!$A$9), 'Points-Table'!$C$9, (W14 = 'Points-Table'!$A$10), 'Points-Table'!$C$10, (W14 = 'Points-Table'!$A$11), 'Points-Table'!$C$11, (W14 = 'Points-Table'!$A$12), 'Points-Table'!$C$12, (W14 = 'Points-Table'!$A$13), 'Points-Table'!$C$13, true, 0 ) | Y14: 8 | Z14: =Ifs( (Y14 = 'Points-Table'!$A$4), 'Points-Table'!$C$4, (Y14 = 'Points-Table'!$A$5), 'Points-Table'!$C$5, (Y14 = 'Points-Table'!$A$6), 'Points-Table'!$C$6, (Y14 = 'Points-Table'!$A$7), 'Points-Table'!$C$7, (Y14 = 'Points-Table'!$A$8), 'Points-Table'!$C$8, (Y14 = 'Points-Table'!$A$9), 'Points-Table'!$C$9, (Y14 = 'Points-Table'!$A$10), 'Points-Table'!$C$10, (Y14 = 'Points-Table'!$A$11), 'Points-Table'!$C$11, (Y14 = 'Points-Table'!$A$12), 'Points-Table'!$C$12, (Y14 = 'Points-Table'!$A$13), 'Points-Table'!$C$13, true, 0 ) | AA14: =SUM(V14,X14,Z14) | AB14: =Ifs( ISBETWEEN(AA14, 0, 'Points-Table'!C$20, TRUE, False), 'Points-Table'!A$20, ISBETWEEN(AA14, 'Points-Table'!C$20, 'Points-Table'!C$21, TRUE, False), 'Points-Table'!A$21, ISBETWEEN(AA14, 'Points-Table'!C$22, 10000, TRUE, TRUE), 'Points-Table'!A$22, true, 0)
A15: Hotels List & Booking Flow | B15: View Hotels List | C15: Map View | K15: Simple | L15: Must Have | R15: =Ifs( (Q15 = 'Points-Table'!$A$4), 'Points-Table'!$C$4, (Q15 = 'Points-Table'!$A$5), 'Points-Table'!$C$5, (Q15 = 'Points-Table'!$A$6), 'Points-Table'!$C$6, (Q15 = 'Points-Table'!$A$7), 'Points-Table'!$C$7, (Q15 = 'Points-Table'!$A$8), 'Points-Table'!$C$8, (Q15 = 'Points-Table'!$A$9), 'Points-Table'!$C$9, (Q15 = 'Points-Table'!$A$10), 'Points-Table'!$C$10, (Q15 = 'Points-Table'!$A$11), 'Points-Table'!$C$11, (Q15 = 'Points-Table'!$A$12), 'Points-Table'!$C$12, (Q15 = 'Points-Table'!$A$13), 'Points-Table'!$C$13, true, 0 ) | T15: =Ifs( (S15 = 'Points-Table'!$A$4), 'Points-Table'!$C$4, (S15 = 'Points-Table'!$A$5), 'Points-Table'!$C$5, (S15 = 'Points-Table'!$A$6), 'Points-Table'!$C$6, (S15 = 'Points-Table'!$A$7), 'Points-Table'!$C$7, (S15 = 'Points-Table'!$A$8), 'Points-Table'!$C$8, (S15 = 'Points-Table'!$A$9), 'Points-Table'!$C$9, (S15 = 'Points-Table'!$A$10), 'Points-Table'!$C$10, (S15 = 'Points-Table'!$A$11), 'Points-Table'!$C$11, (S15 = 'Points-Table'!$A$12), 'Points-Table'!$C$12, (S15 = 'Points-Table'!$A$13), 'Points-Table'!$C$13, true, 0 ) | U15: 13 | V15: =Ifs( (U15 = 'Points-Table'!$A$4), 'Points-Table'!$C$4, (U15 = 'Points-Table'!$A$5), 'Points-Table'!$C$5, (U15 = 'Points-Table'!$A$6), 'Points-Table'!$C$6, (U15 = 'Points-Table'!$A$7), 'Points-Table'!$C$7, (U15 = 'Points-Table'!$A$8), 'Points-Table'!$C$8, (U15 = 'Points-Table'!$A$9), 'Points-Table'!$C$9, (U15 = 'Points-Table'!$A$10), 'Points-Table'!$C$10, (U15 = 'Points-Table'!$A$11), 'Points-Table'!$C$11, (U15 = 'Points-Table'!$A$12), 'Points-Table'!$C$12, (U15 = 'Points-Table'!$A$13), 'Points-Table'!$C$13, true, 0 ) | W15: 0 | X15: =Ifs( (W15 = 'Points-Table'!$A$4), 'Points-Table'!$C$4, (W15 = 'Points-Table'!$A$5), 'Points-Table'!$C$5, (W15 = 'Points-Table'!$A$6), 'Points-Table'!$C$6, (W15 = 'Points-Table'!$A$7), 'Points-Table'!$C$7, (W15 = 'Points-Table'!$A$8), 'Points-Table'!$C$8, (W15 = 'Points-Table'!$A$9), 'Points-Table'!$C$9, (W15 = 'Points-Table'!$A$10), 'Points-Table'!$C$10, (W15 = 'Points-Table'!$A$11), 'Points-Table'!$C$11, (W15 = 'Points-Table'!$A$12), 'Points-Table'!$C$12, (W15 = 'Points-Table'!$A$13), 'Points-Table'!$C$13, true, 0 ) | Y15: 2 | Z15: =Ifs( (Y15 = 'Points-Table'!$A$4), 'Points-Table'!$C$4, (Y15 = 'Points-Table'!$A$5), 'Points-Table'!$C$5, (Y15 = 'Points-Table'!$A$6), 'Points-Table'!$C$6, (Y15 = 'Points-Table'!$A$7), 'Points-Table'!$C$7, (Y15 = 'Points-Table'!$A$8), 'Points-Table'!$C$8, (Y15 = 'Points-Table'!$A$9), 'Points-Table'!$C$9, (Y15 = 'Points-Table'!$A$10), 'Points-Table'!$C$10, (Y15 = 'Points-Table'!$A$11), 'Points-Table'!$C$11, (Y15 = 'Points-Table'!$A$12), 'Points-Table'!$C$12, (Y15 = 'Points-Table'!$A$13), 'Points-Table'!$C$13, true, 0 ) | AA15: =SUM(V15,X15,Z15) | AB15: =Ifs( ISBETWEEN(AA15, 0, 'Points-Table'!C$20, TRUE, False), 'Points-Table'!A$20, ISBETWEEN(AA15, 'Points-Table'!C$20, 'Points-Table'!C$21, TRUE, False), 'Points-Table'!A$21, ISBETWEEN(AA15, 'Points-Table'!C$22, 10000, TRUE, TRUE), 'Points-Table'!A$22, true, 0)
A16: Hotels List & Booking Flow | B16: View Hotels List | C16: Grid view | K16: Simple | L16: Must Have | Q16: 2 | R16: =Ifs( (Q16 = 'Points-Table'!$A$4), 'Points-Table'!$C$4, (Q16 = 'Points-Table'!$A$5), 'Points-Table'!$C$5, (Q16 = 'Points-Table'!$A$6), 'Points-Table'!$C$6, (Q16 = 'Points-Table'!$A$7), 'Points-Table'!$C$7, (Q16 = 'Points-Table'!$A$8), 'Points-Table'!$C$8, (Q16 = 'Points-Table'!$A$9), 'Points-Table'!$C$9, (Q16 = 'Points-Table'!$A$10), 'Points-Table'!$C$10, (Q16 = 'Points-Table'!$A$11), 'Points-Table'!$C$11, (Q16 = 'Points-Table'!$A$12), 'Points-Table'!$C$12, (Q16 = 'Points-Table'!$A$13), 'Points-Table'!$C$13, true, 0 ) | S16: 2 | T16: =Ifs( (S16 = 'Points-Table'!$A$4), 'Points-Table'!$C$4, (S16 = 'Points-Table'!$A$5), 'Points-Table'!$C$5, (S16 = 'Points-Table'!$A$6), 'Points-Table'!$C$6, (S16 = 'Points-Table'!$A$7), 'Points-Table'!$C$7, (S16 = 'Points-Table'!$A$8), 'Points-Table'!$C$8, (S16 = 'Points-Table'!$A$9), 'Points-Table'!$C$9, (S16 = 'Points-Table'!$A$10), 'Points-Table'!$C$10, (S16 = 'Points-Table'!$A$11), 'Points-Table'!$C$11, (S16 = 'Points-Table'!$A$12), 'Points-Table'!$C$12, (S16 = 'Points-Table'!$A$13), 'Points-Table'!$C$13, true, 0 ) | U16: 8 | V16: =Ifs( (U16 = 'Points-Table'!$A$4), 'Points-Table'!$C$4, (U16 = 'Points-Table'!$A$5), 'Points-Table'!$C$5, (U16 = 'Points-Table'!$A$6), 'Points-Table'!$C$6, (U16 = 'Points-Table'!$A$7), 'Points-Table'!$C$7, (U16 = 'Points-Table'!$A$8), 'Points-Table'!$C$8, (U16 = 'Points-Table'!$A$9), 'Points-Table'!$C$9, (U16 = 'Points-Table'!$A$10), 'Points-Table'!$C$10, (U16 = 'Points-Table'!$A$11), 'Points-Table'!$C$11, (U16 = 'Points-Table'!$A$12), 'Points-Table'!$C$12, (U16 = 'Points-Table'!$A$13), 'Points-Table'!$C$13, true, 0 ) | W16: 0 | X16: =Ifs( (W16 = 'Points-Table'!$A$4), 'Points-Table'!$C$4, (W16 = 'Points-Table'!$A$5), 'Points-Table'!$C$5, (W16 = 'Points-Table'!$A$6), 'Points-Table'!$C$6, (W16 = 'Points-Table'!$A$7), 'Points-Table'!$C$7, (W16 = 'Points-Table'!$A$8), 'Points-Table'!$C$8, (W16 = 'Points-Table'!$A$9), 'Points-Table'!$C$9, (W16 = 'Points-Table'!$A$10), 'Points-Table'!$C$10, (W16 = 'Points-Table'!$A$11), 'Points-Table'!$C$11, (W16 = 'Points-Table'!$A$12), 'Points-Table'!$C$12, (W16 = 'Points-Table'!$A$13), 'Points-Table'!$C$13, true, 0 ) | Y16: 0 | Z16: =Ifs( (Y16 = 'Points-Table'!$A$4), 'Points-Table'!$C$4, (Y16 = 'Points-Table'!$A$5), 'Points-Table'!$C$5, (Y16 = 'Points-Table'!$A$6), 'Points-Table'!$C$6, (Y16 = 'Points-Table'!$A$7), 'Points-Table'!$C$7, (Y16 = 'Points-Table'!$A$8), 'Points-Table'!$C$8, (Y16 = 'Points-Table'!$A$9), 'Points-Table'!$C$9, (Y16 = 'Points-Table'!$A$10), 'Points-Table'!$C$10, (Y16 = 'Points-Table'!$A$11), 'Points-Table'!$C$11, (Y16 = 'Points-Table'!$A$12), 'Points-Table'!$C$12, (Y16 = 'Points-Table'!$A$13), 'Points-Table'!$C$13, true, 0 ) | AA16: =SUM(V16,X16,Z16) | AB16: =Ifs( ISBETWEEN(AA16, 0, 'Points-Table'!C$20, TRUE, False), 'Points-Table'!A$20, ISBETWEEN(AA16, 'Points-Table'!C$20, 'Points-Table'!C$21, TRUE, False), 'Points-Table'!A$21, ISBETWEEN(AA16, 'Points-Table'!C$22, 10000, TRUE, TRUE), 'Points-Table'!A$22, true, 0)
A17: Hotels List & Booking Flow | B17: View Hotel details | C17: Explore Rooms view, about hotel | K17: Simple | L17: Must Have | R17: =Ifs( (Q17 = 'Points-Table'!$A$4), 'Points-Table'!$C$4, (Q17 = 'Points-Table'!$A$5), 'Points-Table'!$C$5, (Q17 = 'Points-Table'!$A$6), 'Points-Table'!$C$6, (Q17 = 'Points-Table'!$A$7), 'Points-Table'!$C$7, (Q17 = 'Points-Table'!$A$8), 'Points-Table'!$C$8, (Q17 = 'Points-Table'!$A$9), 'Points-Table'!$C$9, (Q17 = 'Points-Table'!$A$10), 'Points-Table'!$C$10, (Q17 = 'Points-Table'!$A$11), 'Points-Table'!$C$11, (Q17 = 'Points-Table'!$A$12), 'Points-Table'!$C$12, (Q17 = 'Points-Table'!$A$13), 'Points-Table'!$C$13, true, 0 ) | T17: =Ifs( (S17 = 'Points-Table'!$A$4), 'Points-Table'!$C$4, (S17 = 'Points-Table'!$A$5), 'Points-Table'!$C$5, (S17 = 'Points-Table'!$A$6), 'Points-Table'!$C$6, (S17 = 'Points-Table'!$A$7), 'Points-Table'!$C$7, (S17 = 'Points-Table'!$A$8), 'Points-Table'!$C$8, (S17 = 'Points-Table'!$A$9), 'Points-Table'!$C$9, (S17 = 'Points-Table'!$A$10), 'Points-Table'!$C$10, (S17 = 'Points-Table'!$A$11), 'Points-Table'!$C$11, (S17 = 'Points-Table'!$A$12), 'Points-Table'!$C$12, (S17 = 'Points-Table'!$A$13), 'Points-Table'!$C$13, true, 0 ) | U17: 8 | V17: =Ifs( (U17 = 'Points-Table'!$A$4), 'Points-Table'!$C$4, (U17 = 'Points-Table'!$A$5), 'Points-Table'!$C$5, (U17 = 'Points-Table'!$A$6), 'Points-Table'!$C$6, (U17 = 'Points-Table'!$A$7), 'Points-Table'!$C$7, (U17 = 'Points-Table'!$A$8), 'Points-Table'!$C$8, (U17 = 'Points-Table'!$A$9), 'Points-Table'!$C$9, (U17 = 'Points-Table'!$A$10), 'Points-Table'!$C$10, (U17 = 'Points-Table'!$A$11), 'Points-Table'!$C$11, (U17 = 'Points-Table'!$A$12), 'Points-Table'!$C$12, (U17 = 'Points-Table'!$A$13), 'Points-Table'!$C$13, true, 0 ) | W17: 2 | X17: =Ifs( (W17 = 'Points-Table'!$A$4), 'Points-Table'!$C$4, (W17 = 'Points-Table'!$A$5), 'Points-Table'!$C$5, (W17 = 'Points-Table'!$A$6), 'Points-Table'!$C$6, (W17 = 'Points-Table'!$A$7), 'Points-Table'!$C$7, (W17 = 'Points-Table'!$A$8), 'Points-Table'!$C$8, (W17 = 'Points-Table'!$A$9), 'Points-Table'!$C$9, (W17 = 'Points-Table'!$A$10), 'Points-Table'!$C$10, (W17 = 'Points-Table'!$A$11), 'Points-Table'!$C$11, (W17 = 'Points-Table'!$A$12), 'Points-Table'!$C$12, (W17 = 'Points-Table'!$A$13), 'Points-Table'!$C$13, true, 0 ) | Y17: 8 | Z17: =Ifs( (Y17 = 'Points-Table'!$A$4), 'Points-Table'!$C$4, (Y17 = 'Points-Table'!$A$5), 'Points-Table'!$C$5, (Y17 = 'Points-Table'!$A$6), 'Points-Table'!$C$6, (Y17 = 'Points-Table'!$A$7), 'Points-Table'!$C$7, (Y17 = 'Points-Table'!$A$8), 'Points-Table'!$C$8, (Y17 = 'Points-Table'!$A$9), 'Points-Table'!$C$9, (Y17 = 'Points-Table'!$A$10), 'Points-Table'!$C$10, (Y17 = 'Points-Table'!$A$11), 'Points-Table'!$C$11, (Y17 = 'Points-Table'!$A$12), 'Points-Table'!$C$12, (Y17 = 'Points-Table'!$A$13), 'Points-Table'!$C$13, true, 0 ) | AA17: =SUM(V17,X17,Z17) | AB17: =Ifs( ISBETWEEN(AA17, 0, 'Points-Table'!C$20, TRUE, False), 'Points-Table'!A$20, ISBETWEEN(AA17, 'Points-Table'!C$20, 'Points-Table'!C$21, TRUE, False), 'Points-Table'!A$21, ISBETWEEN(AA17, 'Points-Table'!C$22, 10000, TRUE, TRUE), 'Points-Table'!A$22, true, 0)
A18: Hotels List & Booking Flow | B18: View Hotel details | C18: Amenities | K18: Simple | L18: Must Have | Q18: 1 | R18: =Ifs( (Q18 = 'Points-Table'!$A$4), 'Points-Table'!$C$4, (Q18 = 'Points-Table'!$A$5), 'Points-Table'!$C$5, (Q18 = 'Points-Table'!$A$6), 'Points-Table'!$C$6, (Q18 = 'Points-Table'!$A$7), 'Points-Table'!$C$7, (Q18 = 'Points-Table'!$A$8), 'Points-Table'!$C$8, (Q18 = 'Points-Table'!$A$9), 'Points-Table'!$C$9, (Q18 = 'Points-Table'!$A$10), 'Points-Table'!$C$10, (Q18 = 'Points-Table'!$A$11), 'Points-Table'!$C$11, (Q18 = 'Points-Table'!$A$12), 'Points-Table'!$C$12, (Q18 = 'Points-Table'!$A$13), 'Points-Table'!$C$13, true, 0 ) | S18: 1 | T18: =Ifs( (S18 = 'Points-Table'!$A$4), 'Points-Table'!$C$4, (S18 = 'Points-Table'!$A$5), 'Points-Table'!$C$5, (S18 = 'Points-Table'!$A$6), 'Points-Table'!$C$6, (S18 = 'Points-Table'!$A$7), 'Points-Table'!$C$7, (S18 = 'Points-Table'!$A$8), 'Points-Table'!$C$8, (S18 = 'Points-Table'!$A$9), 'Points-Table'!$C$9, (S18 = 'Points-Table'!$A$10), 'Points-Table'!$C$10, (S18 = 'Points-Table'!$A$11), 'Points-Table'!$C$11, (S18 = 'Points-Table'!$A$12), 'Points-Table'!$C$12, (S18 = 'Points-Table'!$A$13), 'Points-Table'!$C$13, true, 0 ) | U18: 3 | V18: =Ifs( (U18 = 'Points-Table'!$A$4), 'Points-Table'!$C$4, (U18 = 'Points-Table'!$A$5), 'Points-Table'!$C$5, (U18 = 'Points-Table'!$A$6), 'Points-Table'!$C$6, (U18 = 'Points-Table'!$A$7), 'Points-Table'!$C$7, (U18 = 'Points-Table'!$A$8), 'Points-Table'!$C$8, (U18 = 'Points-Table'!$A$9), 'Points-Table'!$C$9, (U18 = 'Points-Table'!$A$10), 'Points-Table'!$C$10, (U18 = 'Points-Table'!$A$11), 'Points-Table'!$C$11, (U18 = 'Points-Table'!$A$12), 'Points-Table'!$C$12, (U18 = 'Points-Table'!$A$13), 'Points-Table'!$C$13, true, 0 ) | W18: 2 | X18: =Ifs( (W18 = 'Points-Table'!$A$4), 'Points-Table'!$C$4, (W18 = 'Points-Table'!$A$5), 'Points-Table'!$C$5, (W18 = 'Points-Table'!$A$6), 'Points-Table'!$C$6, (W18 = 'Points-Table'!$A$7), 'Points-Table'!$C$7, (W18 = 'Points-Table'!$A$8), 'Points-Table'!$C$8, (W18 = 'Points-Table'!$A$9), 'Points-Table'!$C$9, (W18 = 'Points-Table'!$A$10), 'Points-Table'!$C$10, (W18 = 'Points-Table'!$A$11), 'Points-Table'!$C$11, (W18 = 'Points-Table'!$A$12), 'Points-Table'!$C$12, (W18 = 'Points-Table'!$A$13), 'Points-Table'!$C$13, true, 0 ) | Y18: 2 | Z18: =Ifs( (Y18 = 'Points-Table'!$A$4), 'Points-Table'!$C$4, (Y18 = 'Points-Table'!$A$5), 'Points-Table'!$C$5, (Y18 = 'Points-Table'!$A$6), 'Points-Table'!$C$6, (Y18 = 'Points-Table'!$A$7), 'Points-Table'!$C$7, (Y18 = 'Points-Table'!$A$8), 'Points-Table'!$C$8, (Y18 = 'Points-Table'!$A$9), 'Points-Table'!$C$9, (Y18 = 'Points-Table'!$A$10), 'Points-Table'!$C$10, (Y18 = 'Points-Table'!$A$11), 'Points-Table'!$C$11, (Y18 = 'Points-Table'!$A$12), 'Points-Table'!$C$12, (Y18 = 'Points-Table'!$A$13), 'Points-Table'!$C$13, true, 0 ) | AA18: =SUM(V18,X18,Z18) | AB18: =Ifs( ISBETWEEN(AA18, 0, 'Points-Table'!C$20, TRUE, False), 'Points-Table'!A$20, ISBETWEEN(AA18, 'Points-Table'!C$20, 'Points-Table'!C$21, TRUE, False), 'Points-Table'!A$21, ISBETWEEN(AA18, 'Points-Table'!C$22, 10000, TRUE, TRUE), 'Points-Table'!A$22, true, 0)
A19: Hotels List & Booking Flow | B19: View Hotel details | C19: Distance to venue, Room types, Nightly rates | K19: Simple | L19: Must Have | Q19: 1 | R19: =Ifs( (Q19 = 'Points-Table'!$A$4), 'Points-Table'!$C$4, (Q19 = 'Points-Table'!$A$5), 'Points-Table'!$C$5, (Q19 = 'Points-Table'!$A$6), 'Points-Table'!$C$6, (Q19 = 'Points-Table'!$A$7), 'Points-Table'!$C$7, (Q19 = 'Points-Table'!$A$8), 'Points-Table'!$C$8, (Q19 = 'Points-Table'!$A$9), 'Points-Table'!$C$9, (Q19 = 'Points-Table'!$A$10), 'Points-Table'!$C$10, (Q19 = 'Points-Table'!$A$11), 'Points-Table'!$C$11, (Q19 = 'Points-Table'!$A$12), 'Points-Table'!$C$12, (Q19 = 'Points-Table'!$A$13), 'Points-Table'!$C$13, true, 0 ) | S19: 1 | T19: =Ifs( (S19 = 'Points-Table'!$A$4), 'Points-Table'!$C$4, (S19 = 'Points-Table'!$A$5), 'Points-Table'!$C$5, (S19 = 'Points-Table'!$A$6), 'Points-Table'!$C$6, (S19 = 'Points-Table'!$A$7), 'Points-Table'!$C$7, (S19 = 'Points-Table'!$A$8), 'Points-Table'!$C$8, (S19 = 'Points-Table'!$A$9), 'Points-Table'!$C$9, (S19 = 'Points-Table'!$A$10), 'Points-Table'!$C$10, (S19 = 'Points-Table'!$A$11), 'Points-Table'!$C$11, (S19 = 'Points-Table'!$A$12), 'Points-Table'!$C$12, (S19 = 'Points-Table'!$A$13), 'Points-Table'!$C$13, true, 0 ) | U19: 5 | V19: =Ifs( (U19 = 'Points-Table'!$A$4), 'Points-Table'!$C$4, (U19 = 'Points-Table'!$A$5), 'Points-Table'!$C$5, (U19 = 'Points-Table'!$A$6), 'Points-Table'!$C$6, (U19 = 'Points-Table'!$A$7), 'Points-Table'!$C$7, (U19 = 'Points-Table'!$A$8), 'Points-Table'!$C$8, (U19 = 'Points-Table'!$A$9), 'Points-Table'!$C$9, (U19 = 'Points-Table'!$A$10), 'Points-Table'!$C$10, (U19 = 'Points-Table'!$A$11), 'Points-Table'!$C$11, (U19 = 'Points-Table'!$A$12), 'Points-Table'!$C$12, (U19 = 'Points-Table'!$A$13), 'Points-Table'!$C$13, true, 0 ) | W19: 2 | X19: =Ifs( (W19 = 'Points-Table'!$A$4), 'Points-Table'!$C$4, (W19 = 'Points-Table'!$A$5), 'Points-Table'!$C$5, (W19 = 'Points-Table'!$A$6), 'Points-Table'!$C$6, (W19 = 'Points-Table'!$A$7), 'Points-Table'!$C$7, (W19 = 'Points-Table'!$A$8), 'Points-Table'!$C$8, (W19 = 'Points-Table'!$A$9), 'Points-Table'!$C$9, (W19 = 'Points-Table'!$A$10), 'Points-Table'!$C$10, (W19 = 'Points-Table'!$A$11), 'Points-Table'!$C$11, (W19 = 'Points-Table'!$A$12), 'Points-Table'!$C$12, (W19 = 'Points-Table'!$A$13), 'Points-Table'!$C$13, true, 0 ) | Y19: 5 | Z19: =Ifs( (Y19 = 'Points-Table'!$A$4), 'Points-Table'!$C$4, (Y19 = 'Points-Table'!$A$5), 'Points-Table'!$C$5, (Y19 = 'Points-Table'!$A$6), 'Points-Table'!$C$6, (Y19 = 'Points-Table'!$A$7), 'Points-Table'!$C$7, (Y19 = 'Points-Table'!$A$8), 'Points-Table'!$C$8, (Y19 = 'Points-Table'!$A$9), 'Points-Table'!$C$9, (Y19 = 'Points-Table'!$A$10), 'Points-Table'!$C$10, (Y19 = 'Points-Table'!$A$11), 'Points-Table'!$C$11, (Y19 = 'Points-Table'!$A$12), 'Points-Table'!$C$12, (Y19 = 'Points-Table'!$A$13), 'Points-Table'!$C$13, true, 0 ) | AA19: =SUM(V19,X19,Z19) | AB19: =Ifs( ISBETWEEN(AA19, 0, 'Points-Table'!C$20, TRUE, False), 'Points-Table'!A$20, ISBETWEEN(AA19, 'Points-Table'!C$20, 'Points-Table'!C$21, TRUE, False), 'Points-Table'!A$21, ISBETWEEN(AA19, 'Points-Table'!C$22, 10000, TRUE, TRUE), 'Points-Table'!A$22, true, 0)
A20: Hotels List & Booking Flow | B20: View Hotel details | C20: Hotel Policies | K20: Simple | L20: Must Have | R20: =Ifs( (Q20 = 'Points-Table'!$A$4), 'Points-Table'!$C$4, (Q20 = 'Points-Table'!$A$5), 'Points-Table'!$C$5, (Q20 = 'Points-Table'!$A$6), 'Points-Table'!$C$6, (Q20 = 'Points-Table'!$A$7), 'Points-Table'!$C$7, (Q20 = 'Points-Table'!$A$8), 'Points-Table'!$C$8, (Q20 = 'Points-Table'!$A$9), 'Points-Table'!$C$9, (Q20 = 'Points-Table'!$A$10), 'Points-Table'!$C$10, (Q20 = 'Points-Table'!$A$11), 'Points-Table'!$C$11, (Q20 = 'Points-Table'!$A$12), 'Points-Table'!$C$12, (Q20 = 'Points-Table'!$A$13), 'Points-Table'!$C$13, true, 0 ) | T20: =Ifs( (S20 = 'Points-Table'!$A$4), 'Points-Table'!$C$4, (S20 = 'Points-Table'!$A$5), 'Points-Table'!$C$5, (S20 = 'Points-Table'!$A$6), 'Points-Table'!$C$6, (S20 = 'Points-Table'!$A$7), 'Points-Table'!$C$7, (S20 = 'Points-Table'!$A$8), 'Points-Table'!$C$8, (S20 = 'Points-Table'!$A$9), 'Points-Table'!$C$9, (S20 = 'Points-Table'!$A$10), 'Points-Table'!$C$10, (S20 = 'Points-Table'!$A$11), 'Points-Table'!$C$11, (S20 = 'Points-Table'!$A$12), 'Points-Table'!$C$12, (S20 = 'Points-Table'!$A$13), 'Points-Table'!$C$13, true, 0 ) | U20: 3 | V20: =Ifs( (U20 = 'Points-Table'!$A$4), 'Points-Table'!$C$4, (U20 = 'Points-Table'!$A$5), 'Points-Table'!$C$5, (U20 = 'Points-Table'!$A$6), 'Points-Table'!$C$6, (U20 = 'Points-Table'!$A$7), 'Points-Table'!$C$7, (U20 = 'Points-Table'!$A$8), 'Points-Table'!$C$8, (U20 = 'Points-Table'!$A$9), 'Points-Table'!$C$9, (U20 = 'Points-Table'!$A$10), 'Points-Table'!$C$10, (U20 = 'Points-Table'!$A$11), 'Points-Table'!$C$11, (U20 = 'Points-Table'!$A$12), 'Points-Table'!$C$12, (U20 = 'Points-Table'!$A$13), 'Points-Table'!$C$13, true, 0 ) | W20: 2 | X20: =Ifs( (W20 = 'Points-Table'!$A$4), 'Points-Table'!$C$4, (W20 = 'Points-Table'!$A$5), 'Points-Table'!$C$5, (W20 = 'Points-Table'!$A$6), 'Points-Table'!$C$6, (W20 = 'Points-Table'!$A$7), 'Points-Table'!$C$7, (W20 = 'Points-Table'!$A$8), 'Points-Table'!$C$8, (W20 = 'Points-Table'!$A$9), 'Points-Table'!$C$9, (W20 = 'Points-Table'!$A$10), 'Points-Table'!$C$10, (W20 = 'Points-Table'!$A$11), 'Points-Table'!$C$11, (W20 = 'Points-Table'!$A$12), 'Points-Table'!$C$12, (W20 = 'Points-Table'!$A$13), 'Points-Table'!$C$13, true, 0 ) | Y20: 3 | Z20: =Ifs( (Y20 = 'Points-Table'!$A$4), 'Points-Table'!$C$4, (Y20 = 'Points-Table'!$A$5), 'Points-Table'!$C$5, (Y20 = 'Points-Table'!$A$6), 'Points-Table'!$C$6, (Y20 = 'Points-Table'!$A$7), 'Points-Table'!$C$7, (Y20 = 'Points-Table'!$A$8), 'Points-Table'!$C$8, (Y20 = 'Points-Table'!$A$9), 'Points-Table'!$C$9, (Y20 = 'Points-Table'!$A$10), 'Points-Table'!$C$10, (Y20 = 'Points-Table'!$A$11), 'Points-Table'!$C$11, (Y20 = 'Points-Table'!$A$12), 'Points-Table'!$C$12, (Y20 = 'Points-Table'!$A$13), 'Points-Table'!$C$13, true, 0 ) | AA20: =SUM(V20,X20,Z20) | AB20: =Ifs( ISBETWEEN(AA20, 0, 'Points-Table'!C$20, TRUE, False), 'Points-Table'!A$20, ISBETWEEN(AA20, 'Points-Table'!C$20, 'Points-Table'!C$21, TRUE, False), 'Points-Table'!A$21, ISBETWEEN(AA20, 'Points-Table'!C$22, 10000, TRUE, TRUE), 'Points-Table'!A$22, true, 0)
A21: Hotels List & Booking Flow | B21: View Hotel details | C21: Booking and refund policies | K21: Simple | L21: Must Have | R21: =Ifs( (Q21 = 'Points-Table'!$A$4), 'Points-Table'!$C$4, (Q21 = 'Points-Table'!$A$5), 'Points-Table'!$C$5, (Q21 = 'Points-Table'!$A$6), 'Points-Table'!$C$6, (Q21 = 'Points-Table'!$A$7), 'Points-Table'!$C$7, (Q21 = 'Points-Table'!$A$8), 'Points-Table'!$C$8, (Q21 = 'Points-Table'!$A$9), 'Points-Table'!$C$9, (Q21 = 'Points-Table'!$A$10), 'Points-Table'!$C$10, (Q21 = 'Points-Table'!$A$11), 'Points-Table'!$C$11, (Q21 = 'Points-Table'!$A$12), 'Points-Table'!$C$12, (Q21 = 'Points-Table'!$A$13), 'Points-Table'!$C$13, true, 0 ) | T21: =Ifs( (S21 = 'Points-Table'!$A$4), 'Points-Table'!$C$4, (S21 = 'Points-Table'!$A$5), 'Points-Table'!$C$5, (S21 = 'Points-Table'!$A$6), 'Points-Table'!$C$6, (S21 = 'Points-Table'!$A$7), 'Points-Table'!$C$7, (S21 = 'Points-Table'!$A$8), 'Points-Table'!$C$8, (S21 = 'Points-Table'!$A$9), 'Points-Table'!$C$9, (S21 = 'Points-Table'!$A$10), 'Points-Table'!$C$10, (S21 = 'Points-Table'!$A$11), 'Points-Table'!$C$11, (S21 = 'Points-Table'!$A$12), 'Points-Table'!$C$12, (S21 = 'Points-Table'!$A$13), 'Points-Table'!$C$13, true, 0 ) | U21: 3 | V21: =Ifs( (U21 = 'Points-Table'!$A$4), 'Points-Table'!$C$4, (U21 = 'Points-Table'!$A$5), 'Points-Table'!$C$5, (U21 = 'Points-Table'!$A$6), 'Points-Table'!$C$6, (U21 = 'Points-Table'!$A$7), 'Points-Table'!$C$7, (U21 = 'Points-Table'!$A$8), 'Points-Table'!$C$8, (U21 = 'Points-Table'!$A$9), 'Points-Table'!$C$9, (U21 = 'Points-Table'!$A$10), 'Points-Table'!$C$10, (U21 = 'Points-Table'!$A$11), 'Points-Table'!$C$11, (U21 = 'Points-Table'!$A$12), 'Points-Table'!$C$12, (U21 = 'Points-Table'!$A$13), 'Points-Table'!$C$13, true, 0 ) | W21: 1 | X21: =Ifs( (W21 = 'Points-Table'!$A$4), 'Points-Table'!$C$4, (W21 = 'Points-Table'!$A$5), 'Points-Table'!$C$5, (W21 = 'Points-Table'!$A$6), 'Points-Table'!$C$6, (W21 = 'Points-Table'!$A$7), 'Points-Table'!$C$7, (W21 = 'Points-Table'!$A$8), 'Points-Table'!$C$8, (W21 = 'Points-Table'!$A$9), 'Points-Table'!$C$9, (W21 = 'Points-Table'!$A$10), 'Points-Table'!$C$10, (W21 = 'Points-Table'!$A$11), 'Points-Table'!$C$11, (W21 = 'Points-Table'!$A$12), 'Points-Table'!$C$12, (W21 = 'Points-Table'!$A$13), 'Points-Table'!$C$13, true, 0 ) | Y21: 0 | Z21: =Ifs( (Y21 = 'Points-Table'!$A$4), 'Points-Table'!$C$4, (Y21 = 'Points-Table'!$A$5), 'Points-Table'!$C$5, (Y21 = 'Points-Table'!$A$6), 'Points-Table'!$C$6, (Y21 = 'Points-Table'!$A$7), 'Points-Table'!$C$7, (Y21 = 'Points-Table'!$A$8), 'Points-Table'!$C$8, (Y21 = 'Points-Table'!$A$9), 'Points-Table'!$C$9, (Y21 = 'Points-Table'!$A$10), 'Points-Table'!$C$10, (Y21 = 'Points-Table'!$A$11), 'Points-Table'!$C$11, (Y21 = 'Points-Table'!$A$12), 'Points-Table'!$C$12, (Y21 = 'Points-Table'!$A$13), 'Points-Table'!$C$13, true, 0 ) | AA21: =SUM(V21,X21,Z21) | AB21: =Ifs( ISBETWEEN(AA21, 0, 'Points-Table'!C$20, TRUE, False), 'Points-Table'!A$20, ISBETWEEN(AA21, 'Points-Table'!C$20, 'Points-Table'!C$21, TRUE, False), 'Points-Table'!A$21, ISBETWEEN(AA21, 'Points-Table'!C$22, 10000, TRUE, TRUE), 'Points-Table'!A$22, true, 0)
A22: Hotels List & Booking Flow | B22: Booking Flow | C22: Select the room type + Checkin/checkout dates + count of rooms | K22: Simple | L22: Must Have | Q22: 1 | R22: =Ifs( (Q22 = 'Points-Table'!$A$4), 'Points-Table'!$C$4, (Q22 = 'Points-Table'!$A$5), 'Points-Table'!$C$5, (Q22 = 'Points-Table'!$A$6), 'Points-Table'!$C$6, (Q22 = 'Points-Table'!$A$7), 'Points-Table'!$C$7, (Q22 = 'Points-Table'!$A$8), 'Points-Table'!$C$8, (Q22 = 'Points-Table'!$A$9), 'Points-Table'!$C$9, (Q22 = 'Points-Table'!$A$10), 'Points-Table'!$C$10, (Q22 = 'Points-Table'!$A$11), 'Points-Table'!$C$11, (Q22 = 'Points-Table'!$A$12), 'Points-Table'!$C$12, (Q22 = 'Points-Table'!$A$13), 'Points-Table'!$C$13, true, 0 ) | S22: 1 | T22: =Ifs( (S22 = 'Points-Table'!$A$4), 'Points-Table'!$C$4, (S22 = 'Points-Table'!$A$5), 'Points-Table'!$C$5, (S22 = 'Points-Table'!$A$6), 'Points-Table'!$C$6, (S22 = 'Points-Table'!$A$7), 'Points-Table'!$C$7, (S22 = 'Points-Table'!$A$8), 'Points-Table'!$C$8, (S22 = 'Points-Table'!$A$9), 'Points-Table'!$C$9, (S22 = 'Points-Table'!$A$10), 'Points-Table'!$C$10, (S22 = 'Points-Table'!$A$11), 'Points-Table'!$C$11, (S22 = 'Points-Table'!$A$12), 'Points-Table'!$C$12, (S22 = 'Points-Table'!$A$13), 'Points-Table'!$C$13, true, 0 ) | U22: 5 | V22: =Ifs( (U22 = 'Points-Table'!$A$4), 'Points-Table'!$C$4, (U22 = 'Points-Table'!$A$5), 'Points-Table'!$C$5, (U22 = 'Points-Table'!$A$6), 'Points-Table'!$C$6, (U22 = 'Points-Table'!$A$7), 'Points-Table'!$C$7, (U22 = 'Points-Table'!$A$8), 'Points-Table'!$C$8, (U22 = 'Points-Table'!$A$9), 'Points-Table'!$C$9, (U22 = 'Points-Table'!$A$10), 'Points-Table'!$C$10, (U22 = 'Points-Table'!$A$11), 'Points-Table'!$C$11, (U22 = 'Points-Table'!$A$12), 'Points-Table'!$C$12, (U22 = 'Points-Table'!$A$13), 'Points-Table'!$C$13, true, 0 ) | W22: 5 | X22: =Ifs( (W22 = 'Points-Table'!$A$4), 'Points-Table'!$C$4, (W22 = 'Points-Table'!$A$5), 'Points-Table'!$C$5, (W22 = 'Points-Table'!$A$6), 'Points-Table'!$C$6, (W22 = 'Points-Table'!$A$7), 'Points-Table'!$C$7, (W22 = 'Points-Table'!$A$8), 'Points-Table'!$C$8, (W22 = 'Points-Table'!$A$9), 'Points-Table'!$C$9, (W22 = 'Points-Table'!$A$10), 'Points-Table'!$C$10, (W22 = 'Points-Table'!$A$11), 'Points-Table'!$C$11, (W22 = 'Points-Table'!$A$12), 'Points-Table'!$C$12, (W22 = 'Points-Table'!$A$13), 'Points-Table'!$C$13, true, 0 ) | Y22: 8 | Z22: =Ifs( (Y22 = 'Points-Table'!$A$4), 'Points-Table'!$C$4, (Y22 = 'Points-Table'!$A$5), 'Points-Table'!$C$5, (Y22 = 'Points-Table'!$A$6), 'Points-Table'!$C$6, (Y22 = 'Points-Table'!$A$7), 'Points-Table'!$C$7, (Y22 = 'Points-Table'!$A$8), 'Points-Table'!$C$8, (Y22 = 'Points-Table'!$A$9), 'Points-Table'!$C$9, (Y22 = 'Points-Table'!$A$10), 'Points-Table'!$C$10, (Y22 = 'Points-Table'!$A$11), 'Points-Table'!$C$11, (Y22 = 'Points-Table'!$A$12), 'Points-Table'!$C$12, (Y22 = 'Points-Table'!$A$13), 'Points-Table'!$C$13, true, 0 ) | AA22: =SUM(V22,X22,Z22) | AB22: =Ifs( ISBETWEEN(AA22, 0, 'Points-Table'!C$20, TRUE, False), 'Points-Table'!A$20, ISBETWEEN(AA22, 'Points-Table'!C$20, 'Points-Table'!C$21, TRUE, False), 'Points-Table'!A$21, ISBETWEEN(AA22, 'Points-Table'!C$22, 10000, TRUE, TRUE), 'Points-Table'!A$22, true, 0)
A23: Hotels List & Booking Flow | B23: Booking Flow | C23: Preview Summary View | K23: Simple | L23: Must Have | R23: =Ifs( (Q23 = 'Points-Table'!$A$4), 'Points-Table'!$C$4, (Q23 = 'Points-Table'!$A$5), 'Points-Table'!$C$5, (Q23 = 'Points-Table'!$A$6), 'Points-Table'!$C$6, (Q23 = 'Points-Table'!$A$7), 'Points-Table'!$C$7, (Q23 = 'Points-Table'!$A$8), 'Points-Table'!$C$8, (Q23 = 'Points-Table'!$A$9), 'Points-Table'!$C$9, (Q23 = 'Points-Table'!$A$10), 'Points-Table'!$C$10, (Q23 = 'Points-Table'!$A$11), 'Points-Table'!$C$11, (Q23 = 'Points-Table'!$A$12), 'Points-Table'!$C$12, (Q23 = 'Points-Table'!$A$13), 'Points-Table'!$C$13, true, 0 ) | T23: =Ifs( (S23 = 'Points-Table'!$A$4), 'Points-Table'!$C$4, (S23 = 'Points-Table'!$A$5), 'Points-Table'!$C$5, (S23 = 'Points-Table'!$A$6), 'Points-Table'!$C$6, (S23 = 'Points-Table'!$A$7), 'Points-Table'!$C$7, (S23 = 'Points-Table'!$A$8), 'Points-Table'!$C$8, (S23 = 'Points-Table'!$A$9), 'Points-Table'!$C$9, (S23 = 'Points-Table'!$A$10), 'Points-Table'!$C$10, (S23 = 'Points-Table'!$A$11), 'Points-Table'!$C$11, (S23 = 'Points-Table'!$A$12), 'Points-Table'!$C$12, (S23 = 'Points-Table'!$A$13), 'Points-Table'!$C$13, true, 0 ) | U23: 3 | V23: =Ifs( (U23 = 'Points-Table'!$A$4), 'Points-Table'!$C$4, (U23 = 'Points-Table'!$A$5), 'Points-Table'!$C$5, (U23 = 'Points-Table'!$A$6), 'Points-Table'!$C$6, (U23 = 'Points-Table'!$A$7), 'Points-Table'!$C$7, (U23 = 'Points-Table'!$A$8), 'Points-Table'!$C$8, (U23 = 'Points-Table'!$A$9), 'Points-Table'!$C$9, (U23 = 'Points-Table'!$A$10), 'Points-Table'!$C$10, (U23 = 'Points-Table'!$A$11), 'Points-Table'!$C$11, (U23 = 'Points-Table'!$A$12), 'Points-Table'!$C$12, (U23 = 'Points-Table'!$A$13), 'Points-Table'!$C$13, true, 0 ) | W23: 0 | X23: =Ifs( (W23 = 'Points-Table'!$A$4), 'Points-Table'!$C$4, (W23 = 'Points-Table'!$A$5), 'Points-Table'!$C$5, (W23 = 'Points-Table'!$A$6), 'Points-Table'!$C$6, (W23 = 'Points-Table'!$A$7), 'Points-Table'!$C$7, (W23 = 'Points-Table'!$A$8), 'Points-Table'!$C$8, (W23 = 'Points-Table'!$A$9), 'Points-Table'!$C$9, (W23 = 'Points-Table'!$A$10), 'Points-Table'!$C$10, (W23 = 'Points-Table'!$A$11), 'Points-Table'!$C$11, (W23 = 'Points-Table'!$A$12), 'Points-Table'!$C$12, (W23 = 'Points-Table'!$A$13), 'Points-Table'!$C$13, true, 0 ) | Y23: 0 | Z23: =Ifs( (Y23 = 'Points-Table'!$A$4), 'Points-Table'!$C$4, (Y23 = 'Points-Table'!$A$5), 'Points-Table'!$C$5, (Y23 = 'Points-Table'!$A$6), 'Points-Table'!$C$6, (Y23 = 'Points-Table'!$A$7), 'Points-Table'!$C$7, (Y23 = 'Points-Table'!$A$8), 'Points-Table'!$C$8, (Y23 = 'Points-Table'!$A$9), 'Points-Table'!$C$9, (Y23 = 'Points-Table'!$A$10), 'Points-Table'!$C$10, (Y23 = 'Points-Table'!$A$11), 'Points-Table'!$C$11, (Y23 = 'Points-Table'!$A$12), 'Points-Table'!$C$12, (Y23 = 'Points-Table'!$A$13), 'Points-Table'!$C$13, true, 0 ) | AA23: =SUM(V23,X23,Z23) | AB23: =Ifs( ISBETWEEN(AA23, 0, 'Points-Table'!C$20, TRUE, False), 'Points-Table'!A$20, ISBETWEEN(AA23, 'Points-Table'!C$20, 'Points-Table'!C$21, TRUE, False), 'Points-Table'!A$21, ISBETWEEN(AA23, 'Points-Table'!C$22, 10000, TRUE, TRUE), 'Points-Table'!A$22, true, 0)
A24: Hotels List & Booking Flow | B24: Booking Flow | C24: Summary Page & modify the current booking state | F24: frontend state management will be done here | K24: Simple | L24: Must Have | R24: =Ifs( (Q24 = 'Points-Table'!$A$4), 'Points-Table'!$C$4, (Q24 = 'Points-Table'!$A$5), 'Points-Table'!$C$5, (Q24 = 'Points-Table'!$A$6), 'Points-Table'!$C$6, (Q24 = 'Points-Table'!$A$7), 'Points-Table'!$C$7, (Q24 = 'Points-Table'!$A$8), 'Points-Table'!$C$8, (Q24 = 'Points-Table'!$A$9), 'Points-Table'!$C$9, (Q24 = 'Points-Table'!$A$10), 'Points-Table'!$C$10, (Q24 = 'Points-Table'!$A$11), 'Points-Table'!$C$11, (Q24 = 'Points-Table'!$A$12), 'Points-Table'!$C$12, (Q24 = 'Points-Table'!$A$13), 'Points-Table'!$C$13, true, 0 ) | T24: =Ifs( (S24 = 'Points-Table'!$A$4), 'Points-Table'!$C$4, (S24 = 'Points-Table'!$A$5), 'Points-Table'!$C$5, (S24 = 'Points-Table'!$A$6), 'Points-Table'!$C$6, (S24 = 'Points-Table'!$A$7), 'Points-Table'!$C$7, (S24 = 'Points-Table'!$A$8), 'Points-Table'!$C$8, (S24 = 'Points-Table'!$A$9), 'Points-Table'!$C$9, (S24 = 'Points-Table'!$A$10), 'Points-Table'!$C$10, (S24 = 'Points-Table'!$A$11), 'Points-Table'!$C$11, (S24 = 'Points-Table'!$A$12), 'Points-Table'!$C$12, (S24 = 'Points-Table'!$A$13), 'Points-Table'!$C$13, true, 0 ) | U24: 8 | V24: =Ifs( (U24 = 'Points-Table'!$A$4), 'Points-Table'!$C$4, (U24 = 'Points-Table'!$A$5), 'Points-Table'!$C$5, (U24 = 'Points-Table'!$A$6), 'Points-Table'!$C$6, (U24 = 'Points-Table'!$A$7), 'Points-Table'!$C$7, (U24 = 'Points-Table'!$A$8), 'Points-Table'!$C$8, (U24 = 'Points-Table'!$A$9), 'Points-Table'!$C$9, (U24 = 'Points-Table'!$A$10), 'Points-Table'!$C$10, (U24 = 'Points-Table'!$A$11), 'Points-Table'!$C$11, (U24 = 'Points-Table'!$A$12), 'Points-Table'!$C$12, (U24 = 'Points-Table'!$A$13), 'Points-Table'!$C$13, true, 0 ) | W24: 0 | X24: =Ifs( (W24 = 'Points-Table'!$A$4), 'Points-Table'!$C$4, (W24 = 'Points-Table'!$A$5), 'Points-Table'!$C$5, (W24 = 'Points-Table'!$A$6), 'Points-Table'!$C$6, (W24 = 'Points-Table'!$A$7), 'Points-Table'!$C$7, (W24 = 'Points-Table'!$A$8), 'Points-Table'!$C$8, (W24 = 'Points-Table'!$A$9), 'Points-Table'!$C$9, (W24 = 'Points-Table'!$A$10), 'Points-Table'!$C$10, (W24 = 'Points-Table'!$A$11), 'Points-Table'!$C$11, (W24 = 'Points-Table'!$A$12), 'Points-Table'!$C$12, (W24 = 'Points-Table'!$A$13), 'Points-Table'!$C$13, true, 0 ) | Y24: 0 | Z24: =Ifs( (Y24 = 'Points-Table'!$A$4), 'Points-Table'!$C$4, (Y24 = 'Points-Table'!$A$5), 'Points-Table'!$C$5, (Y24 = 'Points-Table'!$A$6), 'Points-Table'!$C$6, (Y24 = 'Points-Table'!$A$7), 'Points-Table'!$C$7, (Y24 = 'Points-Table'!$A$8), 'Points-Table'!$C$8, (Y24 = 'Points-Table'!$A$9), 'Points-Table'!$C$9, (Y24 = 'Points-Table'!$A$10), 'Points-Table'!$C$10, (Y24 = 'Points-Table'!$A$11), 'Points-Table'!$C$11, (Y24 = 'Points-Table'!$A$12), 'Points-Table'!$C$12, (Y24 = 'Points-Table'!$A$13), 'Points-Table'!$C$13, true, 0 ) | AA24: =SUM(V24,X24,Z24) | AB24: =Ifs( ISBETWEEN(AA24, 0, 'Points-Table'!C$20, TRUE, False), 'Points-Table'!A$20, ISBETWEEN(AA24, 'Points-Table'!C$20, 'Points-Table'!C$21, TRUE, False), 'Points-Table'!A$21, ISBETWEEN(AA24, 'Points-Table'!C$22, 10000, TRUE, TRUE), 'Points-Table'!A$22, true, 0)
A25: Hotels List & Booking Flow | B25: Booking Flow | C25: Add Guest | K25: Simple | L25: Must Have | Q25: 1 | R25: =Ifs( (Q25 = 'Points-Table'!$A$4), 'Points-Table'!$C$4, (Q25 = 'Points-Table'!$A$5), 'Points-Table'!$C$5, (Q25 = 'Points-Table'!$A$6), 'Points-Table'!$C$6, (Q25 = 'Points-Table'!$A$7), 'Points-Table'!$C$7, (Q25 = 'Points-Table'!$A$8), 'Points-Table'!$C$8, (Q25 = 'Points-Table'!$A$9), 'Points-Table'!$C$9, (Q25 = 'Points-Table'!$A$10), 'Points-Table'!$C$10, (Q25 = 'Points-Table'!$A$11), 'Points-Table'!$C$11, (Q25 = 'Points-Table'!$A$12), 'Points-Table'!$C$12, (Q25 = 'Points-Table'!$A$13), 'Points-Table'!$C$13, true, 0 ) | S25: 1 | T25: =Ifs( (S25 = 'Points-Table'!$A$4), 'Points-Table'!$C$4, (S25 = 'Points-Table'!$A$5), 'Points-Table'!$C$5, (S25 = 'Points-Table'!$A$6), 'Points-Table'!$C$6, (S25 = 'Points-Table'!$A$7), 'Points-Table'!$C$7, (S25 = 'Points-Table'!$A$8), 'Points-Table'!$C$8, (S25 = 'Points-Table'!$A$9), 'Points-Table'!$C$9, (S25 = 'Points-Table'!$A$10), 'Points-Table'!$C$10, (S25 = 'Points-Table'!$A$11), 'Points-Table'!$C$11, (S25 = 'Points-Table'!$A$12), 'Points-Table'!$C$12, (S25 = 'Points-Table'!$A$13), 'Points-Table'!$C$13, true, 0 ) | U25: 5 | V25: =Ifs( (U25 = 'Points-Table'!$A$4), 'Points-Table'!$C$4, (U25 = 'Points-Table'!$A$5), 'Points-Table'!$C$5, (U25 = 'Points-Table'!$A$6), 'Points-Table'!$C$6, (U25 = 'Points-Table'!$A$7), 'Points-Table'!$C$7, (U25 = 'Points-Table'!$A$8), 'Points-Table'!$C$8, (U25 = 'Points-Table'!$A$9), 'Points-Table'!$C$9, (U25 = 'Points-Table'!$A$10), 'Points-Table'!$C$10, (U25 = 'Points-Table'!$A$11), 'Points-Table'!$C$11, (U25 = 'Points-Table'!$A$12), 'Points-Table'!$C$12, (U25 = 'Points-Table'!$A$13), 'Points-Table'!$C$13, true, 0 ) | W25: 3 | X25: =Ifs( (W25 = 'Points-Table'!$A$4), 'Points-Table'!$C$4, (W25 = 'Points-Table'!$A$5), 'Points-Table'!$C$5, (W25 = 'Points-Table'!$A$6), 'Points-Table'!$C$6, (W25 = 'Points-Table'!$A$7), 'Points-Table'!$C$7, (W25 = 'Points-Table'!$A$8), 'Points-Table'!$C$8, (W25 = 'Points-Table'!$A$9), 'Points-Table'!$C$9, (W25 = 'Points-Table'!$A$10), 'Points-Table'!$C$10, (W25 = 'Points-Table'!$A$11), 'Points-Table'!$C$11, (W25 = 'Points-Table'!$A$12), 'Points-Table'!$C$12, (W25 = 'Points-Table'!$A$13), 'Points-Table'!$C$13, true, 0 ) | Y25: 5 | Z25: =Ifs( (Y25 = 'Points-Table'!$A$4), 'Points-Table'!$C$4, (Y25 = 'Points-Table'!$A$5), 'Points-Table'!$C$5, (Y25 = 'Points-Table'!$A$6), 'Points-Table'!$C$6, (Y25 = 'Points-Table'!$A$7), 'Points-Table'!$C$7, (Y25 = 'Points-Table'!$A$8), 'Points-Table'!$C$8, (Y25 = 'Points-Table'!$A$9), 'Points-Table'!$C$9, (Y25 = 'Points-Table'!$A$10), 'Points-Table'!$C$10, (Y25 = 'Points-Table'!$A$11), 'Points-Table'!$C$11, (Y25 = 'Points-Table'!$A$12), 'Points-Table'!$C$12, (Y25 = 'Points-Table'!$A$13), 'Points-Table'!$C$13, true, 0 ) | AA25: =SUM(V25,X25,Z25) | AB25: =Ifs( ISBETWEEN(AA25, 0, 'Points-Table'!C$20, TRUE, False), 'Points-Table'!A$20, ISBETWEEN(AA25, 'Points-Table'!C$20, 'Points-Table'!C$21, TRUE, False), 'Points-Table'!A$21, ISBETWEEN(AA25, 'Points-Table'!C$22, 10000, TRUE, TRUE), 'Points-Table'!A$22, true, 0)
A26: Hotels List & Booking Flow | B26: Booking Flow | C26: Review Policies | K26: Simple | L26: Must Have | R26: =Ifs( (Q26 = 'Points-Table'!$A$4), 'Points-Table'!$C$4, (Q26 = 'Points-Table'!$A$5), 'Points-Table'!$C$5, (Q26 = 'Points-Table'!$A$6), 'Points-Table'!$C$6, (Q26 = 'Points-Table'!$A$7), 'Points-Table'!$C$7, (Q26 = 'Points-Table'!$A$8), 'Points-Table'!$C$8, (Q26 = 'Points-Table'!$A$9), 'Points-Table'!$C$9, (Q26 = 'Points-Table'!$A$10), 'Points-Table'!$C$10, (Q26 = 'Points-Table'!$A$11), 'Points-Table'!$C$11, (Q26 = 'Points-Table'!$A$12), 'Points-Table'!$C$12, (Q26 = 'Points-Table'!$A$13), 'Points-Table'!$C$13, true, 0 ) | T26: =Ifs( (S26 = 'Points-Table'!$A$4), 'Points-Table'!$C$4, (S26 = 'Points-Table'!$A$5), 'Points-Table'!$C$5, (S26 = 'Points-Table'!$A$6), 'Points-Table'!$C$6, (S26 = 'Points-Table'!$A$7), 'Points-Table'!$C$7, (S26 = 'Points-Table'!$A$8), 'Points-Table'!$C$8, (S26 = 'Points-Table'!$A$9), 'Points-Table'!$C$9, (S26 = 'Points-Table'!$A$10), 'Points-Table'!$C$10, (S26 = 'Points-Table'!$A$11), 'Points-Table'!$C$11, (S26 = 'Points-Table'!$A$12), 'Points-Table'!$C$12, (S26 = 'Points-Table'!$A$13), 'Points-Table'!$C$13, true, 0 ) | U26: 5 | V26: =Ifs( (U26 = 'Points-Table'!$A$4), 'Points-Table'!$C$4, (U26 = 'Points-Table'!$A$5), 'Points-Table'!$C$5, (U26 = 'Points-Table'!$A$6), 'Points-Table'!$C$6, (U26 = 'Points-Table'!$A$7), 'Points-Table'!$C$7, (U26 = 'Points-Table'!$A$8), 'Points-Table'!$C$8, (U26 = 'Points-Table'!$A$9), 'Points-Table'!$C$9, (U26 = 'Points-Table'!$A$10), 'Points-Table'!$C$10, (U26 = 'Points-Table'!$A$11), 'Points-Table'!$C$11, (U26 = 'Points-Table'!$A$12), 'Points-Table'!$C$12, (U26 = 'Points-Table'!$A$13), 'Points-Table'!$C$13, true, 0 ) | W26: 2 | X26: =Ifs( (W26 = 'Points-Table'!$A$4), 'Points-Table'!$C$4, (W26 = 'Points-Table'!$A$5), 'Points-Table'!$C$5, (W26 = 'Points-Table'!$A$6), 'Points-Table'!$C$6, (W26 = 'Points-Table'!$A$7), 'Points-Table'!$C$7, (W26 = 'Points-Table'!$A$8), 'Points-Table'!$C$8, (W26 = 'Points-Table'!$A$9), 'Points-Table'!$C$9, (W26 = 'Points-Table'!$A$10), 'Points-Table'!$C$10, (W26 = 'Points-Table'!$A$11), 'Points-Table'!$C$11, (W26 = 'Points-Table'!$A$12), 'Points-Table'!$C$12, (W26 = 'Points-Table'!$A$13), 'Points-Table'!$C$13, true, 0 ) | Y26: 3 | Z26: =Ifs( (Y26 = 'Points-Table'!$A$4), 'Points-Table'!$C$4, (Y26 = 'Points-Table'!$A$5), 'Points-Table'!$C$5, (Y26 = 'Points-Table'!$A$6), 'Points-Table'!$C$6, (Y26 = 'Points-Table'!$A$7), 'Points-Table'!$C$7, (Y26 = 'Points-Table'!$A$8), 'Points-Table'!$C$8, (Y26 = 'Points-Table'!$A$9), 'Points-Table'!$C$9, (Y26 = 'Points-Table'!$A$10), 'Points-Table'!$C$10, (Y26 = 'Points-Table'!$A$11), 'Points-Table'!$C$11, (Y26 = 'Points-Table'!$A$12), 'Points-Table'!$C$12, (Y26 = 'Points-Table'!$A$13), 'Points-Table'!$C$13, true, 0 ) | AA26: =SUM(V26,X26,Z26) | AB26: =Ifs( ISBETWEEN(AA26, 0, 'Points-Table'!C$20, TRUE, False), 'Points-Table'!A$20, ISBETWEEN(AA26, 'Points-Table'!C$20, 'Points-Table'!C$21, TRUE, False), 'Points-Table'!A$21, ISBETWEEN(AA26, 'Points-Table'!C$22, 10000, TRUE, TRUE), 'Points-Table'!A$22, true, 0)
A27: Hotels List & Booking Flow | B27: Booking Flow | C27: Payment View - Bills and taxes(add to cart type) | F27: add to cart api, inventory lock/release mechanism api to use here | K27: Simple | L27: Must Have | R27: =Ifs( (Q27 = 'Points-Table'!$A$4), 'Points-Table'!$C$4, (Q27 = 'Points-Table'!$A$5), 'Points-Table'!$C$5, (Q27 = 'Points-Table'!$A$6), 'Points-Table'!$C$6, (Q27 = 'Points-Table'!$A$7), 'Points-Table'!$C$7, (Q27 = 'Points-Table'!$A$8), 'Points-Table'!$C$8, (Q27 = 'Points-Table'!$A$9), 'Points-Table'!$C$9, (Q27 = 'Points-Table'!$A$10), 'Points-Table'!$C$10, (Q27 = 'Points-Table'!$A$11), 'Points-Table'!$C$11, (Q27 = 'Points-Table'!$A$12), 'Points-Table'!$C$12, (Q27 = 'Points-Table'!$A$13), 'Points-Table'!$C$13, true, 0 ) | T27: =Ifs( (S27 = 'Points-Table'!$A$4), 'Points-Table'!$C$4, (S27 = 'Points-Table'!$A$5), 'Points-Table'!$C$5, (S27 = 'Points-Table'!$A$6), 'Points-Table'!$C$6, (S27 = 'Points-Table'!$A$7), 'Points-Table'!$C$7, (S27 = 'Points-Table'!$A$8), 'Points-Table'!$C$8, (S27 = 'Points-Table'!$A$9), 'Points-Table'!$C$9, (S27 = 'Points-Table'!$A$10), 'Points-Table'!$C$10, (S27 = 'Points-Table'!$A$11), 'Points-Table'!$C$11, (S27 = 'Points-Table'!$A$12), 'Points-Table'!$C$12, (S27 = 'Points-Table'!$A$13), 'Points-Table'!$C$13, true, 0 ) | U27: 5 | V27: =Ifs( (U27 = 'Points-Table'!$A$4), 'Points-Table'!$C$4, (U27 = 'Points-Table'!$A$5), 'Points-Table'!$C$5, (U27 = 'Points-Table'!$A$6), 'Points-Table'!$C$6, (U27 = 'Points-Table'!$A$7), 'Points-Table'!$C$7, (U27 = 'Points-Table'!$A$8), 'Points-Table'!$C$8, (U27 = 'Points-Table'!$A$9), 'Points-Table'!$C$9, (U27 = 'Points-Table'!$A$10), 'Points-Table'!$C$10, (U27 = 'Points-Table'!$A$11), 'Points-Table'!$C$11, (U27 = 'Points-Table'!$A$12), 'Points-Table'!$C$12, (U27 = 'Points-Table'!$A$13), 'Points-Table'!$C$13, true, 0 ) | W27: 3 | X27: =Ifs( (W27 = 'Points-Table'!$A$4), 'Points-Table'!$C$4, (W27 = 'Points-Table'!$A$5), 'Points-Table'!$C$5, (W27 = 'Points-Table'!$A$6), 'Points-Table'!$C$6, (W27 = 'Points-Table'!$A$7), 'Points-Table'!$C$7, (W27 = 'Points-Table'!$A$8), 'Points-Table'!$C$8, (W27 = 'Points-Table'!$A$9), 'Points-Table'!$C$9, (W27 = 'Points-Table'!$A$10), 'Points-Table'!$C$10, (W27 = 'Points-Table'!$A$11), 'Points-Table'!$C$11, (W27 = 'Points-Table'!$A$12), 'Points-Table'!$C$12, (W27 = 'Points-Table'!$A$13), 'Points-Table'!$C$13, true, 0 ) | Y27: 8 | Z27: =Ifs( (Y27 = 'Points-Table'!$A$4), 'Points-Table'!$C$4, (Y27 = 'Points-Table'!$A$5), 'Points-Table'!$C$5, (Y27 = 'Points-Table'!$A$6), 'Points-Table'!$C$6, (Y27 = 'Points-Table'!$A$7), 'Points-Table'!$C$7, (Y27 = 'Points-Table'!$A$8), 'Points-Table'!$C$8, (Y27 = 'Points-Table'!$A$9), 'Points-Table'!$C$9, (Y27 = 'Points-Table'!$A$10), 'Points-Table'!$C$10, (Y27 = 'Points-Table'!$A$11), 'Points-Table'!$C$11, (Y27 = 'Points-Table'!$A$12), 'Points-Table'!$C$12, (Y27 = 'Points-Table'!$A$13), 'Points-Table'!$C$13, true, 0 ) | AA27: =SUM(V27,X27,Z27) | AB27: =Ifs( ISBETWEEN(AA27, 0, 'Points-Table'!C$20, TRUE, False), 'Points-Table'!A$20, ISBETWEEN(AA27, 'Points-Table'!C$20, 'Points-Table'!C$21, TRUE, False), 'Points-Table'!A$21, ISBETWEEN(AA27, 'Points-Table'!C$22, 10000, TRUE, TRUE), 'Points-Table'!A$22, true, 0)
A28: Hotels List & Booking Flow | B28: Booking Flow | C28: More details (Description) | D28: Collect necessary information about the guest (and any additional guests sharing the room). This includes name, contact information (phone, email), and possibly special requests (like dietary needs for breakfast or accessibility requests). User is logged in as an attendee, some details can be pre-filled from their profile to streamline the process. | F28: ? | K28: Simple | L28: Must Have | R28: =Ifs( (Q28 = 'Points-Table'!$A$4), 'Points-Table'!$C$4, (Q28 = 'Points-Table'!$A$5), 'Points-Table'!$C$5, (Q28 = 'Points-Table'!$A$6), 'Points-Table'!$C$6, (Q28 = 'Points-Table'!$A$7), 'Points-Table'!$C$7, (Q28 = 'Points-Table'!$A$8), 'Points-Table'!$C$8, (Q28 = 'Points-Table'!$A$9), 'Points-Table'!$C$9, (Q28 = 'Points-Table'!$A$10), 'Points-Table'!$C$10, (Q28 = 'Points-Table'!$A$11), 'Points-Table'!$C$11, (Q28 = 'Points-Table'!$A$12), 'Points-Table'!$C$12, (Q28 = 'Points-Table'!$A$13), 'Points-Table'!$C$13, true, 0 ) | T28: =Ifs( (S28 = 'Points-Table'!$A$4), 'Points-Table'!$C$4, (S28 = 'Points-Table'!$A$5), 'Points-Table'!$C$5, (S28 = 'Points-Table'!$A$6), 'Points-Table'!$C$6, (S28 = 'Points-Table'!$A$7), 'Points-Table'!$C$7, (S28 = 'Points-Table'!$A$8), 'Points-Table'!$C$8, (S28 = 'Points-Table'!$A$9), 'Points-Table'!$C$9, (S28 = 'Points-Table'!$A$10), 'Points-Table'!$C$10, (S28 = 'Points-Table'!$A$11), 'Points-Table'!$C$11, (S28 = 'Points-Table'!$A$12), 'Points-Table'!$C$12, (S28 = 'Points-Table'!$A$13), 'Points-Table'!$C$13, true, 0 ) | U28: 0 | V28: =Ifs( (U28 = 'Points-Table'!$A$4), 'Points-Table'!$C$4, (U28 = 'Points-Table'!$A$5), 'Points-Table'!$C$5, (U28 = 'Points-Table'!$A$6), 'Points-Table'!$C$6, (U28 = 'Points-Table'!$A$7), 'Points-Table'!$C$7, (U28 = 'Points-Table'!$A$8), 'Points-Table'!$C$8, (U28 = 'Points-Table'!$A$9), 'Points-Table'!$C$9, (U28 = 'Points-Table'!$A$10), 'Points-Table'!$C$10, (U28 = 'Points-Table'!$A$11), 'Points-Table'!$C$11, (U28 = 'Points-Table'!$A$12), 'Points-Table'!$C$12, (U28 = 'Points-Table'!$A$13), 'Points-Table'!$C$13, true, 0 ) | W28: 0 | X28: =Ifs( (W28 = 'Points-Table'!$A$4), 'Points-Table'!$C$4, (W28 = 'Points-Table'!$A$5), 'Points-Table'!$C$5, (W28 = 'Points-Table'!$A$6), 'Points-Table'!$C$6, (W28 = 'Points-Table'!$A$7), 'Points-Table'!$C$7, (W28 = 'Points-Table'!$A$8), 'Points-Table'!$C$8, (W28 = 'Points-Table'!$A$9), 'Points-Table'!$C$9, (W28 = 'Points-Table'!$A$10), 'Points-Table'!$C$10, (W28 = 'Points-Table'!$A$11), 'Points-Table'!$C$11, (W28 = 'Points-Table'!$A$12), 'Points-Table'!$C$12, (W28 = 'Points-Table'!$A$13), 'Points-Table'!$C$13, true, 0 ) | Y28: 0 | Z28: =Ifs( (Y28 = 'Points-Table'!$A$4), 'Points-Table'!$C$4, (Y28 = 'Points-Table'!$A$5), 'Points-Table'!$C$5, (Y28 = 'Points-Table'!$A$6), 'Points-Table'!$C$6, (Y28 = 'Points-Table'!$A$7), 'Points-Table'!$C$7, (Y28 = 'Points-Table'!$A$8), 'Points-Table'!$C$8, (Y28 = 'Points-Table'!$A$9), 'Points-Table'!$C$9, (Y28 = 'Points-Table'!$A$10), 'Points-Table'!$C$10, (Y28 = 'Points-Table'!$A$11), 'Points-Table'!$C$11, (Y28 = 'Points-Table'!$A$12), 'Points-Table'!$C$12, (Y28 = 'Points-Table'!$A$13), 'Points-Table'!$C$13, true, 0 ) | AA28: =SUM(V28,X28,Z28) | AB28: =Ifs( ISBETWEEN(AA28, 0, 'Points-Table'!C$20, TRUE, False), 'Points-Table'!A$20, ISBETWEEN(AA28, 'Points-Table'!C$20, 'Points-Table'!C$21, TRUE, False), 'Points-Table'!A$21, ISBETWEEN(AA28, 'Points-Table'!C$22, 10000, TRUE, TRUE), 'Points-Table'!A$22, true, 0)
A29: Hotels List & Booking Flow | B29: Booking Flow | C29: Select the Check-in and Check out dates | K29: Simple | L29: Must Have | Q29: 1 | R29: =Ifs( (Q29 = 'Points-Table'!$A$4), 'Points-Table'!$C$4, (Q29 = 'Points-Table'!$A$5), 'Points-Table'!$C$5, (Q29 = 'Points-Table'!$A$6), 'Points-Table'!$C$6, (Q29 = 'Points-Table'!$A$7), 'Points-Table'!$C$7, (Q29 = 'Points-Table'!$A$8), 'Points-Table'!$C$8, (Q29 = 'Points-Table'!$A$9), 'Points-Table'!$C$9, (Q29 = 'Points-Table'!$A$10), 'Points-Table'!$C$10, (Q29 = 'Points-Table'!$A$11), 'Points-Table'!$C$11, (Q29 = 'Points-Table'!$A$12), 'Points-Table'!$C$12, (Q29 = 'Points-Table'!$A$13), 'Points-Table'!$C$13, true, 0 ) | S29: 1 | T29: =Ifs( (S29 = 'Points-Table'!$A$4), 'Points-Table'!$C$4, (S29 = 'Points-Table'!$A$5), 'Points-Table'!$C$5, (S29 = 'Points-Table'!$A$6), 'Points-Table'!$C$6, (S29 = 'Points-Table'!$A$7), 'Points-Table'!$C$7, (S29 = 'Points-Table'!$A$8), 'Points-Table'!$C$8, (S29 = 'Points-Table'!$A$9), 'Points-Table'!$C$9, (S29 = 'Points-Table'!$A$10), 'Points-Table'!$C$10, (S29 = 'Points-Table'!$A$11), 'Points-Table'!$C$11, (S29 = 'Points-Table'!$A$12), 'Points-Table'!$C$12, (S29 = 'Points-Table'!$A$13), 'Points-Table'!$C$13, true, 0 ) | U29: 5 | V29: =Ifs( (U29 = 'Points-Table'!$A$4), 'Points-Table'!$C$4, (U29 = 'Points-Table'!$A$5), 'Points-Table'!$C$5, (U29 = 'Points-Table'!$A$6), 'Points-Table'!$C$6, (U29 = 'Points-Table'!$A$7), 'Points-Table'!$C$7, (U29 = 'Points-Table'!$A$8), 'Points-Table'!$C$8, (U29 = 'Points-Table'!$A$9), 'Points-Table'!$C$9, (U29 = 'Points-Table'!$A$10), 'Points-Table'!$C$10, (U29 = 'Points-Table'!$A$11), 'Points-Table'!$C$11, (U29 = 'Points-Table'!$A$12), 'Points-Table'!$C$12, (U29 = 'Points-Table'!$A$13), 'Points-Table'!$C$13, true, 0 ) | W29: 0 | X29: =Ifs( (W29 = 'Points-Table'!$A$4), 'Points-Table'!$C$4, (W29 = 'Points-Table'!$A$5), 'Points-Table'!$C$5, (W29 = 'Points-Table'!$A$6), 'Points-Table'!$C$6, (W29 = 'Points-Table'!$A$7), 'Points-Table'!$C$7, (W29 = 'Points-Table'!$A$8), 'Points-Table'!$C$8, (W29 = 'Points-Table'!$A$9), 'Points-Table'!$C$9, (W29 = 'Points-Table'!$A$10), 'Points-Table'!$C$10, (W29 = 'Points-Table'!$A$11), 'Points-Table'!$C$11, (W29 = 'Points-Table'!$A$12), 'Points-Table'!$C$12, (W29 = 'Points-Table'!$A$13), 'Points-Table'!$C$13, true, 0 ) | Y29: 0 | Z29: =Ifs( (Y29 = 'Points-Table'!$A$4), 'Points-Table'!$C$4, (Y29 = 'Points-Table'!$A$5), 'Points-Table'!$C$5, (Y29 = 'Points-Table'!$A$6), 'Points-Table'!$C$6, (Y29 = 'Points-Table'!$A$7), 'Points-Table'!$C$7, (Y29 = 'Points-Table'!$A$8), 'Points-Table'!$C$8, (Y29 = 'Points-Table'!$A$9), 'Points-Table'!$C$9, (Y29 = 'Points-Table'!$A$10), 'Points-Table'!$C$10, (Y29 = 'Points-Table'!$A$11), 'Points-Table'!$C$11, (Y29 = 'Points-Table'!$A$12), 'Points-Table'!$C$12, (Y29 = 'Points-Table'!$A$13), 'Points-Table'!$C$13, true, 0 ) | AA29: =SUM(V29,X29,Z29) | AB29: =Ifs( ISBETWEEN(AA29, 0, 'Points-Table'!C$20, TRUE, False), 'Points-Table'!A$20, ISBETWEEN(AA29, 'Points-Table'!C$20, 'Points-Table'!C$21, TRUE, False), 'Points-Table'!A$21, ISBETWEEN(AA29, 'Points-Table'!C$22, 10000, TRUE, TRUE), 'Points-Table'!A$22, true, 0)
A30: Hotels List & Booking Flow | B30: Bulk Booking | C30: Check in and check out date | K30: Simple | L30: Must Have | R30: =Ifs( (Q30 = 'Points-Table'!$A$4), 'Points-Table'!$C$4, (Q30 = 'Points-Table'!$A$5), 'Points-Table'!$C$5, (Q30 = 'Points-Table'!$A$6), 'Points-Table'!$C$6, (Q30 = 'Points-Table'!$A$7), 'Points-Table'!$C$7, (Q30 = 'Points-Table'!$A$8), 'Points-Table'!$C$8, (Q30 = 'Points-Table'!$A$9), 'Points-Table'!$C$9, (Q30 = 'Points-Table'!$A$10), 'Points-Table'!$C$10, (Q30 = 'Points-Table'!$A$11), 'Points-Table'!$C$11, (Q30 = 'Points-Table'!$A$12), 'Points-Table'!$C$12, (Q30 = 'Points-Table'!$A$13), 'Points-Table'!$C$13, true, 0 ) | T30: =Ifs( (S30 = 'Points-Table'!$A$4), 'Points-Table'!$C$4, (S30 = 'Points-Table'!$A$5), 'Points-Table'!$C$5, (S30 = 'Points-Table'!$A$6), 'Points-Table'!$C$6, (S30 = 'Points-Table'!$A$7), 'Points-Table'!$C$7, (S30 = 'Points-Table'!$A$8), 'Points-Table'!$C$8, (S30 = 'Points-Table'!$A$9), 'Points-Table'!$C$9, (S30 = 'Points-Table'!$A$10), 'Points-Table'!$C$10, (S30 = 'Points-Table'!$A$11), 'Points-Table'!$C$11, (S30 = 'Points-Table'!$A$12), 'Points-Table'!$C$12, (S30 = 'Points-Table'!$A$13), 'Points-Table'!$C$13, true, 0 ) | U30: 2 | V30: =Ifs( (U30 = 'Points-Table'!$A$4), 'Points-Table'!$C$4, (U30 = 'Points-Table'!$A$5), 'Points-Table'!$C$5, (U30 = 'Points-Table'!$A$6), 'Points-Table'!$C$6, (U30 = 'Points-Table'!$A$7), 'Points-Table'!$C$7, (U30 = 'Points-Table'!$A$8), 'Points-Table'!$C$8, (U30 = 'Points-Table'!$A$9), 'Points-Table'!$C$9, (U30 = 'Points-Table'!$A$10), 'Points-Table'!$C$10, (U30 = 'Points-Table'!$A$11), 'Points-Table'!$C$11, (U30 = 'Points-Table'!$A$12), 'Points-Table'!$C$12, (U30 = 'Points-Table'!$A$13), 'Points-Table'!$C$13, true, 0 ) | W30: 2 | X30: =Ifs( (W30 = 'Points-Table'!$A$4), 'Points-Table'!$C$4, (W30 = 'Points-Table'!$A$5), 'Points-Table'!$C$5, (W30 = 'Points-Table'!$A$6), 'Points-Table'!$C$6, (W30 = 'Points-Table'!$A$7), 'Points-Table'!$C$7, (W30 = 'Points-Table'!$A$8), 'Points-Table'!$C$8, (W30 = 'Points-Table'!$A$9), 'Points-Table'!$C$9, (W30 = 'Points-Table'!$A$10), 'Points-Table'!$C$10, (W30 = 'Points-Table'!$A$11), 'Points-Table'!$C$11, (W30 = 'Points-Table'!$A$12), 'Points-Table'!$C$12, (W30 = 'Points-Table'!$A$13), 'Points-Table'!$C$13, true, 0 ) | Y30: 3 | Z30: =Ifs( (Y30 = 'Points-Table'!$A$4), 'Points-Table'!$C$4, (Y30 = 'Points-Table'!$A$5), 'Points-Table'!$C$5, (Y30 = 'Points-Table'!$A$6), 'Points-Table'!$C$6, (Y30 = 'Points-Table'!$A$7), 'Points-Table'!$C$7, (Y30 = 'Points-Table'!$A$8), 'Points-Table'!$C$8, (Y30 = 'Points-Table'!$A$9), 'Points-Table'!$C$9, (Y30 = 'Points-Table'!$A$10), 'Points-Table'!$C$10, (Y30 = 'Points-Table'!$A$11), 'Points-Table'!$C$11, (Y30 = 'Points-Table'!$A$12), 'Points-Table'!$C$12, (Y30 = 'Points-Table'!$A$13), 'Points-Table'!$C$13, true, 0 ) | AA30: =SUM(V30,X30,Z30) | AB30: =Ifs( ISBETWEEN(AA30, 0, 'Points-Table'!C$20, TRUE, False), 'Points-Table'!A$20, ISBETWEEN(AA30, 'Points-Table'!C$20, 'Points-Table'!C$21, TRUE, False), 'Points-Table'!A$21, ISBETWEEN(AA30, 'Points-Table'!C$22, 10000, TRUE, TRUE), 'Points-Table'!A$22, true, 0)
A31: Hotels List & Booking Flow | B31: Bulk Booking | C31: Select room type | K31: Simple | L31: Must Have | R31: =Ifs( (Q31 = 'Points-Table'!$A$4), 'Points-Table'!$C$4, (Q31 = 'Points-Table'!$A$5), 'Points-Table'!$C$5, (Q31 = 'Points-Table'!$A$6), 'Points-Table'!$C$6, (Q31 = 'Points-Table'!$A$7), 'Points-Table'!$C$7, (Q31 = 'Points-Table'!$A$8), 'Points-Table'!$C$8, (Q31 = 'Points-Table'!$A$9), 'Points-Table'!$C$9, (Q31 = 'Points-Table'!$A$10), 'Points-Table'!$C$10, (Q31 = 'Points-Table'!$A$11), 'Points-Table'!$C$11, (Q31 = 'Points-Table'!$A$12), 'Points-Table'!$C$12, (Q31 = 'Points-Table'!$A$13), 'Points-Table'!$C$13, true, 0 ) | T31: =Ifs( (S31 = 'Points-Table'!$A$4), 'Points-Table'!$C$4, (S31 = 'Points-Table'!$A$5), 'Points-Table'!$C$5, (S31 = 'Points-Table'!$A$6), 'Points-Table'!$C$6, (S31 = 'Points-Table'!$A$7), 'Points-Table'!$C$7, (S31 = 'Points-Table'!$A$8), 'Points-Table'!$C$8, (S31 = 'Points-Table'!$A$9), 'Points-Table'!$C$9, (S31 = 'Points-Table'!$A$10), 'Points-Table'!$C$10, (S31 = 'Points-Table'!$A$11), 'Points-Table'!$C$11, (S31 = 'Points-Table'!$A$12), 'Points-Table'!$C$12, (S31 = 'Points-Table'!$A$13), 'Points-Table'!$C$13, true, 0 ) | U31: 2 | V31: =Ifs( (U31 = 'Points-Table'!$A$4), 'Points-Table'!$C$4, (U31 = 'Points-Table'!$A$5), 'Points-Table'!$C$5, (U31 = 'Points-Table'!$A$6), 'Points-Table'!$C$6, (U31 = 'Points-Table'!$A$7), 'Points-Table'!$C$7, (U31 = 'Points-Table'!$A$8), 'Points-Table'!$C$8, (U31 = 'Points-Table'!$A$9), 'Points-Table'!$C$9, (U31 = 'Points-Table'!$A$10), 'Points-Table'!$C$10, (U31 = 'Points-Table'!$A$11), 'Points-Table'!$C$11, (U31 = 'Points-Table'!$A$12), 'Points-Table'!$C$12, (U31 = 'Points-Table'!$A$13), 'Points-Table'!$C$13, true, 0 ) | W31: 2 | X31: =Ifs( (W31 = 'Points-Table'!$A$4), 'Points-Table'!$C$4, (W31 = 'Points-Table'!$A$5), 'Points-Table'!$C$5, (W31 = 'Points-Table'!$A$6), 'Points-Table'!$C$6, (W31 = 'Points-Table'!$A$7), 'Points-Table'!$C$7, (W31 = 'Points-Table'!$A$8), 'Points-Table'!$C$8, (W31 = 'Points-Table'!$A$9), 'Points-Table'!$C$9, (W31 = 'Points-Table'!$A$10), 'Points-Table'!$C$10, (W31 = 'Points-Table'!$A$11), 'Points-Table'!$C$11, (W31 = 'Points-Table'!$A$12), 'Points-Table'!$C$12, (W31 = 'Points-Table'!$A$13), 'Points-Table'!$C$13, true, 0 ) | Y31: 3 | Z31: =Ifs( (Y31 = 'Points-Table'!$A$4), 'Points-Table'!$C$4, (Y31 = 'Points-Table'!$A$5), 'Points-Table'!$C$5, (Y31 = 'Points-Table'!$A$6), 'Points-Table'!$C$6, (Y31 = 'Points-Table'!$A$7), 'Points-Table'!$C$7, (Y31 = 'Points-Table'!$A$8), 'Points-Table'!$C$8, (Y31 = 'Points-Table'!$A$9), 'Points-Table'!$C$9, (Y31 = 'Points-Table'!$A$10), 'Points-Table'!$C$10, (Y31 = 'Points-Table'!$A$11), 'Points-Table'!$C$11, (Y31 = 'Points-Table'!$A$12), 'Points-Table'!$C$12, (Y31 = 'Points-Table'!$A$13), 'Points-Table'!$C$13, true, 0 ) | AA31: =SUM(V31,X31,Z31) | AB31: =Ifs( ISBETWEEN(AA31, 0, 'Points-Table'!C$20, TRUE, False), 'Points-Table'!A$20, ISBETWEEN(AA31, 'Points-Table'!C$20, 'Points-Table'!C$21, TRUE, False), 'Points-Table'!A$21, ISBETWEEN(AA31, 'Points-Table'!C$22, 10000, TRUE, TRUE), 'Points-Table'!A$22, true, 0)
A32: Hotels List & Booking Flow | B32: Bulk Booking | C32: Reservation view | K32: Simple | L32: Must Have | R32: =Ifs( (Q32 = 'Points-Table'!$A$4), 'Points-Table'!$C$4, (Q32 = 'Points-Table'!$A$5), 'Points-Table'!$C$5, (Q32 = 'Points-Table'!$A$6), 'Points-Table'!$C$6, (Q32 = 'Points-Table'!$A$7), 'Points-Table'!$C$7, (Q32 = 'Points-Table'!$A$8), 'Points-Table'!$C$8, (Q32 = 'Points-Table'!$A$9), 'Points-Table'!$C$9, (Q32 = 'Points-Table'!$A$10), 'Points-Table'!$C$10, (Q32 = 'Points-Table'!$A$11), 'Points-Table'!$C$11, (Q32 = 'Points-Table'!$A$12), 'Points-Table'!$C$12, (Q32 = 'Points-Table'!$A$13), 'Points-Table'!$C$13, true, 0 ) | T32: =Ifs( (S32 = 'Points-Table'!$A$4), 'Points-Table'!$C$4, (S32 = 'Points-Table'!$A$5), 'Points-Table'!$C$5, (S32 = 'Points-Table'!$A$6), 'Points-Table'!$C$6, (S32 = 'Points-Table'!$A$7), 'Points-Table'!$C$7, (S32 = 'Points-Table'!$A$8), 'Points-Table'!$C$8, (S32 = 'Points-Table'!$A$9), 'Points-Table'!$C$9, (S32 = 'Points-Table'!$A$10), 'Points-Table'!$C$10, (S32 = 'Points-Table'!$A$11), 'Points-Table'!$C$11, (S32 = 'Points-Table'!$A$12), 'Points-Table'!$C$12, (S32 = 'Points-Table'!$A$13), 'Points-Table'!$C$13, true, 0 ) | U32: 8 | V32: =Ifs( (U32 = 'Points-Table'!$A$4), 'Points-Table'!$C$4, (U32 = 'Points-Table'!$A$5), 'Points-Table'!$C$5, (U32 = 'Points-Table'!$A$6), 'Points-Table'!$C$6, (U32 = 'Points-Table'!$A$7), 'Points-Table'!$C$7, (U32 = 'Points-Table'!$A$8), 'Points-Table'!$C$8, (U32 = 'Points-Table'!$A$9), 'Points-Table'!$C$9, (U32 = 'Points-Table'!$A$10), 'Points-Table'!$C$10, (U32 = 'Points-Table'!$A$11), 'Points-Table'!$C$11, (U32 = 'Points-Table'!$A$12), 'Points-Table'!$C$12, (U32 = 'Points-Table'!$A$13), 'Points-Table'!$C$13, true, 0 ) | W32: 2 | X32: =Ifs( (W32 = 'Points-Table'!$A$4), 'Points-Table'!$C$4, (W32 = 'Points-Table'!$A$5), 'Points-Table'!$C$5, (W32 = 'Points-Table'!$A$6), 'Points-Table'!$C$6, (W32 = 'Points-Table'!$A$7), 'Points-Table'!$C$7, (W32 = 'Points-Table'!$A$8), 'Points-Table'!$C$8, (W32 = 'Points-Table'!$A$9), 'Points-Table'!$C$9, (W32 = 'Points-Table'!$A$10), 'Points-Table'!$C$10, (W32 = 'Points-Table'!$A$11), 'Points-Table'!$C$11, (W32 = 'Points-Table'!$A$12), 'Points-Table'!$C$12, (W32 = 'Points-Table'!$A$13), 'Points-Table'!$C$13, true, 0 ) | Y32: 3 | Z32: =Ifs( (Y32 = 'Points-Table'!$A$4), 'Points-Table'!$C$4, (Y32 = 'Points-Table'!$A$5), 'Points-Table'!$C$5, (Y32 = 'Points-Table'!$A$6), 'Points-Table'!$C$6, (Y32 = 'Points-Table'!$A$7), 'Points-Table'!$C$7, (Y32 = 'Points-Table'!$A$8), 'Points-Table'!$C$8, (Y32 = 'Points-Table'!$A$9), 'Points-Table'!$C$9, (Y32 = 'Points-Table'!$A$10), 'Points-Table'!$C$10, (Y32 = 'Points-Table'!$A$11), 'Points-Table'!$C$11, (Y32 = 'Points-Table'!$A$12), 'Points-Table'!$C$12, (Y32 = 'Points-Table'!$A$13), 'Points-Table'!$C$13, true, 0 ) | AA32: =SUM(V32,X32,Z32) | AB32: =Ifs( ISBETWEEN(AA32, 0, 'Points-Table'!C$20, TRUE, False), 'Points-Table'!A$20, ISBETWEEN(AA32, 'Points-Table'!C$20, 'Points-Table'!C$21, TRUE, False), 'Points-Table'!A$21, ISBETWEEN(AA32, 'Points-Table'!C$22, 10000, TRUE, TRUE), 'Points-Table'!A$22, true, 0)
A33: Hotels List & Booking Flow | B33: Bulk Booking | C33: Preview Summary View | K33: Simple | L33: Must Have | R33: =Ifs( (Q33 = 'Points-Table'!$A$4), 'Points-Table'!$C$4, (Q33 = 'Points-Table'!$A$5), 'Points-Table'!$C$5, (Q33 = 'Points-Table'!$A$6), 'Points-Table'!$C$6, (Q33 = 'Points-Table'!$A$7), 'Points-Table'!$C$7, (Q33 = 'Points-Table'!$A$8), 'Points-Table'!$C$8, (Q33 = 'Points-Table'!$A$9), 'Points-Table'!$C$9, (Q33 = 'Points-Table'!$A$10), 'Points-Table'!$C$10, (Q33 = 'Points-Table'!$A$11), 'Points-Table'!$C$11, (Q33 = 'Points-Table'!$A$12), 'Points-Table'!$C$12, (Q33 = 'Points-Table'!$A$13), 'Points-Table'!$C$13, true, 0 ) | T33: =Ifs( (S33 = 'Points-Table'!$A$4), 'Points-Table'!$C$4, (S33 = 'Points-Table'!$A$5), 'Points-Table'!$C$5, (S33 = 'Points-Table'!$A$6), 'Points-Table'!$C$6, (S33 = 'Points-Table'!$A$7), 'Points-Table'!$C$7, (S33 = 'Points-Table'!$A$8), 'Points-Table'!$C$8, (S33 = 'Points-Table'!$A$9), 'Points-Table'!$C$9, (S33 = 'Points-Table'!$A$10), 'Points-Table'!$C$10, (S33 = 'Points-Table'!$A$11), 'Points-Table'!$C$11, (S33 = 'Points-Table'!$A$12), 'Points-Table'!$C$12, (S33 = 'Points-Table'!$A$13), 'Points-Table'!$C$13, true, 0 ) | U33: 5 | V33: =Ifs( (U33 = 'Points-Table'!$A$4), 'Points-Table'!$C$4, (U33 = 'Points-Table'!$A$5), 'Points-Table'!$C$5, (U33 = 'Points-Table'!$A$6), 'Points-Table'!$C$6, (U33 = 'Points-Table'!$A$7), 'Points-Table'!$C$7, (U33 = 'Points-Table'!$A$8), 'Points-Table'!$C$8, (U33 = 'Points-Table'!$A$9), 'Points-Table'!$C$9, (U33 = 'Points-Table'!$A$10), 'Points-Table'!$C$10, (U33 = 'Points-Table'!$A$11), 'Points-Table'!$C$11, (U33 = 'Points-Table'!$A$12), 'Points-Table'!$C$12, (U33 = 'Points-Table'!$A$13), 'Points-Table'!$C$13, true, 0 ) | W33: 2 | X33: =Ifs( (W33 = 'Points-Table'!$A$4), 'Points-Table'!$C$4, (W33 = 'Points-Table'!$A$5), 'Points-Table'!$C$5, (W33 = 'Points-Table'!$A$6), 'Points-Table'!$C$6, (W33 = 'Points-Table'!$A$7), 'Points-Table'!$C$7, (W33 = 'Points-Table'!$A$8), 'Points-Table'!$C$8, (W33 = 'Points-Table'!$A$9), 'Points-Table'!$C$9, (W33 = 'Points-Table'!$A$10), 'Points-Table'!$C$10, (W33 = 'Points-Table'!$A$11), 'Points-Table'!$C$11, (W33 = 'Points-Table'!$A$12), 'Points-Table'!$C$12, (W33 = 'Points-Table'!$A$13), 'Points-Table'!$C$13, true, 0 ) | Y33: 5 | Z33: =Ifs( (Y33 = 'Points-Table'!$A$4), 'Points-Table'!$C$4, (Y33 = 'Points-Table'!$A$5), 'Points-Table'!$C$5, (Y33 = 'Points-Table'!$A$6), 'Points-Table'!$C$6, (Y33 = 'Points-Table'!$A$7), 'Points-Table'!$C$7, (Y33 = 'Points-Table'!$A$8), 'Points-Table'!$C$8, (Y33 = 'Points-Table'!$A$9), 'Points-Table'!$C$9, (Y33 = 'Points-Table'!$A$10), 'Points-Table'!$C$10, (Y33 = 'Points-Table'!$A$11), 'Points-Table'!$C$11, (Y33 = 'Points-Table'!$A$12), 'Points-Table'!$C$12, (Y33 = 'Points-Table'!$A$13), 'Points-Table'!$C$13, true, 0 ) | AA33: =SUM(V33,X33,Z33) | AB33: =Ifs( ISBETWEEN(AA33, 0, 'Points-Table'!C$20, TRUE, False), 'Points-Table'!A$20, ISBETWEEN(AA33, 'Points-Table'!C$20, 'Points-Table'!C$21, TRUE, False), 'Points-Table'!A$21, ISBETWEEN(AA33, 'Points-Table'!C$22, 10000, TRUE, TRUE), 'Points-Table'!A$22, true, 0)
A34: Hotels List & Booking Flow | B34: Bulk Booking | C34: Booking Summary Page(add to cart type) | F34: 1. add to cart api 2. inventory lock/release mechanism api to use | K34: Simple | L34: Must Have | R34: =Ifs( (Q34 = 'Points-Table'!$A$4), 'Points-Table'!$C$4, (Q34 = 'Points-Table'!$A$5), 'Points-Table'!$C$5, (Q34 = 'Points-Table'!$A$6), 'Points-Table'!$C$6, (Q34 = 'Points-Table'!$A$7), 'Points-Table'!$C$7, (Q34 = 'Points-Table'!$A$8), 'Points-Table'!$C$8, (Q34 = 'Points-Table'!$A$9), 'Points-Table'!$C$9, (Q34 = 'Points-Table'!$A$10), 'Points-Table'!$C$10, (Q34 = 'Points-Table'!$A$11), 'Points-Table'!$C$11, (Q34 = 'Points-Table'!$A$12), 'Points-Table'!$C$12, (Q34 = 'Points-Table'!$A$13), 'Points-Table'!$C$13, true, 0 ) | T34: =Ifs( (S34 = 'Points-Table'!$A$4), 'Points-Table'!$C$4, (S34 = 'Points-Table'!$A$5), 'Points-Table'!$C$5, (S34 = 'Points-Table'!$A$6), 'Points-Table'!$C$6, (S34 = 'Points-Table'!$A$7), 'Points-Table'!$C$7, (S34 = 'Points-Table'!$A$8), 'Points-Table'!$C$8, (S34 = 'Points-Table'!$A$9), 'Points-Table'!$C$9, (S34 = 'Points-Table'!$A$10), 'Points-Table'!$C$10, (S34 = 'Points-Table'!$A$11), 'Points-Table'!$C$11, (S34 = 'Points-Table'!$A$12), 'Points-Table'!$C$12, (S34 = 'Points-Table'!$A$13), 'Points-Table'!$C$13, true, 0 ) | U34: 5 | V34: =Ifs( (U34 = 'Points-Table'!$A$4), 'Points-Table'!$C$4, (U34 = 'Points-Table'!$A$5), 'Points-Table'!$C$5, (U34 = 'Points-Table'!$A$6), 'Points-Table'!$C$6, (U34 = 'Points-Table'!$A$7), 'Points-Table'!$C$7, (U34 = 'Points-Table'!$A$8), 'Points-Table'!$C$8, (U34 = 'Points-Table'!$A$9), 'Points-Table'!$C$9, (U34 = 'Points-Table'!$A$10), 'Points-Table'!$C$10, (U34 = 'Points-Table'!$A$11), 'Points-Table'!$C$11, (U34 = 'Points-Table'!$A$12), 'Points-Table'!$C$12, (U34 = 'Points-Table'!$A$13), 'Points-Table'!$C$13, true, 0 ) | W34: 0 | X34: =Ifs( (W34 = 'Points-Table'!$A$4), 'Points-Table'!$C$4, (W34 = 'Points-Table'!$A$5), 'Points-Table'!$C$5, (W34 = 'Points-Table'!$A$6), 'Points-Table'!$C$6, (W34 = 'Points-Table'!$A$7), 'Points-Table'!$C$7, (W34 = 'Points-Table'!$A$8), 'Points-Table'!$C$8, (W34 = 'Points-Table'!$A$9), 'Points-Table'!$C$9, (W34 = 'Points-Table'!$A$10), 'Points-Table'!$C$10, (W34 = 'Points-Table'!$A$11), 'Points-Table'!$C$11, (W34 = 'Points-Table'!$A$12), 'Points-Table'!$C$12, (W34 = 'Points-Table'!$A$13), 'Points-Table'!$C$13, true, 0 ) | Y34: 8 | Z34: =Ifs( (Y34 = 'Points-Table'!$A$4), 'Points-Table'!$C$4, (Y34 = 'Points-Table'!$A$5), 'Points-Table'!$C$5, (Y34 = 'Points-Table'!$A$6), 'Points-Table'!$C$6, (Y34 = 'Points-Table'!$A$7), 'Points-Table'!$C$7, (Y34 = 'Points-Table'!$A$8), 'Points-Table'!$C$8, (Y34 = 'Points-Table'!$A$9), 'Points-Table'!$C$9, (Y34 = 'Points-Table'!$A$10), 'Points-Table'!$C$10, (Y34 = 'Points-Table'!$A$11), 'Points-Table'!$C$11, (Y34 = 'Points-Table'!$A$12), 'Points-Table'!$C$12, (Y34 = 'Points-Table'!$A$13), 'Points-Table'!$C$13, true, 0 ) | AA34: =SUM(V34,X34,Z34) | AB34: =Ifs( ISBETWEEN(AA34, 0, 'Points-Table'!C$20, TRUE, False), 'Points-Table'!A$20, ISBETWEEN(AA34, 'Points-Table'!C$20, 'Points-Table'!C$21, TRUE, False), 'Points-Table'!A$21, ISBETWEEN(AA34, 'Points-Table'!C$22, 10000, TRUE, TRUE), 'Points-Table'!A$22, true, 0)
A35: Hotels List & Booking Flow | B35: Bulk Booking | C35: Modify Current Booking State | K35: Simple | L35: Must Have | R35: =Ifs( (Q35 = 'Points-Table'!$A$4), 'Points-Table'!$C$4, (Q35 = 'Points-Table'!$A$5), 'Points-Table'!$C$5, (Q35 = 'Points-Table'!$A$6), 'Points-Table'!$C$6, (Q35 = 'Points-Table'!$A$7), 'Points-Table'!$C$7, (Q35 = 'Points-Table'!$A$8), 'Points-Table'!$C$8, (Q35 = 'Points-Table'!$A$9), 'Points-Table'!$C$9, (Q35 = 'Points-Table'!$A$10), 'Points-Table'!$C$10, (Q35 = 'Points-Table'!$A$11), 'Points-Table'!$C$11, (Q35 = 'Points-Table'!$A$12), 'Points-Table'!$C$12, (Q35 = 'Points-Table'!$A$13), 'Points-Table'!$C$13, true, 0 ) | T35: =Ifs( (S35 = 'Points-Table'!$A$4), 'Points-Table'!$C$4, (S35 = 'Points-Table'!$A$5), 'Points-Table'!$C$5, (S35 = 'Points-Table'!$A$6), 'Points-Table'!$C$6, (S35 = 'Points-Table'!$A$7), 'Points-Table'!$C$7, (S35 = 'Points-Table'!$A$8), 'Points-Table'!$C$8, (S35 = 'Points-Table'!$A$9), 'Points-Table'!$C$9, (S35 = 'Points-Table'!$A$10), 'Points-Table'!$C$10, (S35 = 'Points-Table'!$A$11), 'Points-Table'!$C$11, (S35 = 'Points-Table'!$A$12), 'Points-Table'!$C$12, (S35 = 'Points-Table'!$A$13), 'Points-Table'!$C$13, true, 0 ) | U35: 3 | V35: =Ifs( (U35 = 'Points-Table'!$A$4), 'Points-Table'!$C$4, (U35 = 'Points-Table'!$A$5), 'Points-Table'!$C$5, (U35 = 'Points-Table'!$A$6), 'Points-Table'!$C$6, (U35 = 'Points-Table'!$A$7), 'Points-Table'!$C$7, (U35 = 'Points-Table'!$A$8), 'Points-Table'!$C$8, (U35 = 'Points-Table'!$A$9), 'Points-Table'!$C$9, (U35 = 'Points-Table'!$A$10), 'Points-Table'!$C$10, (U35 = 'Points-Table'!$A$11), 'Points-Table'!$C$11, (U35 = 'Points-Table'!$A$12), 'Points-Table'!$C$12, (U35 = 'Points-Table'!$A$13), 'Points-Table'!$C$13, true, 0 ) | W35: 0 | X35: =Ifs( (W35 = 'Points-Table'!$A$4), 'Points-Table'!$C$4, (W35 = 'Points-Table'!$A$5), 'Points-Table'!$C$5, (W35 = 'Points-Table'!$A$6), 'Points-Table'!$C$6, (W35 = 'Points-Table'!$A$7), 'Points-Table'!$C$7, (W35 = 'Points-Table'!$A$8), 'Points-Table'!$C$8, (W35 = 'Points-Table'!$A$9), 'Points-Table'!$C$9, (W35 = 'Points-Table'!$A$10), 'Points-Table'!$C$10, (W35 = 'Points-Table'!$A$11), 'Points-Table'!$C$11, (W35 = 'Points-Table'!$A$12), 'Points-Table'!$C$12, (W35 = 'Points-Table'!$A$13), 'Points-Table'!$C$13, true, 0 ) | Y35: 0 | Z35: =Ifs( (Y35 = 'Points-Table'!$A$4), 'Points-Table'!$C$4, (Y35 = 'Points-Table'!$A$5), 'Points-Table'!$C$5, (Y35 = 'Points-Table'!$A$6), 'Points-Table'!$C$6, (Y35 = 'Points-Table'!$A$7), 'Points-Table'!$C$7, (Y35 = 'Points-Table'!$A$8), 'Points-Table'!$C$8, (Y35 = 'Points-Table'!$A$9), 'Points-Table'!$C$9, (Y35 = 'Points-Table'!$A$10), 'Points-Table'!$C$10, (Y35 = 'Points-Table'!$A$11), 'Points-Table'!$C$11, (Y35 = 'Points-Table'!$A$12), 'Points-Table'!$C$12, (Y35 = 'Points-Table'!$A$13), 'Points-Table'!$C$13, true, 0 ) | AA35: =SUM(V35,X35,Z35) | AB35: =Ifs( ISBETWEEN(AA35, 0, 'Points-Table'!C$20, TRUE, False), 'Points-Table'!A$20, ISBETWEEN(AA35, 'Points-Table'!C$20, 'Points-Table'!C$21, TRUE, False), 'Points-Table'!A$21, ISBETWEEN(AA35, 'Points-Table'!C$22, 10000, TRUE, TRUE), 'Points-Table'!A$22, true, 0)
A36: Hotels List & Booking Flow | B36: Bulk Booking | C36: Add guest details | K36: Simple | L36: Must Have | R36: =Ifs( (Q36 = 'Points-Table'!$A$4), 'Points-Table'!$C$4, (Q36 = 'Points-Table'!$A$5), 'Points-Table'!$C$5, (Q36 = 'Points-Table'!$A$6), 'Points-Table'!$C$6, (Q36 = 'Points-Table'!$A$7), 'Points-Table'!$C$7, (Q36 = 'Points-Table'!$A$8), 'Points-Table'!$C$8, (Q36 = 'Points-Table'!$A$9), 'Points-Table'!$C$9, (Q36 = 'Points-Table'!$A$10), 'Points-Table'!$C$10, (Q36 = 'Points-Table'!$A$11), 'Points-Table'!$C$11, (Q36 = 'Points-Table'!$A$12), 'Points-Table'!$C$12, (Q36 = 'Points-Table'!$A$13), 'Points-Table'!$C$13, true, 0 ) | T36: =Ifs( (S36 = 'Points-Table'!$A$4), 'Points-Table'!$C$4, (S36 = 'Points-Table'!$A$5), 'Points-Table'!$C$5, (S36 = 'Points-Table'!$A$6), 'Points-Table'!$C$6, (S36 = 'Points-Table'!$A$7), 'Points-Table'!$C$7, (S36 = 'Points-Table'!$A$8), 'Points-Table'!$C$8, (S36 = 'Points-Table'!$A$9), 'Points-Table'!$C$9, (S36 = 'Points-Table'!$A$10), 'Points-Table'!$C$10, (S36 = 'Points-Table'!$A$11), 'Points-Table'!$C$11, (S36 = 'Points-Table'!$A$12), 'Points-Table'!$C$12, (S36 = 'Points-Table'!$A$13), 'Points-Table'!$C$13, true, 0 ) | U36: 3 | V36: =Ifs( (U36 = 'Points-Table'!$A$4), 'Points-Table'!$C$4, (U36 = 'Points-Table'!$A$5), 'Points-Table'!$C$5, (U36 = 'Points-Table'!$A$6), 'Points-Table'!$C$6, (U36 = 'Points-Table'!$A$7), 'Points-Table'!$C$7, (U36 = 'Points-Table'!$A$8), 'Points-Table'!$C$8, (U36 = 'Points-Table'!$A$9), 'Points-Table'!$C$9, (U36 = 'Points-Table'!$A$10), 'Points-Table'!$C$10, (U36 = 'Points-Table'!$A$11), 'Points-Table'!$C$11, (U36 = 'Points-Table'!$A$12), 'Points-Table'!$C$12, (U36 = 'Points-Table'!$A$13), 'Points-Table'!$C$13, true, 0 ) | W36: 0 | X36: =Ifs( (W36 = 'Points-Table'!$A$4), 'Points-Table'!$C$4, (W36 = 'Points-Table'!$A$5), 'Points-Table'!$C$5, (W36 = 'Points-Table'!$A$6), 'Points-Table'!$C$6, (W36 = 'Points-Table'!$A$7), 'Points-Table'!$C$7, (W36 = 'Points-Table'!$A$8), 'Points-Table'!$C$8, (W36 = 'Points-Table'!$A$9), 'Points-Table'!$C$9, (W36 = 'Points-Table'!$A$10), 'Points-Table'!$C$10, (W36 = 'Points-Table'!$A$11), 'Points-Table'!$C$11, (W36 = 'Points-Table'!$A$12), 'Points-Table'!$C$12, (W36 = 'Points-Table'!$A$13), 'Points-Table'!$C$13, true, 0 ) | Y36: 3 | Z36: =Ifs( (Y36 = 'Points-Table'!$A$4), 'Points-Table'!$C$4, (Y36 = 'Points-Table'!$A$5), 'Points-Table'!$C$5, (Y36 = 'Points-Table'!$A$6), 'Points-Table'!$C$6, (Y36 = 'Points-Table'!$A$7), 'Points-Table'!$C$7, (Y36 = 'Points-Table'!$A$8), 'Points-Table'!$C$8, (Y36 = 'Points-Table'!$A$9), 'Points-Table'!$C$9, (Y36 = 'Points-Table'!$A$10), 'Points-Table'!$C$10, (Y36 = 'Points-Table'!$A$11), 'Points-Table'!$C$11, (Y36 = 'Points-Table'!$A$12), 'Points-Table'!$C$12, (Y36 = 'Points-Table'!$A$13), 'Points-Table'!$C$13, true, 0 ) | AA36: =SUM(V36,X36,Z36) | AB36: =Ifs( ISBETWEEN(AA36, 0, 'Points-Table'!C$20, TRUE, False), 'Points-Table'!A$20, ISBETWEEN(AA36, 'Points-Table'!C$20, 'Points-Table'!C$21, TRUE, False), 'Points-Table'!A$21, ISBETWEEN(AA36, 'Points-Table'!C$22, 10000, TRUE, TRUE), 'Points-Table'!A$22, true, 0)
A37: Hotels List & Booking Flow | B37: Bulk Booking | C37: Add/Edit number of rooms per day | K37: Simple | L37: Must Have | R37: =Ifs( (Q37 = 'Points-Table'!$A$4), 'Points-Table'!$C$4, (Q37 = 'Points-Table'!$A$5), 'Points-Table'!$C$5, (Q37 = 'Points-Table'!$A$6), 'Points-Table'!$C$6, (Q37 = 'Points-Table'!$A$7), 'Points-Table'!$C$7, (Q37 = 'Points-Table'!$A$8), 'Points-Table'!$C$8, (Q37 = 'Points-Table'!$A$9), 'Points-Table'!$C$9, (Q37 = 'Points-Table'!$A$10), 'Points-Table'!$C$10, (Q37 = 'Points-Table'!$A$11), 'Points-Table'!$C$11, (Q37 = 'Points-Table'!$A$12), 'Points-Table'!$C$12, (Q37 = 'Points-Table'!$A$13), 'Points-Table'!$C$13, true, 0 ) | T37: =Ifs( (S37 = 'Points-Table'!$A$4), 'Points-Table'!$C$4, (S37 = 'Points-Table'!$A$5), 'Points-Table'!$C$5, (S37 = 'Points-Table'!$A$6), 'Points-Table'!$C$6, (S37 = 'Points-Table'!$A$7), 'Points-Table'!$C$7, (S37 = 'Points-Table'!$A$8), 'Points-Table'!$C$8, (S37 = 'Points-Table'!$A$9), 'Points-Table'!$C$9, (S37 = 'Points-Table'!$A$10), 'Points-Table'!$C$10, (S37 = 'Points-Table'!$A$11), 'Points-Table'!$C$11, (S37 = 'Points-Table'!$A$12), 'Points-Table'!$C$12, (S37 = 'Points-Table'!$A$13), 'Points-Table'!$C$13, true, 0 ) | U37: 2 | V37: =Ifs( (U37 = 'Points-Table'!$A$4), 'Points-Table'!$C$4, (U37 = 'Points-Table'!$A$5), 'Points-Table'!$C$5, (U37 = 'Points-Table'!$A$6), 'Points-Table'!$C$6, (U37 = 'Points-Table'!$A$7), 'Points-Table'!$C$7, (U37 = 'Points-Table'!$A$8), 'Points-Table'!$C$8, (U37 = 'Points-Table'!$A$9), 'Points-Table'!$C$9, (U37 = 'Points-Table'!$A$10), 'Points-Table'!$C$10, (U37 = 'Points-Table'!$A$11), 'Points-Table'!$C$11, (U37 = 'Points-Table'!$A$12), 'Points-Table'!$C$12, (U37 = 'Points-Table'!$A$13), 'Points-Table'!$C$13, true, 0 ) | W37: 0 | X37: =Ifs( (W37 = 'Points-Table'!$A$4), 'Points-Table'!$C$4, (W37 = 'Points-Table'!$A$5), 'Points-Table'!$C$5, (W37 = 'Points-Table'!$A$6), 'Points-Table'!$C$6, (W37 = 'Points-Table'!$A$7), 'Points-Table'!$C$7, (W37 = 'Points-Table'!$A$8), 'Points-Table'!$C$8, (W37 = 'Points-Table'!$A$9), 'Points-Table'!$C$9, (W37 = 'Points-Table'!$A$10), 'Points-Table'!$C$10, (W37 = 'Points-Table'!$A$11), 'Points-Table'!$C$11, (W37 = 'Points-Table'!$A$12), 'Points-Table'!$C$12, (W37 = 'Points-Table'!$A$13), 'Points-Table'!$C$13, true, 0 ) | Y37: 0 | Z37: =Ifs( (Y37 = 'Points-Table'!$A$4), 'Points-Table'!$C$4, (Y37 = 'Points-Table'!$A$5), 'Points-Table'!$C$5, (Y37 = 'Points-Table'!$A$6), 'Points-Table'!$C$6, (Y37 = 'Points-Table'!$A$7), 'Points-Table'!$C$7, (Y37 = 'Points-Table'!$A$8), 'Points-Table'!$C$8, (Y37 = 'Points-Table'!$A$9), 'Points-Table'!$C$9, (Y37 = 'Points-Table'!$A$10), 'Points-Table'!$C$10, (Y37 = 'Points-Table'!$A$11), 'Points-Table'!$C$11, (Y37 = 'Points-Table'!$A$12), 'Points-Table'!$C$12, (Y37 = 'Points-Table'!$A$13), 'Points-Table'!$C$13, true, 0 ) | AA37: =SUM(V37,X37,Z37) | AB37: =Ifs( ISBETWEEN(AA37, 0, 'Points-Table'!C$20, TRUE, False), 'Points-Table'!A$20, ISBETWEEN(AA37, 'Points-Table'!C$20, 'Points-Table'!C$21, TRUE, False), 'Points-Table'!A$21, ISBETWEEN(AA37, 'Points-Table'!C$22, 10000, TRUE, TRUE), 'Points-Table'!A$22, true, 0)
A38: Hotels List & Booking Flow | B38: Make a Payment (Stripe) | K38: Simple | L38: Must Have | R38: =Ifs( (Q38 = 'Points-Table'!$A$4), 'Points-Table'!$C$4, (Q38 = 'Points-Table'!$A$5), 'Points-Table'!$C$5, (Q38 = 'Points-Table'!$A$6), 'Points-Table'!$C$6, (Q38 = 'Points-Table'!$A$7), 'Points-Table'!$C$7, (Q38 = 'Points-Table'!$A$8), 'Points-Table'!$C$8, (Q38 = 'Points-Table'!$A$9), 'Points-Table'!$C$9, (Q38 = 'Points-Table'!$A$10), 'Points-Table'!$C$10, (Q38 = 'Points-Table'!$A$11), 'Points-Table'!$C$11, (Q38 = 'Points-Table'!$A$12), 'Points-Table'!$C$12, (Q38 = 'Points-Table'!$A$13), 'Points-Table'!$C$13, true, 0 ) | T38: =Ifs( (S38 = 'Points-Table'!$A$4), 'Points-Table'!$C$4, (S38 = 'Points-Table'!$A$5), 'Points-Table'!$C$5, (S38 = 'Points-Table'!$A$6), 'Points-Table'!$C$6, (S38 = 'Points-Table'!$A$7), 'Points-Table'!$C$7, (S38 = 'Points-Table'!$A$8), 'Points-Table'!$C$8, (S38 = 'Points-Table'!$A$9), 'Points-Table'!$C$9, (S38 = 'Points-Table'!$A$10), 'Points-Table'!$C$10, (S38 = 'Points-Table'!$A$11), 'Points-Table'!$C$11, (S38 = 'Points-Table'!$A$12), 'Points-Table'!$C$12, (S38 = 'Points-Table'!$A$13), 'Points-Table'!$C$13, true, 0 ) | U38: 5 | V38: =Ifs( (U38 = 'Points-Table'!$A$4), 'Points-Table'!$C$4, (U38 = 'Points-Table'!$A$5), 'Points-Table'!$C$5, (U38 = 'Points-Table'!$A$6), 'Points-Table'!$C$6, (U38 = 'Points-Table'!$A$7), 'Points-Table'!$C$7, (U38 = 'Points-Table'!$A$8), 'Points-Table'!$C$8, (U38 = 'Points-Table'!$A$9), 'Points-Table'!$C$9, (U38 = 'Points-Table'!$A$10), 'Points-Table'!$C$10, (U38 = 'Points-Table'!$A$11), 'Points-Table'!$C$11, (U38 = 'Points-Table'!$A$12), 'Points-Table'!$C$12, (U38 = 'Points-Table'!$A$13), 'Points-Table'!$C$13, true, 0 ) | W38: 13 | X38: =Ifs( (W38 = 'Points-Table'!$A$4), 'Points-Table'!$C$4, (W38 = 'Points-Table'!$A$5), 'Points-Table'!$C$5, (W38 = 'Points-Table'!$A$6), 'Points-Table'!$C$6, (W38 = 'Points-Table'!$A$7), 'Points-Table'!$C$7, (W38 = 'Points-Table'!$A$8), 'Points-Table'!$C$8, (W38 = 'Points-Table'!$A$9), 'Points-Table'!$C$9, (W38 = 'Points-Table'!$A$10), 'Points-Table'!$C$10, (W38 = 'Points-Table'!$A$11), 'Points-Table'!$C$11, (W38 = 'Points-Table'!$A$12), 'Points-Table'!$C$12, (W38 = 'Points-Table'!$A$13), 'Points-Table'!$C$13, true, 0 ) | Y38: 34 | Z38: =Ifs( (Y38 = 'Points-Table'!$A$4), 'Points-Table'!$C$4, (Y38 = 'Points-Table'!$A$5), 'Points-Table'!$C$5, (Y38 = 'Points-Table'!$A$6), 'Points-Table'!$C$6, (Y38 = 'Points-Table'!$A$7), 'Points-Table'!$C$7, (Y38 = 'Points-Table'!$A$8), 'Points-Table'!$C$8, (Y38 = 'Points-Table'!$A$9), 'Points-Table'!$C$9, (Y38 = 'Points-Table'!$A$10), 'Points-Table'!$C$10, (Y38 = 'Points-Table'!$A$11), 'Points-Table'!$C$11, (Y38 = 'Points-Table'!$A$12), 'Points-Table'!$C$12, (Y38 = 'Points-Table'!$A$13), 'Points-Table'!$C$13, true, 0 ) | AA38: =SUM(V38,X38,Z38) | AB38: =Ifs( ISBETWEEN(AA38, 0, 'Points-Table'!C$20, TRUE, False), 'Points-Table'!A$20, ISBETWEEN(AA38, 'Points-Table'!C$20, 'Points-Table'!C$21, TRUE, False), 'Points-Table'!A$21, ISBETWEEN(AA38, 'Points-Table'!C$22, 10000, TRUE, TRUE), 'Points-Table'!A$22, true, 0)
A39: Hotels List & Booking Flow | B39: Booking confirmation | F39: save booking with all transactional details | K39: Simple | L39: Must Have | Q39: 1 | R39: =Ifs( (Q39 = 'Points-Table'!$A$4), 'Points-Table'!$C$4, (Q39 = 'Points-Table'!$A$5), 'Points-Table'!$C$5, (Q39 = 'Points-Table'!$A$6), 'Points-Table'!$C$6, (Q39 = 'Points-Table'!$A$7), 'Points-Table'!$C$7, (Q39 = 'Points-Table'!$A$8), 'Points-Table'!$C$8, (Q39 = 'Points-Table'!$A$9), 'Points-Table'!$C$9, (Q39 = 'Points-Table'!$A$10), 'Points-Table'!$C$10, (Q39 = 'Points-Table'!$A$11), 'Points-Table'!$C$11, (Q39 = 'Points-Table'!$A$12), 'Points-Table'!$C$12, (Q39 = 'Points-Table'!$A$13), 'Points-Table'!$C$13, true, 0 ) | S39: 1 | T39: =Ifs( (S39 = 'Points-Table'!$A$4), 'Points-Table'!$C$4, (S39 = 'Points-Table'!$A$5), 'Points-Table'!$C$5, (S39 = 'Points-Table'!$A$6), 'Points-Table'!$C$6, (S39 = 'Points-Table'!$A$7), 'Points-Table'!$C$7, (S39 = 'Points-Table'!$A$8), 'Points-Table'!$C$8, (S39 = 'Points-Table'!$A$9), 'Points-Table'!$C$9, (S39 = 'Points-Table'!$A$10), 'Points-Table'!$C$10, (S39 = 'Points-Table'!$A$11), 'Points-Table'!$C$11, (S39 = 'Points-Table'!$A$12), 'Points-Table'!$C$12, (S39 = 'Points-Table'!$A$13), 'Points-Table'!$C$13, true, 0 ) | U39: 3 | V39: =Ifs( (U39 = 'Points-Table'!$A$4), 'Points-Table'!$C$4, (U39 = 'Points-Table'!$A$5), 'Points-Table'!$C$5, (U39 = 'Points-Table'!$A$6), 'Points-Table'!$C$6, (U39 = 'Points-Table'!$A$7), 'Points-Table'!$C$7, (U39 = 'Points-Table'!$A$8), 'Points-Table'!$C$8, (U39 = 'Points-Table'!$A$9), 'Points-Table'!$C$9, (U39 = 'Points-Table'!$A$10), 'Points-Table'!$C$10, (U39 = 'Points-Table'!$A$11), 'Points-Table'!$C$11, (U39 = 'Points-Table'!$A$12), 'Points-Table'!$C$12, (U39 = 'Points-Table'!$A$13), 'Points-Table'!$C$13, true, 0 ) | W39: 2 | X39: =Ifs( (W39 = 'Points-Table'!$A$4), 'Points-Table'!$C$4, (W39 = 'Points-Table'!$A$5), 'Points-Table'!$C$5, (W39 = 'Points-Table'!$A$6), 'Points-Table'!$C$6, (W39 = 'Points-Table'!$A$7), 'Points-Table'!$C$7, (W39 = 'Points-Table'!$A$8), 'Points-Table'!$C$8, (W39 = 'Points-Table'!$A$9), 'Points-Table'!$C$9, (W39 = 'Points-Table'!$A$10), 'Points-Table'!$C$10, (W39 = 'Points-Table'!$A$11), 'Points-Table'!$C$11, (W39 = 'Points-Table'!$A$12), 'Points-Table'!$C$12, (W39 = 'Points-Table'!$A$13), 'Points-Table'!$C$13, true, 0 ) | Y39: 13 | Z39: =Ifs( (Y39 = 'Points-Table'!$A$4), 'Points-Table'!$C$4, (Y39 = 'Points-Table'!$A$5), 'Points-Table'!$C$5, (Y39 = 'Points-Table'!$A$6), 'Points-Table'!$C$6, (Y39 = 'Points-Table'!$A$7), 'Points-Table'!$C$7, (Y39 = 'Points-Table'!$A$8), 'Points-Table'!$C$8, (Y39 = 'Points-Table'!$A$9), 'Points-Table'!$C$9, (Y39 = 'Points-Table'!$A$10), 'Points-Table'!$C$10, (Y39 = 'Points-Table'!$A$11), 'Points-Table'!$C$11, (Y39 = 'Points-Table'!$A$12), 'Points-Table'!$C$12, (Y39 = 'Points-Table'!$A$13), 'Points-Table'!$C$13, true, 0 ) | AA39: =SUM(V39,X39,Z39) | AB39: =Ifs( ISBETWEEN(AA39, 0, 'Points-Table'!C$20, TRUE, False), 'Points-Table'!A$20, ISBETWEEN(AA39, 'Points-Table'!C$20, 'Points-Table'!C$21, TRUE, False), 'Points-Table'!A$21, ISBETWEEN(AA39, 'Points-Table'!C$22, 10000, TRUE, TRUE), 'Points-Table'!A$22, true, 0)
A40: Hotels List & Booking Flow | B40: Trigger Booking Email confirmation | D40: also setup other system booking emails | K40: Simple | L40: Must Have | R40: =Ifs( (Q40 = 'Points-Table'!$A$4), 'Points-Table'!$C$4, (Q40 = 'Points-Table'!$A$5), 'Points-Table'!$C$5, (Q40 = 'Points-Table'!$A$6), 'Points-Table'!$C$6, (Q40 = 'Points-Table'!$A$7), 'Points-Table'!$C$7, (Q40 = 'Points-Table'!$A$8), 'Points-Table'!$C$8, (Q40 = 'Points-Table'!$A$9), 'Points-Table'!$C$9, (Q40 = 'Points-Table'!$A$10), 'Points-Table'!$C$10, (Q40 = 'Points-Table'!$A$11), 'Points-Table'!$C$11, (Q40 = 'Points-Table'!$A$12), 'Points-Table'!$C$12, (Q40 = 'Points-Table'!$A$13), 'Points-Table'!$C$13, true, 0 ) | T40: =Ifs( (S40 = 'Points-Table'!$A$4), 'Points-Table'!$C$4, (S40 = 'Points-Table'!$A$5), 'Points-Table'!$C$5, (S40 = 'Points-Table'!$A$6), 'Points-Table'!$C$6, (S40 = 'Points-Table'!$A$7), 'Points-Table'!$C$7, (S40 = 'Points-Table'!$A$8), 'Points-Table'!$C$8, (S40 = 'Points-Table'!$A$9), 'Points-Table'!$C$9, (S40 = 'Points-Table'!$A$10), 'Points-Table'!$C$10, (S40 = 'Points-Table'!$A$11), 'Points-Table'!$C$11, (S40 = 'Points-Table'!$A$12), 'Points-Table'!$C$12, (S40 = 'Points-Table'!$A$13), 'Points-Table'!$C$13, true, 0 ) | U40: 5 | V40: =Ifs( (U40 = 'Points-Table'!$A$4), 'Points-Table'!$C$4, (U40 = 'Points-Table'!$A$5), 'Points-Table'!$C$5, (U40 = 'Points-Table'!$A$6), 'Points-Table'!$C$6, (U40 = 'Points-Table'!$A$7), 'Points-Table'!$C$7, (U40 = 'Points-Table'!$A$8), 'Points-Table'!$C$8, (U40 = 'Points-Table'!$A$9), 'Points-Table'!$C$9, (U40 = 'Points-Table'!$A$10), 'Points-Table'!$C$10, (U40 = 'Points-Table'!$A$11), 'Points-Table'!$C$11, (U40 = 'Points-Table'!$A$12), 'Points-Table'!$C$12, (U40 = 'Points-Table'!$A$13), 'Points-Table'!$C$13, true, 0 ) | W40: 0 | X40: =Ifs( (W40 = 'Points-Table'!$A$4), 'Points-Table'!$C$4, (W40 = 'Points-Table'!$A$5), 'Points-Table'!$C$5, (W40 = 'Points-Table'!$A$6), 'Points-Table'!$C$6, (W40 = 'Points-Table'!$A$7), 'Points-Table'!$C$7, (W40 = 'Points-Table'!$A$8), 'Points-Table'!$C$8, (W40 = 'Points-Table'!$A$9), 'Points-Table'!$C$9, (W40 = 'Points-Table'!$A$10), 'Points-Table'!$C$10, (W40 = 'Points-Table'!$A$11), 'Points-Table'!$C$11, (W40 = 'Points-Table'!$A$12), 'Points-Table'!$C$12, (W40 = 'Points-Table'!$A$13), 'Points-Table'!$C$13, true, 0 ) | Y40: 13 | Z40: =Ifs( (Y40 = 'Points-Table'!$A$4), 'Points-Table'!$C$4, (Y40 = 'Points-Table'!$A$5), 'Points-Table'!$C$5, (Y40 = 'Points-Table'!$A$6), 'Points-Table'!$C$6, (Y40 = 'Points-Table'!$A$7), 'Points-Table'!$C$7, (Y40 = 'Points-Table'!$A$8), 'Points-Table'!$C$8, (Y40 = 'Points-Table'!$A$9), 'Points-Table'!$C$9, (Y40 = 'Points-Table'!$A$10), 'Points-Table'!$C$10, (Y40 = 'Points-Table'!$A$11), 'Points-Table'!$C$11, (Y40 = 'Points-Table'!$A$12), 'Points-Table'!$C$12, (Y40 = 'Points-Table'!$A$13), 'Points-Table'!$C$13, true, 0 ) | AA40: =SUM(V40,X40,Z40) | AB40: =Ifs( ISBETWEEN(AA40, 0, 'Points-Table'!C$20, TRUE, False), 'Points-Table'!A$20, ISBETWEEN(AA40, 'Points-Table'!C$20, 'Points-Table'!C$21, TRUE, False), 'Points-Table'!A$21, ISBETWEEN(AA40, 'Points-Table'!C$22, 10000, TRUE, TRUE), 'Points-Table'!A$22, true, 0)
A41: My Bookings | B41: Bookings List ( Present Bookings / Past Bookings / Cancelled) | D41: Tab is not needed as per the design. | K41: Simple | L41: Must Have | Q41: 5 | R41: =Ifs( (Q41 = 'Points-Table'!$A$4), 'Points-Table'!$C$4, (Q41 = 'Points-Table'!$A$5), 'Points-Table'!$C$5, (Q41 = 'Points-Table'!$A$6), 'Points-Table'!$C$6, (Q41 = 'Points-Table'!$A$7), 'Points-Table'!$C$7, (Q41 = 'Points-Table'!$A$8), 'Points-Table'!$C$8, (Q41 = 'Points-Table'!$A$9), 'Points-Table'!$C$9, (Q41 = 'Points-Table'!$A$10), 'Points-Table'!$C$10, (Q41 = 'Points-Table'!$A$11), 'Points-Table'!$C$11, (Q41 = 'Points-Table'!$A$12), 'Points-Table'!$C$12, (Q41 = 'Points-Table'!$A$13), 'Points-Table'!$C$13, true, 0 ) | S41: 5 | T41: =Ifs( (S41 = 'Points-Table'!$A$4), 'Points-Table'!$C$4, (S41 = 'Points-Table'!$A$5), 'Points-Table'!$C$5, (S41 = 'Points-Table'!$A$6), 'Points-Table'!$C$6, (S41 = 'Points-Table'!$A$7), 'Points-Table'!$C$7, (S41 = 'Points-Table'!$A$8), 'Points-Table'!$C$8, (S41 = 'Points-Table'!$A$9), 'Points-Table'!$C$9, (S41 = 'Points-Table'!$A$10), 'Points-Table'!$C$10, (S41 = 'Points-Table'!$A$11), 'Points-Table'!$C$11, (S41 = 'Points-Table'!$A$12), 'Points-Table'!$C$12, (S41 = 'Points-Table'!$A$13), 'Points-Table'!$C$13, true, 0 ) | U41: 8 | V41: =Ifs( (U41 = 'Points-Table'!$A$4), 'Points-Table'!$C$4, (U41 = 'Points-Table'!$A$5), 'Points-Table'!$C$5, (U41 = 'Points-Table'!$A$6), 'Points-Table'!$C$6, (U41 = 'Points-Table'!$A$7), 'Points-Table'!$C$7, (U41 = 'Points-Table'!$A$8), 'Points-Table'!$C$8, (U41 = 'Points-Table'!$A$9), 'Points-Table'!$C$9, (U41 = 'Points-Table'!$A$10), 'Points-Table'!$C$10, (U41 = 'Points-Table'!$A$11), 'Points-Table'!$C$11, (U41 = 'Points-Table'!$A$12), 'Points-Table'!$C$12, (U41 = 'Points-Table'!$A$13), 'Points-Table'!$C$13, true, 0 ) | W41: 5 | X41: =Ifs( (W41 = 'Points-Table'!$A$4), 'Points-Table'!$C$4, (W41 = 'Points-Table'!$A$5), 'Points-Table'!$C$5, (W41 = 'Points-Table'!$A$6), 'Points-Table'!$C$6, (W41 = 'Points-Table'!$A$7), 'Points-Table'!$C$7, (W41 = 'Points-Table'!$A$8), 'Points-Table'!$C$8, (W41 = 'Points-Table'!$A$9), 'Points-Table'!$C$9, (W41 = 'Points-Table'!$A$10), 'Points-Table'!$C$10, (W41 = 'Points-Table'!$A$11), 'Points-Table'!$C$11, (W41 = 'Points-Table'!$A$12), 'Points-Table'!$C$12, (W41 = 'Points-Table'!$A$13), 'Points-Table'!$C$13, true, 0 ) | Y41: 5 | Z41: =Ifs( (Y41 = 'Points-Table'!$A$4), 'Points-Table'!$C$4, (Y41 = 'Points-Table'!$A$5), 'Points-Table'!$C$5, (Y41 = 'Points-Table'!$A$6), 'Points-Table'!$C$6, (Y41 = 'Points-Table'!$A$7), 'Points-Table'!$C$7, (Y41 = 'Points-Table'!$A$8), 'Points-Table'!$C$8, (Y41 = 'Points-Table'!$A$9), 'Points-Table'!$C$9, (Y41 = 'Points-Table'!$A$10), 'Points-Table'!$C$10, (Y41 = 'Points-Table'!$A$11), 'Points-Table'!$C$11, (Y41 = 'Points-Table'!$A$12), 'Points-Table'!$C$12, (Y41 = 'Points-Table'!$A$13), 'Points-Table'!$C$13, true, 0 ) | AA41: =SUM(V41,X41,Z41) | AB41: =Ifs( ISBETWEEN(AA41, 0, 'Points-Table'!C$20, TRUE, False), 'Points-Table'!A$20, ISBETWEEN(AA41, 'Points-Table'!C$20, 'Points-Table'!C$21, TRUE, False), 'Points-Table'!A$21, ISBETWEEN(AA41, 'Points-Table'!C$22, 10000, TRUE, TRUE), 'Points-Table'!A$22, true, 0)
A42: My Bookings | B42: View Booking details | K42: Simple | L42: Must Have | Q42: 2 | R42: =Ifs( (Q42 = 'Points-Table'!$A$4), 'Points-Table'!$C$4, (Q42 = 'Points-Table'!$A$5), 'Points-Table'!$C$5, (Q42 = 'Points-Table'!$A$6), 'Points-Table'!$C$6, (Q42 = 'Points-Table'!$A$7), 'Points-Table'!$C$7, (Q42 = 'Points-Table'!$A$8), 'Points-Table'!$C$8, (Q42 = 'Points-Table'!$A$9), 'Points-Table'!$C$9, (Q42 = 'Points-Table'!$A$10), 'Points-Table'!$C$10, (Q42 = 'Points-Table'!$A$11), 'Points-Table'!$C$11, (Q42 = 'Points-Table'!$A$12), 'Points-Table'!$C$12, (Q42 = 'Points-Table'!$A$13), 'Points-Table'!$C$13, true, 0 ) | S42: 2 | T42: =Ifs( (S42 = 'Points-Table'!$A$4), 'Points-Table'!$C$4, (S42 = 'Points-Table'!$A$5), 'Points-Table'!$C$5, (S42 = 'Points-Table'!$A$6), 'Points-Table'!$C$6, (S42 = 'Points-Table'!$A$7), 'Points-Table'!$C$7, (S42 = 'Points-Table'!$A$8), 'Points-Table'!$C$8, (S42 = 'Points-Table'!$A$9), 'Points-Table'!$C$9, (S42 = 'Points-Table'!$A$10), 'Points-Table'!$C$10, (S42 = 'Points-Table'!$A$11), 'Points-Table'!$C$11, (S42 = 'Points-Table'!$A$12), 'Points-Table'!$C$12, (S42 = 'Points-Table'!$A$13), 'Points-Table'!$C$13, true, 0 ) | U42: 5 | V42: =Ifs( (U42 = 'Points-Table'!$A$4), 'Points-Table'!$C$4, (U42 = 'Points-Table'!$A$5), 'Points-Table'!$C$5, (U42 = 'Points-Table'!$A$6), 'Points-Table'!$C$6, (U42 = 'Points-Table'!$A$7), 'Points-Table'!$C$7, (U42 = 'Points-Table'!$A$8), 'Points-Table'!$C$8, (U42 = 'Points-Table'!$A$9), 'Points-Table'!$C$9, (U42 = 'Points-Table'!$A$10), 'Points-Table'!$C$10, (U42 = 'Points-Table'!$A$11), 'Points-Table'!$C$11, (U42 = 'Points-Table'!$A$12), 'Points-Table'!$C$12, (U42 = 'Points-Table'!$A$13), 'Points-Table'!$C$13, true, 0 ) | W42: 3 | X42: =Ifs( (W42 = 'Points-Table'!$A$4), 'Points-Table'!$C$4, (W42 = 'Points-Table'!$A$5), 'Points-Table'!$C$5, (W42 = 'Points-Table'!$A$6), 'Points-Table'!$C$6, (W42 = 'Points-Table'!$A$7), 'Points-Table'!$C$7, (W42 = 'Points-Table'!$A$8), 'Points-Table'!$C$8, (W42 = 'Points-Table'!$A$9), 'Points-Table'!$C$9, (W42 = 'Points-Table'!$A$10), 'Points-Table'!$C$10, (W42 = 'Points-Table'!$A$11), 'Points-Table'!$C$11, (W42 = 'Points-Table'!$A$12), 'Points-Table'!$C$12, (W42 = 'Points-Table'!$A$13), 'Points-Table'!$C$13, true, 0 ) | Y42: 5 | Z42: =Ifs( (Y42 = 'Points-Table'!$A$4), 'Points-Table'!$C$4, (Y42 = 'Points-Table'!$A$5), 'Points-Table'!$C$5, (Y42 = 'Points-Table'!$A$6), 'Points-Table'!$C$6, (Y42 = 'Points-Table'!$A$7), 'Points-Table'!$C$7, (Y42 = 'Points-Table'!$A$8), 'Points-Table'!$C$8, (Y42 = 'Points-Table'!$A$9), 'Points-Table'!$C$9, (Y42 = 'Points-Table'!$A$10), 'Points-Table'!$C$10, (Y42 = 'Points-Table'!$A$11), 'Points-Table'!$C$11, (Y42 = 'Points-Table'!$A$12), 'Points-Table'!$C$12, (Y42 = 'Points-Table'!$A$13), 'Points-Table'!$C$13, true, 0 ) | AA42: =SUM(V42,X42,Z42) | AB42: =Ifs( ISBETWEEN(AA42, 0, 'Points-Table'!C$20, TRUE, False), 'Points-Table'!A$20, ISBETWEEN(AA42, 'Points-Table'!C$20, 'Points-Table'!C$21, TRUE, False), 'Points-Table'!A$21, ISBETWEEN(AA42, 'Points-Table'!C$22, 10000, TRUE, TRUE), 'Points-Table'!A$22, true, 0)
A43: My Bookings | B43: Modify Booking | D43: * | K43: Simple | L43: Must Have | Q43: 2 | R43: =Ifs( (Q43 = 'Points-Table'!$A$4), 'Points-Table'!$C$4, (Q43 = 'Points-Table'!$A$5), 'Points-Table'!$C$5, (Q43 = 'Points-Table'!$A$6), 'Points-Table'!$C$6, (Q43 = 'Points-Table'!$A$7), 'Points-Table'!$C$7, (Q43 = 'Points-Table'!$A$8), 'Points-Table'!$C$8, (Q43 = 'Points-Table'!$A$9), 'Points-Table'!$C$9, (Q43 = 'Points-Table'!$A$10), 'Points-Table'!$C$10, (Q43 = 'Points-Table'!$A$11), 'Points-Table'!$C$11, (Q43 = 'Points-Table'!$A$12), 'Points-Table'!$C$12, (Q43 = 'Points-Table'!$A$13), 'Points-Table'!$C$13, true, 0 ) | S43: 2 | T43: =Ifs( (S43 = 'Points-Table'!$A$4), 'Points-Table'!$C$4, (S43 = 'Points-Table'!$A$5), 'Points-Table'!$C$5, (S43 = 'Points-Table'!$A$6), 'Points-Table'!$C$6, (S43 = 'Points-Table'!$A$7), 'Points-Table'!$C$7, (S43 = 'Points-Table'!$A$8), 'Points-Table'!$C$8, (S43 = 'Points-Table'!$A$9), 'Points-Table'!$C$9, (S43 = 'Points-Table'!$A$10), 'Points-Table'!$C$10, (S43 = 'Points-Table'!$A$11), 'Points-Table'!$C$11, (S43 = 'Points-Table'!$A$12), 'Points-Table'!$C$12, (S43 = 'Points-Table'!$A$13), 'Points-Table'!$C$13, true, 0 ) | U43: 5 | V43: =Ifs( (U43 = 'Points-Table'!$A$4), 'Points-Table'!$C$4, (U43 = 'Points-Table'!$A$5), 'Points-Table'!$C$5, (U43 = 'Points-Table'!$A$6), 'Points-Table'!$C$6, (U43 = 'Points-Table'!$A$7), 'Points-Table'!$C$7, (U43 = 'Points-Table'!$A$8), 'Points-Table'!$C$8, (U43 = 'Points-Table'!$A$9), 'Points-Table'!$C$9, (U43 = 'Points-Table'!$A$10), 'Points-Table'!$C$10, (U43 = 'Points-Table'!$A$11), 'Points-Table'!$C$11, (U43 = 'Points-Table'!$A$12), 'Points-Table'!$C$12, (U43 = 'Points-Table'!$A$13), 'Points-Table'!$C$13, true, 0 ) | W43: 3 | X43: =Ifs( (W43 = 'Points-Table'!$A$4), 'Points-Table'!$C$4, (W43 = 'Points-Table'!$A$5), 'Points-Table'!$C$5, (W43 = 'Points-Table'!$A$6), 'Points-Table'!$C$6, (W43 = 'Points-Table'!$A$7), 'Points-Table'!$C$7, (W43 = 'Points-Table'!$A$8), 'Points-Table'!$C$8, (W43 = 'Points-Table'!$A$9), 'Points-Table'!$C$9, (W43 = 'Points-Table'!$A$10), 'Points-Table'!$C$10, (W43 = 'Points-Table'!$A$11), 'Points-Table'!$C$11, (W43 = 'Points-Table'!$A$12), 'Points-Table'!$C$12, (W43 = 'Points-Table'!$A$13), 'Points-Table'!$C$13, true, 0 ) | Y43: 5 | Z43: =Ifs( (Y43 = 'Points-Table'!$A$4), 'Points-Table'!$C$4, (Y43 = 'Points-Table'!$A$5), 'Points-Table'!$C$5, (Y43 = 'Points-Table'!$A$6), 'Points-Table'!$C$6, (Y43 = 'Points-Table'!$A$7), 'Points-Table'!$C$7, (Y43 = 'Points-Table'!$A$8), 'Points-Table'!$C$8, (Y43 = 'Points-Table'!$A$9), 'Points-Table'!$C$9, (Y43 = 'Points-Table'!$A$10), 'Points-Table'!$C$10, (Y43 = 'Points-Table'!$A$11), 'Points-Table'!$C$11, (Y43 = 'Points-Table'!$A$12), 'Points-Table'!$C$12, (Y43 = 'Points-Table'!$A$13), 'Points-Table'!$C$13, true, 0 ) | AA43: =SUM(V43,X43,Z43) | AB43: =Ifs( ISBETWEEN(AA43, 0, 'Points-Table'!C$20, TRUE, False), 'Points-Table'!A$20, ISBETWEEN(AA43, 'Points-Table'!C$20, 'Points-Table'!C$21, TRUE, False), 'Points-Table'!A$21, ISBETWEEN(AA43, 'Points-Table'!C$22, 10000, TRUE, TRUE), 'Points-Table'!A$22, true, 0)
A44: My Bookings | B44: Confirmation screen on Modification / Cancellation | D44: * | K44: Simple | L44: Must Have | Q44: 1 | R44: =Ifs( (Q44 = 'Points-Table'!$A$4), 'Points-Table'!$C$4, (Q44 = 'Points-Table'!$A$5), 'Points-Table'!$C$5, (Q44 = 'Points-Table'!$A$6), 'Points-Table'!$C$6, (Q44 = 'Points-Table'!$A$7), 'Points-Table'!$C$7, (Q44 = 'Points-Table'!$A$8), 'Points-Table'!$C$8, (Q44 = 'Points-Table'!$A$9), 'Points-Table'!$C$9, (Q44 = 'Points-Table'!$A$10), 'Points-Table'!$C$10, (Q44 = 'Points-Table'!$A$11), 'Points-Table'!$C$11, (Q44 = 'Points-Table'!$A$12), 'Points-Table'!$C$12, (Q44 = 'Points-Table'!$A$13), 'Points-Table'!$C$13, true, 0 ) | S44: 1 | T44: =Ifs( (S44 = 'Points-Table'!$A$4), 'Points-Table'!$C$4, (S44 = 'Points-Table'!$A$5), 'Points-Table'!$C$5, (S44 = 'Points-Table'!$A$6), 'Points-Table'!$C$6, (S44 = 'Points-Table'!$A$7), 'Points-Table'!$C$7, (S44 = 'Points-Table'!$A$8), 'Points-Table'!$C$8, (S44 = 'Points-Table'!$A$9), 'Points-Table'!$C$9, (S44 = 'Points-Table'!$A$10), 'Points-Table'!$C$10, (S44 = 'Points-Table'!$A$11), 'Points-Table'!$C$11, (S44 = 'Points-Table'!$A$12), 'Points-Table'!$C$12, (S44 = 'Points-Table'!$A$13), 'Points-Table'!$C$13, true, 0 ) | U44: 5 | V44: =Ifs( (U44 = 'Points-Table'!$A$4), 'Points-Table'!$C$4, (U44 = 'Points-Table'!$A$5), 'Points-Table'!$C$5, (U44 = 'Points-Table'!$A$6), 'Points-Table'!$C$6, (U44 = 'Points-Table'!$A$7), 'Points-Table'!$C$7, (U44 = 'Points-Table'!$A$8), 'Points-Table'!$C$8, (U44 = 'Points-Table'!$A$9), 'Points-Table'!$C$9, (U44 = 'Points-Table'!$A$10), 'Points-Table'!$C$10, (U44 = 'Points-Table'!$A$11), 'Points-Table'!$C$11, (U44 = 'Points-Table'!$A$12), 'Points-Table'!$C$12, (U44 = 'Points-Table'!$A$13), 'Points-Table'!$C$13, true, 0 ) | W44: 3 | X44: =Ifs( (W44 = 'Points-Table'!$A$4), 'Points-Table'!$C$4, (W44 = 'Points-Table'!$A$5), 'Points-Table'!$C$5, (W44 = 'Points-Table'!$A$6), 'Points-Table'!$C$6, (W44 = 'Points-Table'!$A$7), 'Points-Table'!$C$7, (W44 = 'Points-Table'!$A$8), 'Points-Table'!$C$8, (W44 = 'Points-Table'!$A$9), 'Points-Table'!$C$9, (W44 = 'Points-Table'!$A$10), 'Points-Table'!$C$10, (W44 = 'Points-Table'!$A$11), 'Points-Table'!$C$11, (W44 = 'Points-Table'!$A$12), 'Points-Table'!$C$12, (W44 = 'Points-Table'!$A$13), 'Points-Table'!$C$13, true, 0 ) | Y44: 5 | Z44: =Ifs( (Y44 = 'Points-Table'!$A$4), 'Points-Table'!$C$4, (Y44 = 'Points-Table'!$A$5), 'Points-Table'!$C$5, (Y44 = 'Points-Table'!$A$6), 'Points-Table'!$C$6, (Y44 = 'Points-Table'!$A$7), 'Points-Table'!$C$7, (Y44 = 'Points-Table'!$A$8), 'Points-Table'!$C$8, (Y44 = 'Points-Table'!$A$9), 'Points-Table'!$C$9, (Y44 = 'Points-Table'!$A$10), 'Points-Table'!$C$10, (Y44 = 'Points-Table'!$A$11), 'Points-Table'!$C$11, (Y44 = 'Points-Table'!$A$12), 'Points-Table'!$C$12, (Y44 = 'Points-Table'!$A$13), 'Points-Table'!$C$13, true, 0 ) | AA44: =SUM(V44,X44,Z44) | AB44: =Ifs( ISBETWEEN(AA44, 0, 'Points-Table'!C$20, TRUE, False), 'Points-Table'!A$20, ISBETWEEN(AA44, 'Points-Table'!C$20, 'Points-Table'!C$21, TRUE, False), 'Points-Table'!A$21, ISBETWEEN(AA44, 'Points-Table'!C$22, 10000, TRUE, TRUE), 'Points-Table'!A$22, true, 0)
A45: My Bookings | B45: Cancel Booking + Additional Remarks | D45: * | K45: Simple | L45: Must Have | Q45: 1 | R45: =Ifs( (Q45 = 'Points-Table'!$A$4), 'Points-Table'!$C$4, (Q45 = 'Points-Table'!$A$5), 'Points-Table'!$C$5, (Q45 = 'Points-Table'!$A$6), 'Points-Table'!$C$6, (Q45 = 'Points-Table'!$A$7), 'Points-Table'!$C$7, (Q45 = 'Points-Table'!$A$8), 'Points-Table'!$C$8, (Q45 = 'Points-Table'!$A$9), 'Points-Table'!$C$9, (Q45 = 'Points-Table'!$A$10), 'Points-Table'!$C$10, (Q45 = 'Points-Table'!$A$11), 'Points-Table'!$C$11, (Q45 = 'Points-Table'!$A$12), 'Points-Table'!$C$12, (Q45 = 'Points-Table'!$A$13), 'Points-Table'!$C$13, true, 0 ) | S45: 1 | T45: =Ifs( (S45 = 'Points-Table'!$A$4), 'Points-Table'!$C$4, (S45 = 'Points-Table'!$A$5), 'Points-Table'!$C$5, (S45 = 'Points-Table'!$A$6), 'Points-Table'!$C$6, (S45 = 'Points-Table'!$A$7), 'Points-Table'!$C$7, (S45 = 'Points-Table'!$A$8), 'Points-Table'!$C$8, (S45 = 'Points-Table'!$A$9), 'Points-Table'!$C$9, (S45 = 'Points-Table'!$A$10), 'Points-Table'!$C$10, (S45 = 'Points-Table'!$A$11), 'Points-Table'!$C$11, (S45 = 'Points-Table'!$A$12), 'Points-Table'!$C$12, (S45 = 'Points-Table'!$A$13), 'Points-Table'!$C$13, true, 0 ) | U45: 3 | V45: =Ifs( (U45 = 'Points-Table'!$A$4), 'Points-Table'!$C$4, (U45 = 'Points-Table'!$A$5), 'Points-Table'!$C$5, (U45 = 'Points-Table'!$A$6), 'Points-Table'!$C$6, (U45 = 'Points-Table'!$A$7), 'Points-Table'!$C$7, (U45 = 'Points-Table'!$A$8), 'Points-Table'!$C$8, (U45 = 'Points-Table'!$A$9), 'Points-Table'!$C$9, (U45 = 'Points-Table'!$A$10), 'Points-Table'!$C$10, (U45 = 'Points-Table'!$A$11), 'Points-Table'!$C$11, (U45 = 'Points-Table'!$A$12), 'Points-Table'!$C$12, (U45 = 'Points-Table'!$A$13), 'Points-Table'!$C$13, true, 0 ) | W45: 3 | X45: =Ifs( (W45 = 'Points-Table'!$A$4), 'Points-Table'!$C$4, (W45 = 'Points-Table'!$A$5), 'Points-Table'!$C$5, (W45 = 'Points-Table'!$A$6), 'Points-Table'!$C$6, (W45 = 'Points-Table'!$A$7), 'Points-Table'!$C$7, (W45 = 'Points-Table'!$A$8), 'Points-Table'!$C$8, (W45 = 'Points-Table'!$A$9), 'Points-Table'!$C$9, (W45 = 'Points-Table'!$A$10), 'Points-Table'!$C$10, (W45 = 'Points-Table'!$A$11), 'Points-Table'!$C$11, (W45 = 'Points-Table'!$A$12), 'Points-Table'!$C$12, (W45 = 'Points-Table'!$A$13), 'Points-Table'!$C$13, true, 0 ) | Y45: 5 | Z45: =Ifs( (Y45 = 'Points-Table'!$A$4), 'Points-Table'!$C$4, (Y45 = 'Points-Table'!$A$5), 'Points-Table'!$C$5, (Y45 = 'Points-Table'!$A$6), 'Points-Table'!$C$6, (Y45 = 'Points-Table'!$A$7), 'Points-Table'!$C$7, (Y45 = 'Points-Table'!$A$8), 'Points-Table'!$C$8, (Y45 = 'Points-Table'!$A$9), 'Points-Table'!$C$9, (Y45 = 'Points-Table'!$A$10), 'Points-Table'!$C$10, (Y45 = 'Points-Table'!$A$11), 'Points-Table'!$C$11, (Y45 = 'Points-Table'!$A$12), 'Points-Table'!$C$12, (Y45 = 'Points-Table'!$A$13), 'Points-Table'!$C$13, true, 0 ) | AA45: =SUM(V45,X45,Z45) | AB45: =Ifs( ISBETWEEN(AA45, 0, 'Points-Table'!C$20, TRUE, False), 'Points-Table'!A$20, ISBETWEEN(AA45, 'Points-Table'!C$20, 'Points-Table'!C$21, TRUE, False), 'Points-Table'!A$21, ISBETWEEN(AA45, 'Points-Table'!C$22, 10000, TRUE, TRUE), 'Points-Table'!A$22, true, 0)
A46: My Bookings | B46: Show cancellation / modification charges | K46: Simple | L46: Must Have | Q46: 1 | R46: =Ifs( (Q46 = 'Points-Table'!$A$4), 'Points-Table'!$C$4, (Q46 = 'Points-Table'!$A$5), 'Points-Table'!$C$5, (Q46 = 'Points-Table'!$A$6), 'Points-Table'!$C$6, (Q46 = 'Points-Table'!$A$7), 'Points-Table'!$C$7, (Q46 = 'Points-Table'!$A$8), 'Points-Table'!$C$8, (Q46 = 'Points-Table'!$A$9), 'Points-Table'!$C$9, (Q46 = 'Points-Table'!$A$10), 'Points-Table'!$C$10, (Q46 = 'Points-Table'!$A$11), 'Points-Table'!$C$11, (Q46 = 'Points-Table'!$A$12), 'Points-Table'!$C$12, (Q46 = 'Points-Table'!$A$13), 'Points-Table'!$C$13, true, 0 ) | S46: 1 | T46: =Ifs( (S46 = 'Points-Table'!$A$4), 'Points-Table'!$C$4, (S46 = 'Points-Table'!$A$5), 'Points-Table'!$C$5, (S46 = 'Points-Table'!$A$6), 'Points-Table'!$C$6, (S46 = 'Points-Table'!$A$7), 'Points-Table'!$C$7, (S46 = 'Points-Table'!$A$8), 'Points-Table'!$C$8, (S46 = 'Points-Table'!$A$9), 'Points-Table'!$C$9, (S46 = 'Points-Table'!$A$10), 'Points-Table'!$C$10, (S46 = 'Points-Table'!$A$11), 'Points-Table'!$C$11, (S46 = 'Points-Table'!$A$12), 'Points-Table'!$C$12, (S46 = 'Points-Table'!$A$13), 'Points-Table'!$C$13, true, 0 ) | U46: 5 | V46: =Ifs( (U46 = 'Points-Table'!$A$4), 'Points-Table'!$C$4, (U46 = 'Points-Table'!$A$5), 'Points-Table'!$C$5, (U46 = 'Points-Table'!$A$6), 'Points-Table'!$C$6, (U46 = 'Points-Table'!$A$7), 'Points-Table'!$C$7, (U46 = 'Points-Table'!$A$8), 'Points-Table'!$C$8, (U46 = 'Points-Table'!$A$9), 'Points-Table'!$C$9, (U46 = 'Points-Table'!$A$10), 'Points-Table'!$C$10, (U46 = 'Points-Table'!$A$11), 'Points-Table'!$C$11, (U46 = 'Points-Table'!$A$12), 'Points-Table'!$C$12, (U46 = 'Points-Table'!$A$13), 'Points-Table'!$C$13, true, 0 ) | W46: 2 | X46: =Ifs( (W46 = 'Points-Table'!$A$4), 'Points-Table'!$C$4, (W46 = 'Points-Table'!$A$5), 'Points-Table'!$C$5, (W46 = 'Points-Table'!$A$6), 'Points-Table'!$C$6, (W46 = 'Points-Table'!$A$7), 'Points-Table'!$C$7, (W46 = 'Points-Table'!$A$8), 'Points-Table'!$C$8, (W46 = 'Points-Table'!$A$9), 'Points-Table'!$C$9, (W46 = 'Points-Table'!$A$10), 'Points-Table'!$C$10, (W46 = 'Points-Table'!$A$11), 'Points-Table'!$C$11, (W46 = 'Points-Table'!$A$12), 'Points-Table'!$C$12, (W46 = 'Points-Table'!$A$13), 'Points-Table'!$C$13, true, 0 ) | Y46: 3 | Z46: =Ifs( (Y46 = 'Points-Table'!$A$4), 'Points-Table'!$C$4, (Y46 = 'Points-Table'!$A$5), 'Points-Table'!$C$5, (Y46 = 'Points-Table'!$A$6), 'Points-Table'!$C$6, (Y46 = 'Points-Table'!$A$7), 'Points-Table'!$C$7, (Y46 = 'Points-Table'!$A$8), 'Points-Table'!$C$8, (Y46 = 'Points-Table'!$A$9), 'Points-Table'!$C$9, (Y46 = 'Points-Table'!$A$10), 'Points-Table'!$C$10, (Y46 = 'Points-Table'!$A$11), 'Points-Table'!$C$11, (Y46 = 'Points-Table'!$A$12), 'Points-Table'!$C$12, (Y46 = 'Points-Table'!$A$13), 'Points-Table'!$C$13, true, 0 ) | AA46: =SUM(V46,X46,Z46) | AB46: =Ifs( ISBETWEEN(AA46, 0, 'Points-Table'!C$20, TRUE, False), 'Points-Table'!A$20, ISBETWEEN(AA46, 'Points-Table'!C$20, 'Points-Table'!C$21, TRUE, False), 'Points-Table'!A$21, ISBETWEEN(AA46, 'Points-Table'!C$22, 10000, TRUE, TRUE), 'Points-Table'!A$22, true, 0)
A47: My Bookings | B47: Make a payment (For modification) + Booking confirmation | K47: Simple | L47: Must Have | R47: =Ifs( (Q47 = 'Points-Table'!$A$4), 'Points-Table'!$C$4, (Q47 = 'Points-Table'!$A$5), 'Points-Table'!$C$5, (Q47 = 'Points-Table'!$A$6), 'Points-Table'!$C$6, (Q47 = 'Points-Table'!$A$7), 'Points-Table'!$C$7, (Q47 = 'Points-Table'!$A$8), 'Points-Table'!$C$8, (Q47 = 'Points-Table'!$A$9), 'Points-Table'!$C$9, (Q47 = 'Points-Table'!$A$10), 'Points-Table'!$C$10, (Q47 = 'Points-Table'!$A$11), 'Points-Table'!$C$11, (Q47 = 'Points-Table'!$A$12), 'Points-Table'!$C$12, (Q47 = 'Points-Table'!$A$13), 'Points-Table'!$C$13, true, 0 ) | T47: =Ifs( (S47 = 'Points-Table'!$A$4), 'Points-Table'!$C$4, (S47 = 'Points-Table'!$A$5), 'Points-Table'!$C$5, (S47 = 'Points-Table'!$A$6), 'Points-Table'!$C$6, (S47 = 'Points-Table'!$A$7), 'Points-Table'!$C$7, (S47 = 'Points-Table'!$A$8), 'Points-Table'!$C$8, (S47 = 'Points-Table'!$A$9), 'Points-Table'!$C$9, (S47 = 'Points-Table'!$A$10), 'Points-Table'!$C$10, (S47 = 'Points-Table'!$A$11), 'Points-Table'!$C$11, (S47 = 'Points-Table'!$A$12), 'Points-Table'!$C$12, (S47 = 'Points-Table'!$A$13), 'Points-Table'!$C$13, true, 0 ) | U47: 5 | V47: =Ifs( (U47 = 'Points-Table'!$A$4), 'Points-Table'!$C$4, (U47 = 'Points-Table'!$A$5), 'Points-Table'!$C$5, (U47 = 'Points-Table'!$A$6), 'Points-Table'!$C$6, (U47 = 'Points-Table'!$A$7), 'Points-Table'!$C$7, (U47 = 'Points-Table'!$A$8), 'Points-Table'!$C$8, (U47 = 'Points-Table'!$A$9), 'Points-Table'!$C$9, (U47 = 'Points-Table'!$A$10), 'Points-Table'!$C$10, (U47 = 'Points-Table'!$A$11), 'Points-Table'!$C$11, (U47 = 'Points-Table'!$A$12), 'Points-Table'!$C$12, (U47 = 'Points-Table'!$A$13), 'Points-Table'!$C$13, true, 0 ) | W47: 13 | X47: =Ifs( (W47 = 'Points-Table'!$A$4), 'Points-Table'!$C$4, (W47 = 'Points-Table'!$A$5), 'Points-Table'!$C$5, (W47 = 'Points-Table'!$A$6), 'Points-Table'!$C$6, (W47 = 'Points-Table'!$A$7), 'Points-Table'!$C$7, (W47 = 'Points-Table'!$A$8), 'Points-Table'!$C$8, (W47 = 'Points-Table'!$A$9), 'Points-Table'!$C$9, (W47 = 'Points-Table'!$A$10), 'Points-Table'!$C$10, (W47 = 'Points-Table'!$A$11), 'Points-Table'!$C$11, (W47 = 'Points-Table'!$A$12), 'Points-Table'!$C$12, (W47 = 'Points-Table'!$A$13), 'Points-Table'!$C$13, true, 0 ) | Y47: 8 | Z47: =Ifs( (Y47 = 'Points-Table'!$A$4), 'Points-Table'!$C$4, (Y47 = 'Points-Table'!$A$5), 'Points-Table'!$C$5, (Y47 = 'Points-Table'!$A$6), 'Points-Table'!$C$6, (Y47 = 'Points-Table'!$A$7), 'Points-Table'!$C$7, (Y47 = 'Points-Table'!$A$8), 'Points-Table'!$C$8, (Y47 = 'Points-Table'!$A$9), 'Points-Table'!$C$9, (Y47 = 'Points-Table'!$A$10), 'Points-Table'!$C$10, (Y47 = 'Points-Table'!$A$11), 'Points-Table'!$C$11, (Y47 = 'Points-Table'!$A$12), 'Points-Table'!$C$12, (Y47 = 'Points-Table'!$A$13), 'Points-Table'!$C$13, true, 0 ) | AA47: =SUM(V47,X47,Z47) | AB47: =Ifs( ISBETWEEN(AA47, 0, 'Points-Table'!C$20, TRUE, False), 'Points-Table'!A$20, ISBETWEEN(AA47, 'Points-Table'!C$20, 'Points-Table'!C$21, TRUE, False), 'Points-Table'!A$21, ISBETWEEN(AA47, 'Points-Table'!C$22, 10000, TRUE, TRUE), 'Points-Table'!A$22, true, 0)
A48: My Bookings | B48: Trigger email to Event Admin incase of cancellation | K48: Simple | L48: Must Have | R48: =Ifs( (Q48 = 'Points-Table'!$A$4), 'Points-Table'!$C$4, (Q48 = 'Points-Table'!$A$5), 'Points-Table'!$C$5, (Q48 = 'Points-Table'!$A$6), 'Points-Table'!$C$6, (Q48 = 'Points-Table'!$A$7), 'Points-Table'!$C$7, (Q48 = 'Points-Table'!$A$8), 'Points-Table'!$C$8, (Q48 = 'Points-Table'!$A$9), 'Points-Table'!$C$9, (Q48 = 'Points-Table'!$A$10), 'Points-Table'!$C$10, (Q48 = 'Points-Table'!$A$11), 'Points-Table'!$C$11, (Q48 = 'Points-Table'!$A$12), 'Points-Table'!$C$12, (Q48 = 'Points-Table'!$A$13), 'Points-Table'!$C$13, true, 0 ) | T48: =Ifs( (S48 = 'Points-Table'!$A$4), 'Points-Table'!$C$4, (S48 = 'Points-Table'!$A$5), 'Points-Table'!$C$5, (S48 = 'Points-Table'!$A$6), 'Points-Table'!$C$6, (S48 = 'Points-Table'!$A$7), 'Points-Table'!$C$7, (S48 = 'Points-Table'!$A$8), 'Points-Table'!$C$8, (S48 = 'Points-Table'!$A$9), 'Points-Table'!$C$9, (S48 = 'Points-Table'!$A$10), 'Points-Table'!$C$10, (S48 = 'Points-Table'!$A$11), 'Points-Table'!$C$11, (S48 = 'Points-Table'!$A$12), 'Points-Table'!$C$12, (S48 = 'Points-Table'!$A$13), 'Points-Table'!$C$13, true, 0 ) | U48: 5 | V48: =Ifs( (U48 = 'Points-Table'!$A$4), 'Points-Table'!$C$4, (U48 = 'Points-Table'!$A$5), 'Points-Table'!$C$5, (U48 = 'Points-Table'!$A$6), 'Points-Table'!$C$6, (U48 = 'Points-Table'!$A$7), 'Points-Table'!$C$7, (U48 = 'Points-Table'!$A$8), 'Points-Table'!$C$8, (U48 = 'Points-Table'!$A$9), 'Points-Table'!$C$9, (U48 = 'Points-Table'!$A$10), 'Points-Table'!$C$10, (U48 = 'Points-Table'!$A$11), 'Points-Table'!$C$11, (U48 = 'Points-Table'!$A$12), 'Points-Table'!$C$12, (U48 = 'Points-Table'!$A$13), 'Points-Table'!$C$13, true, 0 ) | W48: 0 | X48: =Ifs( (W48 = 'Points-Table'!$A$4), 'Points-Table'!$C$4, (W48 = 'Points-Table'!$A$5), 'Points-Table'!$C$5, (W48 = 'Points-Table'!$A$6), 'Points-Table'!$C$6, (W48 = 'Points-Table'!$A$7), 'Points-Table'!$C$7, (W48 = 'Points-Table'!$A$8), 'Points-Table'!$C$8, (W48 = 'Points-Table'!$A$9), 'Points-Table'!$C$9, (W48 = 'Points-Table'!$A$10), 'Points-Table'!$C$10, (W48 = 'Points-Table'!$A$11), 'Points-Table'!$C$11, (W48 = 'Points-Table'!$A$12), 'Points-Table'!$C$12, (W48 = 'Points-Table'!$A$13), 'Points-Table'!$C$13, true, 0 ) | Y48: 5 | Z48: =Ifs( (Y48 = 'Points-Table'!$A$4), 'Points-Table'!$C$4, (Y48 = 'Points-Table'!$A$5), 'Points-Table'!$C$5, (Y48 = 'Points-Table'!$A$6), 'Points-Table'!$C$6, (Y48 = 'Points-Table'!$A$7), 'Points-Table'!$C$7, (Y48 = 'Points-Table'!$A$8), 'Points-Table'!$C$8, (Y48 = 'Points-Table'!$A$9), 'Points-Table'!$C$9, (Y48 = 'Points-Table'!$A$10), 'Points-Table'!$C$10, (Y48 = 'Points-Table'!$A$11), 'Points-Table'!$C$11, (Y48 = 'Points-Table'!$A$12), 'Points-Table'!$C$12, (Y48 = 'Points-Table'!$A$13), 'Points-Table'!$C$13, true, 0 ) | AA48: =SUM(V48,X48,Z48) | AB48: =Ifs( ISBETWEEN(AA48, 0, 'Points-Table'!C$20, TRUE, False), 'Points-Table'!A$20, ISBETWEEN(AA48, 'Points-Table'!C$20, 'Points-Table'!C$21, TRUE, False), 'Points-Table'!A$21, ISBETWEEN(AA48, 'Points-Table'!C$22, 10000, TRUE, TRUE), 'Points-Table'!A$22, true, 0)
A49: My Bookings | B49: Download Invoice | D49: iInclude invoice setup with branding also here | F49: all booking transactional invoices considering here, invoice capture from stripe | K49: Simple | L49: Must Have | R49: =Ifs( (Q49 = 'Points-Table'!$A$4), 'Points-Table'!$C$4, (Q49 = 'Points-Table'!$A$5), 'Points-Table'!$C$5, (Q49 = 'Points-Table'!$A$6), 'Points-Table'!$C$6, (Q49 = 'Points-Table'!$A$7), 'Points-Table'!$C$7, (Q49 = 'Points-Table'!$A$8), 'Points-Table'!$C$8, (Q49 = 'Points-Table'!$A$9), 'Points-Table'!$C$9, (Q49 = 'Points-Table'!$A$10), 'Points-Table'!$C$10, (Q49 = 'Points-Table'!$A$11), 'Points-Table'!$C$11, (Q49 = 'Points-Table'!$A$12), 'Points-Table'!$C$12, (Q49 = 'Points-Table'!$A$13), 'Points-Table'!$C$13, true, 0 ) | T49: =Ifs( (S49 = 'Points-Table'!$A$4), 'Points-Table'!$C$4, (S49 = 'Points-Table'!$A$5), 'Points-Table'!$C$5, (S49 = 'Points-Table'!$A$6), 'Points-Table'!$C$6, (S49 = 'Points-Table'!$A$7), 'Points-Table'!$C$7, (S49 = 'Points-Table'!$A$8), 'Points-Table'!$C$8, (S49 = 'Points-Table'!$A$9), 'Points-Table'!$C$9, (S49 = 'Points-Table'!$A$10), 'Points-Table'!$C$10, (S49 = 'Points-Table'!$A$11), 'Points-Table'!$C$11, (S49 = 'Points-Table'!$A$12), 'Points-Table'!$C$12, (S49 = 'Points-Table'!$A$13), 'Points-Table'!$C$13, true, 0 ) | U49: 2 | V49: =Ifs( (U49 = 'Points-Table'!$A$4), 'Points-Table'!$C$4, (U49 = 'Points-Table'!$A$5), 'Points-Table'!$C$5, (U49 = 'Points-Table'!$A$6), 'Points-Table'!$C$6, (U49 = 'Points-Table'!$A$7), 'Points-Table'!$C$7, (U49 = 'Points-Table'!$A$8), 'Points-Table'!$C$8, (U49 = 'Points-Table'!$A$9), 'Points-Table'!$C$9, (U49 = 'Points-Table'!$A$10), 'Points-Table'!$C$10, (U49 = 'Points-Table'!$A$11), 'Points-Table'!$C$11, (U49 = 'Points-Table'!$A$12), 'Points-Table'!$C$12, (U49 = 'Points-Table'!$A$13), 'Points-Table'!$C$13, true, 0 ) | W49: 2 | X49: =Ifs( (W49 = 'Points-Table'!$A$4), 'Points-Table'!$C$4, (W49 = 'Points-Table'!$A$5), 'Points-Table'!$C$5, (W49 = 'Points-Table'!$A$6), 'Points-Table'!$C$6, (W49 = 'Points-Table'!$A$7), 'Points-Table'!$C$7, (W49 = 'Points-Table'!$A$8), 'Points-Table'!$C$8, (W49 = 'Points-Table'!$A$9), 'Points-Table'!$C$9, (W49 = 'Points-Table'!$A$10), 'Points-Table'!$C$10, (W49 = 'Points-Table'!$A$11), 'Points-Table'!$C$11, (W49 = 'Points-Table'!$A$12), 'Points-Table'!$C$12, (W49 = 'Points-Table'!$A$13), 'Points-Table'!$C$13, true, 0 ) | Y49: 8 | Z49: =Ifs( (Y49 = 'Points-Table'!$A$4), 'Points-Table'!$C$4, (Y49 = 'Points-Table'!$A$5), 'Points-Table'!$C$5, (Y49 = 'Points-Table'!$A$6), 'Points-Table'!$C$6, (Y49 = 'Points-Table'!$A$7), 'Points-Table'!$C$7, (Y49 = 'Points-Table'!$A$8), 'Points-Table'!$C$8, (Y49 = 'Points-Table'!$A$9), 'Points-Table'!$C$9, (Y49 = 'Points-Table'!$A$10), 'Points-Table'!$C$10, (Y49 = 'Points-Table'!$A$11), 'Points-Table'!$C$11, (Y49 = 'Points-Table'!$A$12), 'Points-Table'!$C$12, (Y49 = 'Points-Table'!$A$13), 'Points-Table'!$C$13, true, 0 ) | AA49: =SUM(V49,X49,Z49) | AB49: =Ifs( ISBETWEEN(AA49, 0, 'Points-Table'!C$20, TRUE, False), 'Points-Table'!A$20, ISBETWEEN(AA49, 'Points-Table'!C$20, 'Points-Table'!C$21, TRUE, False), 'Points-Table'!A$21, ISBETWEEN(AA49, 'Points-Table'!C$22, 10000, TRUE, TRUE), 'Points-Table'!A$22, true, 0)
A50: My Bookings | B50: Search | Sort | Filter | K50: Simple | L50: Must Have | R50: =Ifs( (Q50 = 'Points-Table'!$A$4), 'Points-Table'!$C$4, (Q50 = 'Points-Table'!$A$5), 'Points-Table'!$C$5, (Q50 = 'Points-Table'!$A$6), 'Points-Table'!$C$6, (Q50 = 'Points-Table'!$A$7), 'Points-Table'!$C$7, (Q50 = 'Points-Table'!$A$8), 'Points-Table'!$C$8, (Q50 = 'Points-Table'!$A$9), 'Points-Table'!$C$9, (Q50 = 'Points-Table'!$A$10), 'Points-Table'!$C$10, (Q50 = 'Points-Table'!$A$11), 'Points-Table'!$C$11, (Q50 = 'Points-Table'!$A$12), 'Points-Table'!$C$12, (Q50 = 'Points-Table'!$A$13), 'Points-Table'!$C$13, true, 0 ) | T50: =Ifs( (S50 = 'Points-Table'!$A$4), 'Points-Table'!$C$4, (S50 = 'Points-Table'!$A$5), 'Points-Table'!$C$5, (S50 = 'Points-Table'!$A$6), 'Points-Table'!$C$6, (S50 = 'Points-Table'!$A$7), 'Points-Table'!$C$7, (S50 = 'Points-Table'!$A$8), 'Points-Table'!$C$8, (S50 = 'Points-Table'!$A$9), 'Points-Table'!$C$9, (S50 = 'Points-Table'!$A$10), 'Points-Table'!$C$10, (S50 = 'Points-Table'!$A$11), 'Points-Table'!$C$11, (S50 = 'Points-Table'!$A$12), 'Points-Table'!$C$12, (S50 = 'Points-Table'!$A$13), 'Points-Table'!$C$13, true, 0 ) | U50: 5 | V50: =Ifs( (U50 = 'Points-Table'!$A$4), 'Points-Table'!$C$4, (U50 = 'Points-Table'!$A$5), 'Points-Table'!$C$5, (U50 = 'Points-Table'!$A$6), 'Points-Table'!$C$6, (U50 = 'Points-Table'!$A$7), 'Points-Table'!$C$7, (U50 = 'Points-Table'!$A$8), 'Points-Table'!$C$8, (U50 = 'Points-Table'!$A$9), 'Points-Table'!$C$9, (U50 = 'Points-Table'!$A$10), 'Points-Table'!$C$10, (U50 = 'Points-Table'!$A$11), 'Points-Table'!$C$11, (U50 = 'Points-Table'!$A$12), 'Points-Table'!$C$12, (U50 = 'Points-Table'!$A$13), 'Points-Table'!$C$13, true, 0 ) | W50: 3 | X50: =Ifs( (W50 = 'Points-Table'!$A$4), 'Points-Table'!$C$4, (W50 = 'Points-Table'!$A$5), 'Points-Table'!$C$5, (W50 = 'Points-Table'!$A$6), 'Points-Table'!$C$6, (W50 = 'Points-Table'!$A$7), 'Points-Table'!$C$7, (W50 = 'Points-Table'!$A$8), 'Points-Table'!$C$8, (W50 = 'Points-Table'!$A$9), 'Points-Table'!$C$9, (W50 = 'Points-Table'!$A$10), 'Points-Table'!$C$10, (W50 = 'Points-Table'!$A$11), 'Points-Table'!$C$11, (W50 = 'Points-Table'!$A$12), 'Points-Table'!$C$12, (W50 = 'Points-Table'!$A$13), 'Points-Table'!$C$13, true, 0 ) | Y50: 5 | Z50: =Ifs( (Y50 = 'Points-Table'!$A$4), 'Points-Table'!$C$4, (Y50 = 'Points-Table'!$A$5), 'Points-Table'!$C$5, (Y50 = 'Points-Table'!$A$6), 'Points-Table'!$C$6, (Y50 = 'Points-Table'!$A$7), 'Points-Table'!$C$7, (Y50 = 'Points-Table'!$A$8), 'Points-Table'!$C$8, (Y50 = 'Points-Table'!$A$9), 'Points-Table'!$C$9, (Y50 = 'Points-Table'!$A$10), 'Points-Table'!$C$10, (Y50 = 'Points-Table'!$A$11), 'Points-Table'!$C$11, (Y50 = 'Points-Table'!$A$12), 'Points-Table'!$C$12, (Y50 = 'Points-Table'!$A$13), 'Points-Table'!$C$13, true, 0 ) | AA50: =SUM(V50,X50,Z50) | AB50: =Ifs( ISBETWEEN(AA50, 0, 'Points-Table'!C$20, TRUE, False), 'Points-Table'!A$20, ISBETWEEN(AA50, 'Points-Table'!C$20, 'Points-Table'!C$21, TRUE, False), 'Points-Table'!A$21, ISBETWEEN(AA50, 'Points-Table'!C$22, 10000, TRUE, TRUE), 'Points-Table'!A$22, true, 0)
A51: Notifications | B51: Booking confirmation Email | D51: Email to the user immediately after booking with all details. Optionally, send a summary to relevant admins or hotel contacts if needed (for example, the hotel could get a daily report of new reservations). | K51: Simple | L51: Must Have | Q51: 1 | R51: =Ifs( (Q51 = 'Points-Table'!$A$4), 'Points-Table'!$C$4, (Q51 = 'Points-Table'!$A$5), 'Points-Table'!$C$5, (Q51 = 'Points-Table'!$A$6), 'Points-Table'!$C$6, (Q51 = 'Points-Table'!$A$7), 'Points-Table'!$C$7, (Q51 = 'Points-Table'!$A$8), 'Points-Table'!$C$8, (Q51 = 'Points-Table'!$A$9), 'Points-Table'!$C$9, (Q51 = 'Points-Table'!$A$10), 'Points-Table'!$C$10, (Q51 = 'Points-Table'!$A$11), 'Points-Table'!$C$11, (Q51 = 'Points-Table'!$A$12), 'Points-Table'!$C$12, (Q51 = 'Points-Table'!$A$13), 'Points-Table'!$C$13, true, 0 ) | S51: 3 | T51: =Ifs( (S51 = 'Points-Table'!$A$4), 'Points-Table'!$C$4, (S51 = 'Points-Table'!$A$5), 'Points-Table'!$C$5, (S51 = 'Points-Table'!$A$6), 'Points-Table'!$C$6, (S51 = 'Points-Table'!$A$7), 'Points-Table'!$C$7, (S51 = 'Points-Table'!$A$8), 'Points-Table'!$C$8, (S51 = 'Points-Table'!$A$9), 'Points-Table'!$C$9, (S51 = 'Points-Table'!$A$10), 'Points-Table'!$C$10, (S51 = 'Points-Table'!$A$11), 'Points-Table'!$C$11, (S51 = 'Points-Table'!$A$12), 'Points-Table'!$C$12, (S51 = 'Points-Table'!$A$13), 'Points-Table'!$C$13, true, 0 ) | U51: 2 | V51: =Ifs( (U51 = 'Points-Table'!$A$4), 'Points-Table'!$C$4, (U51 = 'Points-Table'!$A$5), 'Points-Table'!$C$5, (U51 = 'Points-Table'!$A$6), 'Points-Table'!$C$6, (U51 = 'Points-Table'!$A$7), 'Points-Table'!$C$7, (U51 = 'Points-Table'!$A$8), 'Points-Table'!$C$8, (U51 = 'Points-Table'!$A$9), 'Points-Table'!$C$9, (U51 = 'Points-Table'!$A$10), 'Points-Table'!$C$10, (U51 = 'Points-Table'!$A$11), 'Points-Table'!$C$11, (U51 = 'Points-Table'!$A$12), 'Points-Table'!$C$12, (U51 = 'Points-Table'!$A$13), 'Points-Table'!$C$13, true, 0 ) | W51: 2 | X51: =Ifs( (W51 = 'Points-Table'!$A$4), 'Points-Table'!$C$4, (W51 = 'Points-Table'!$A$5), 'Points-Table'!$C$5, (W51 = 'Points-Table'!$A$6), 'Points-Table'!$C$6, (W51 = 'Points-Table'!$A$7), 'Points-Table'!$C$7, (W51 = 'Points-Table'!$A$8), 'Points-Table'!$C$8, (W51 = 'Points-Table'!$A$9), 'Points-Table'!$C$9, (W51 = 'Points-Table'!$A$10), 'Points-Table'!$C$10, (W51 = 'Points-Table'!$A$11), 'Points-Table'!$C$11, (W51 = 'Points-Table'!$A$12), 'Points-Table'!$C$12, (W51 = 'Points-Table'!$A$13), 'Points-Table'!$C$13, true, 0 ) | Y51: 13 | Z51: =Ifs( (Y51 = 'Points-Table'!$A$4), 'Points-Table'!$C$4, (Y51 = 'Points-Table'!$A$5), 'Points-Table'!$C$5, (Y51 = 'Points-Table'!$A$6), 'Points-Table'!$C$6, (Y51 = 'Points-Table'!$A$7), 'Points-Table'!$C$7, (Y51 = 'Points-Table'!$A$8), 'Points-Table'!$C$8, (Y51 = 'Points-Table'!$A$9), 'Points-Table'!$C$9, (Y51 = 'Points-Table'!$A$10), 'Points-Table'!$C$10, (Y51 = 'Points-Table'!$A$11), 'Points-Table'!$C$11, (Y51 = 'Points-Table'!$A$12), 'Points-Table'!$C$12, (Y51 = 'Points-Table'!$A$13), 'Points-Table'!$C$13, true, 0 ) | AA51: =SUM(V51,X51,Z51) | AB51: =Ifs( ISBETWEEN(AA51, 0, 'Points-Table'!C$20, TRUE, False), 'Points-Table'!A$20, ISBETWEEN(AA51, 'Points-Table'!C$20, 'Points-Table'!C$21, TRUE, False), 'Points-Table'!A$21, ISBETWEEN(AA51, 'Points-Table'!C$22, 10000, TRUE, TRUE), 'Points-Table'!A$22, true, 0)
A52: Notifications | B52: Post-Modification Notices: | D52: If a booking is changed or canceled, send an updated confirmation or a cancellation notice to the user. If admin approval was needed for a change, notify the user that their request has been processed or require further action. | K52: Simple | L52: Must Have | Q52: 1 | R52: =Ifs( (Q52 = 'Points-Table'!$A$4), 'Points-Table'!$C$4, (Q52 = 'Points-Table'!$A$5), 'Points-Table'!$C$5, (Q52 = 'Points-Table'!$A$6), 'Points-Table'!$C$6, (Q52 = 'Points-Table'!$A$7), 'Points-Table'!$C$7, (Q52 = 'Points-Table'!$A$8), 'Points-Table'!$C$8, (Q52 = 'Points-Table'!$A$9), 'Points-Table'!$C$9, (Q52 = 'Points-Table'!$A$10), 'Points-Table'!$C$10, (Q52 = 'Points-Table'!$A$11), 'Points-Table'!$C$11, (Q52 = 'Points-Table'!$A$12), 'Points-Table'!$C$12, (Q52 = 'Points-Table'!$A$13), 'Points-Table'!$C$13, true, 0 ) | S52: 3 | T52: =Ifs( (S52 = 'Points-Table'!$A$4), 'Points-Table'!$C$4, (S52 = 'Points-Table'!$A$5), 'Points-Table'!$C$5, (S52 = 'Points-Table'!$A$6), 'Points-Table'!$C$6, (S52 = 'Points-Table'!$A$7), 'Points-Table'!$C$7, (S52 = 'Points-Table'!$A$8), 'Points-Table'!$C$8, (S52 = 'Points-Table'!$A$9), 'Points-Table'!$C$9, (S52 = 'Points-Table'!$A$10), 'Points-Table'!$C$10, (S52 = 'Points-Table'!$A$11), 'Points-Table'!$C$11, (S52 = 'Points-Table'!$A$12), 'Points-Table'!$C$12, (S52 = 'Points-Table'!$A$13), 'Points-Table'!$C$13, true, 0 ) | U52: 3 | V52: =Ifs( (U52 = 'Points-Table'!$A$4), 'Points-Table'!$C$4, (U52 = 'Points-Table'!$A$5), 'Points-Table'!$C$5, (U52 = 'Points-Table'!$A$6), 'Points-Table'!$C$6, (U52 = 'Points-Table'!$A$7), 'Points-Table'!$C$7, (U52 = 'Points-Table'!$A$8), 'Points-Table'!$C$8, (U52 = 'Points-Table'!$A$9), 'Points-Table'!$C$9, (U52 = 'Points-Table'!$A$10), 'Points-Table'!$C$10, (U52 = 'Points-Table'!$A$11), 'Points-Table'!$C$11, (U52 = 'Points-Table'!$A$12), 'Points-Table'!$C$12, (U52 = 'Points-Table'!$A$13), 'Points-Table'!$C$13, true, 0 ) | W52: 1 | X52: =Ifs( (W52 = 'Points-Table'!$A$4), 'Points-Table'!$C$4, (W52 = 'Points-Table'!$A$5), 'Points-Table'!$C$5, (W52 = 'Points-Table'!$A$6), 'Points-Table'!$C$6, (W52 = 'Points-Table'!$A$7), 'Points-Table'!$C$7, (W52 = 'Points-Table'!$A$8), 'Points-Table'!$C$8, (W52 = 'Points-Table'!$A$9), 'Points-Table'!$C$9, (W52 = 'Points-Table'!$A$10), 'Points-Table'!$C$10, (W52 = 'Points-Table'!$A$11), 'Points-Table'!$C$11, (W52 = 'Points-Table'!$A$12), 'Points-Table'!$C$12, (W52 = 'Points-Table'!$A$13), 'Points-Table'!$C$13, true, 0 ) | Y52: 8 | Z52: =Ifs( (Y52 = 'Points-Table'!$A$4), 'Points-Table'!$C$4, (Y52 = 'Points-Table'!$A$5), 'Points-Table'!$C$5, (Y52 = 'Points-Table'!$A$6), 'Points-Table'!$C$6, (Y52 = 'Points-Table'!$A$7), 'Points-Table'!$C$7, (Y52 = 'Points-Table'!$A$8), 'Points-Table'!$C$8, (Y52 = 'Points-Table'!$A$9), 'Points-Table'!$C$9, (Y52 = 'Points-Table'!$A$10), 'Points-Table'!$C$10, (Y52 = 'Points-Table'!$A$11), 'Points-Table'!$C$11, (Y52 = 'Points-Table'!$A$12), 'Points-Table'!$C$12, (Y52 = 'Points-Table'!$A$13), 'Points-Table'!$C$13, true, 0 ) | AA52: =SUM(V52,X52,Z52) | AB52: =Ifs( ISBETWEEN(AA52, 0, 'Points-Table'!C$20, TRUE, False), 'Points-Table'!A$20, ISBETWEEN(AA52, 'Points-Table'!C$20, 'Points-Table'!C$21, TRUE, False), 'Points-Table'!A$21, ISBETWEEN(AA52, 'Points-Table'!C$22, 10000, TRUE, TRUE), 'Points-Table'!A$22, true, 0)
A53: Contact Support (Contact info) | D53: Contact mail id is mentioned | K53: Simple | L53: Must Have | Q53: 2 | R53: =Ifs( (Q53 = 'Points-Table'!$A$4), 'Points-Table'!$C$4, (Q53 = 'Points-Table'!$A$5), 'Points-Table'!$C$5, (Q53 = 'Points-Table'!$A$6), 'Points-Table'!$C$6, (Q53 = 'Points-Table'!$A$7), 'Points-Table'!$C$7, (Q53 = 'Points-Table'!$A$8), 'Points-Table'!$C$8, (Q53 = 'Points-Table'!$A$9), 'Points-Table'!$C$9, (Q53 = 'Points-Table'!$A$10), 'Points-Table'!$C$10, (Q53 = 'Points-Table'!$A$11), 'Points-Table'!$C$11, (Q53 = 'Points-Table'!$A$12), 'Points-Table'!$C$12, (Q53 = 'Points-Table'!$A$13), 'Points-Table'!$C$13, true, 0 ) | S53: 2 | T53: =Ifs( (S53 = 'Points-Table'!$A$4), 'Points-Table'!$C$4, (S53 = 'Points-Table'!$A$5), 'Points-Table'!$C$5, (S53 = 'Points-Table'!$A$6), 'Points-Table'!$C$6, (S53 = 'Points-Table'!$A$7), 'Points-Table'!$C$7, (S53 = 'Points-Table'!$A$8), 'Points-Table'!$C$8, (S53 = 'Points-Table'!$A$9), 'Points-Table'!$C$9, (S53 = 'Points-Table'!$A$10), 'Points-Table'!$C$10, (S53 = 'Points-Table'!$A$11), 'Points-Table'!$C$11, (S53 = 'Points-Table'!$A$12), 'Points-Table'!$C$12, (S53 = 'Points-Table'!$A$13), 'Points-Table'!$C$13, true, 0 ) | U53: 3 | V53: =Ifs( (U53 = 'Points-Table'!$A$4), 'Points-Table'!$C$4, (U53 = 'Points-Table'!$A$5), 'Points-Table'!$C$5, (U53 = 'Points-Table'!$A$6), 'Points-Table'!$C$6, (U53 = 'Points-Table'!$A$7), 'Points-Table'!$C$7, (U53 = 'Points-Table'!$A$8), 'Points-Table'!$C$8, (U53 = 'Points-Table'!$A$9), 'Points-Table'!$C$9, (U53 = 'Points-Table'!$A$10), 'Points-Table'!$C$10, (U53 = 'Points-Table'!$A$11), 'Points-Table'!$C$11, (U53 = 'Points-Table'!$A$12), 'Points-Table'!$C$12, (U53 = 'Points-Table'!$A$13), 'Points-Table'!$C$13, true, 0 ) | W53: 2 | X53: =Ifs( (W53 = 'Points-Table'!$A$4), 'Points-Table'!$C$4, (W53 = 'Points-Table'!$A$5), 'Points-Table'!$C$5, (W53 = 'Points-Table'!$A$6), 'Points-Table'!$C$6, (W53 = 'Points-Table'!$A$7), 'Points-Table'!$C$7, (W53 = 'Points-Table'!$A$8), 'Points-Table'!$C$8, (W53 = 'Points-Table'!$A$9), 'Points-Table'!$C$9, (W53 = 'Points-Table'!$A$10), 'Points-Table'!$C$10, (W53 = 'Points-Table'!$A$11), 'Points-Table'!$C$11, (W53 = 'Points-Table'!$A$12), 'Points-Table'!$C$12, (W53 = 'Points-Table'!$A$13), 'Points-Table'!$C$13, true, 0 ) | Y53: 3 | Z53: =Ifs( (Y53 = 'Points-Table'!$A$4), 'Points-Table'!$C$4, (Y53 = 'Points-Table'!$A$5), 'Points-Table'!$C$5, (Y53 = 'Points-Table'!$A$6), 'Points-Table'!$C$6, (Y53 = 'Points-Table'!$A$7), 'Points-Table'!$C$7, (Y53 = 'Points-Table'!$A$8), 'Points-Table'!$C$8, (Y53 = 'Points-Table'!$A$9), 'Points-Table'!$C$9, (Y53 = 'Points-Table'!$A$10), 'Points-Table'!$C$10, (Y53 = 'Points-Table'!$A$11), 'Points-Table'!$C$11, (Y53 = 'Points-Table'!$A$12), 'Points-Table'!$C$12, (Y53 = 'Points-Table'!$A$13), 'Points-Table'!$C$13, true, 0 ) | AA53: =SUM(V53,X53,Z53) | AB53: =Ifs( ISBETWEEN(AA53, 0, 'Points-Table'!C$20, TRUE, False), 'Points-Table'!A$20, ISBETWEEN(AA53, 'Points-Table'!C$20, 'Points-Table'!C$21, TRUE, False), 'Points-Table'!A$21, ISBETWEEN(AA53, 'Points-Table'!C$22, 10000, TRUE, TRUE), 'Points-Table'!A$22, true, 0)
A54: Profile | D54: We just have logout under Profile | F54: view and edit is considered | K54: Simple | L54: Must Have | Q54: 3 | R54: =Ifs( (Q54 = 'Points-Table'!$A$4), 'Points-Table'!$C$4, (Q54 = 'Points-Table'!$A$5), 'Points-Table'!$C$5, (Q54 = 'Points-Table'!$A$6), 'Points-Table'!$C$6, (Q54 = 'Points-Table'!$A$7), 'Points-Table'!$C$7, (Q54 = 'Points-Table'!$A$8), 'Points-Table'!$C$8, (Q54 = 'Points-Table'!$A$9), 'Points-Table'!$C$9, (Q54 = 'Points-Table'!$A$10), 'Points-Table'!$C$10, (Q54 = 'Points-Table'!$A$11), 'Points-Table'!$C$11, (Q54 = 'Points-Table'!$A$12), 'Points-Table'!$C$12, (Q54 = 'Points-Table'!$A$13), 'Points-Table'!$C$13, true, 0 ) | S54: 3 | T54: =Ifs( (S54 = 'Points-Table'!$A$4), 'Points-Table'!$C$4, (S54 = 'Points-Table'!$A$5), 'Points-Table'!$C$5, (S54 = 'Points-Table'!$A$6), 'Points-Table'!$C$6, (S54 = 'Points-Table'!$A$7), 'Points-Table'!$C$7, (S54 = 'Points-Table'!$A$8), 'Points-Table'!$C$8, (S54 = 'Points-Table'!$A$9), 'Points-Table'!$C$9, (S54 = 'Points-Table'!$A$10), 'Points-Table'!$C$10, (S54 = 'Points-Table'!$A$11), 'Points-Table'!$C$11, (S54 = 'Points-Table'!$A$12), 'Points-Table'!$C$12, (S54 = 'Points-Table'!$A$13), 'Points-Table'!$C$13, true, 0 ) | U54: 8 | V54: =Ifs( (U54 = 'Points-Table'!$A$4), 'Points-Table'!$C$4, (U54 = 'Points-Table'!$A$5), 'Points-Table'!$C$5, (U54 = 'Points-Table'!$A$6), 'Points-Table'!$C$6, (U54 = 'Points-Table'!$A$7), 'Points-Table'!$C$7, (U54 = 'Points-Table'!$A$8), 'Points-Table'!$C$8, (U54 = 'Points-Table'!$A$9), 'Points-Table'!$C$9, (U54 = 'Points-Table'!$A$10), 'Points-Table'!$C$10, (U54 = 'Points-Table'!$A$11), 'Points-Table'!$C$11, (U54 = 'Points-Table'!$A$12), 'Points-Table'!$C$12, (U54 = 'Points-Table'!$A$13), 'Points-Table'!$C$13, true, 0 ) | W54: 5 | X54: =Ifs( (W54 = 'Points-Table'!$A$4), 'Points-Table'!$C$4, (W54 = 'Points-Table'!$A$5), 'Points-Table'!$C$5, (W54 = 'Points-Table'!$A$6), 'Points-Table'!$C$6, (W54 = 'Points-Table'!$A$7), 'Points-Table'!$C$7, (W54 = 'Points-Table'!$A$8), 'Points-Table'!$C$8, (W54 = 'Points-Table'!$A$9), 'Points-Table'!$C$9, (W54 = 'Points-Table'!$A$10), 'Points-Table'!$C$10, (W54 = 'Points-Table'!$A$11), 'Points-Table'!$C$11, (W54 = 'Points-Table'!$A$12), 'Points-Table'!$C$12, (W54 = 'Points-Table'!$A$13), 'Points-Table'!$C$13, true, 0 ) | Y54: 8 | Z54: =Ifs( (Y54 = 'Points-Table'!$A$4), 'Points-Table'!$C$4, (Y54 = 'Points-Table'!$A$5), 'Points-Table'!$C$5, (Y54 = 'Points-Table'!$A$6), 'Points-Table'!$C$6, (Y54 = 'Points-Table'!$A$7), 'Points-Table'!$C$7, (Y54 = 'Points-Table'!$A$8), 'Points-Table'!$C$8, (Y54 = 'Points-Table'!$A$9), 'Points-Table'!$C$9, (Y54 = 'Points-Table'!$A$10), 'Points-Table'!$C$10, (Y54 = 'Points-Table'!$A$11), 'Points-Table'!$C$11, (Y54 = 'Points-Table'!$A$12), 'Points-Table'!$C$12, (Y54 = 'Points-Table'!$A$13), 'Points-Table'!$C$13, true, 0 ) | AA54: =SUM(V54,X54,Z54) | AB54: =Ifs( ISBETWEEN(AA54, 0, 'Points-Table'!C$20, TRUE, False), 'Points-Table'!A$20, ISBETWEEN(AA54, 'Points-Table'!C$20, 'Points-Table'!C$21, TRUE, False), 'Points-Table'!A$21, ISBETWEEN(AA54, 'Points-Table'!C$22, 10000, TRUE, TRUE), 'Points-Table'!A$22, true, 0)
A55: Logout | K55: Simple | L55: Must Have | R55: =Ifs( (Q55 = 'Points-Table'!$A$4), 'Points-Table'!$C$4, (Q55 = 'Points-Table'!$A$5), 'Points-Table'!$C$5, (Q55 = 'Points-Table'!$A$6), 'Points-Table'!$C$6, (Q55 = 'Points-Table'!$A$7), 'Points-Table'!$C$7, (Q55 = 'Points-Table'!$A$8), 'Points-Table'!$C$8, (Q55 = 'Points-Table'!$A$9), 'Points-Table'!$C$9, (Q55 = 'Points-Table'!$A$10), 'Points-Table'!$C$10, (Q55 = 'Points-Table'!$A$11), 'Points-Table'!$C$11, (Q55 = 'Points-Table'!$A$12), 'Points-Table'!$C$12, (Q55 = 'Points-Table'!$A$13), 'Points-Table'!$C$13, true, 0 ) | T55: =Ifs( (S55 = 'Points-Table'!$A$4), 'Points-Table'!$C$4, (S55 = 'Points-Table'!$A$5), 'Points-Table'!$C$5, (S55 = 'Points-Table'!$A$6), 'Points-Table'!$C$6, (S55 = 'Points-Table'!$A$7), 'Points-Table'!$C$7, (S55 = 'Points-Table'!$A$8), 'Points-Table'!$C$8, (S55 = 'Points-Table'!$A$9), 'Points-Table'!$C$9, (S55 = 'Points-Table'!$A$10), 'Points-Table'!$C$10, (S55 = 'Points-Table'!$A$11), 'Points-Table'!$C$11, (S55 = 'Points-Table'!$A$12), 'Points-Table'!$C$12, (S55 = 'Points-Table'!$A$13), 'Points-Table'!$C$13, true, 0 ) | U55: 1 | V55: =Ifs( (U55 = 'Points-Table'!$A$4), 'Points-Table'!$C$4, (U55 = 'Points-Table'!$A$5), 'Points-Table'!$C$5, (U55 = 'Points-Table'!$A$6), 'Points-Table'!$C$6, (U55 = 'Points-Table'!$A$7), 'Points-Table'!$C$7, (U55 = 'Points-Table'!$A$8), 'Points-Table'!$C$8, (U55 = 'Points-Table'!$A$9), 'Points-Table'!$C$9, (U55 = 'Points-Table'!$A$10), 'Points-Table'!$C$10, (U55 = 'Points-Table'!$A$11), 'Points-Table'!$C$11, (U55 = 'Points-Table'!$A$12), 'Points-Table'!$C$12, (U55 = 'Points-Table'!$A$13), 'Points-Table'!$C$13, true, 0 ) | W55: 1 | X55: =Ifs( (W55 = 'Points-Table'!$A$4), 'Points-Table'!$C$4, (W55 = 'Points-Table'!$A$5), 'Points-Table'!$C$5, (W55 = 'Points-Table'!$A$6), 'Points-Table'!$C$6, (W55 = 'Points-Table'!$A$7), 'Points-Table'!$C$7, (W55 = 'Points-Table'!$A$8), 'Points-Table'!$C$8, (W55 = 'Points-Table'!$A$9), 'Points-Table'!$C$9, (W55 = 'Points-Table'!$A$10), 'Points-Table'!$C$10, (W55 = 'Points-Table'!$A$11), 'Points-Table'!$C$11, (W55 = 'Points-Table'!$A$12), 'Points-Table'!$C$12, (W55 = 'Points-Table'!$A$13), 'Points-Table'!$C$13, true, 0 ) | Y55: 0 | Z55: =Ifs( (Y55 = 'Points-Table'!$A$4), 'Points-Table'!$C$4, (Y55 = 'Points-Table'!$A$5), 'Points-Table'!$C$5, (Y55 = 'Points-Table'!$A$6), 'Points-Table'!$C$6, (Y55 = 'Points-Table'!$A$7), 'Points-Table'!$C$7, (Y55 = 'Points-Table'!$A$8), 'Points-Table'!$C$8, (Y55 = 'Points-Table'!$A$9), 'Points-Table'!$C$9, (Y55 = 'Points-Table'!$A$10), 'Points-Table'!$C$10, (Y55 = 'Points-Table'!$A$11), 'Points-Table'!$C$11, (Y55 = 'Points-Table'!$A$12), 'Points-Table'!$C$12, (Y55 = 'Points-Table'!$A$13), 'Points-Table'!$C$13, true, 0 ) | AA55: =SUM(V55,X55,Z55) | AB55: =Ifs( ISBETWEEN(AA55, 0, 'Points-Table'!C$20, TRUE, False), 'Points-Table'!A$20, ISBETWEEN(AA55, 'Points-Table'!C$20, 'Points-Table'!C$21, TRUE, False), 'Points-Table'!A$21, ISBETWEEN(AA55, 'Points-Table'!C$22, 10000, TRUE, TRUE), 'Points-Table'!A$22, true, 0)
A56: User journey Analytics Integration(Optional) | F56: basic Firebase basic event based analytics | K56: Simple | L56: Must Have | Q56: 0 | R56: =Ifs( (Q56 = 'Points-Table'!$A$4), 'Points-Table'!$C$4, (Q56 = 'Points-Table'!$A$5), 'Points-Table'!$C$5, (Q56 = 'Points-Table'!$A$6), 'Points-Table'!$C$6, (Q56 = 'Points-Table'!$A$7), 'Points-Table'!$C$7, (Q56 = 'Points-Table'!$A$8), 'Points-Table'!$C$8, (Q56 = 'Points-Table'!$A$9), 'Points-Table'!$C$9, (Q56 = 'Points-Table'!$A$10), 'Points-Table'!$C$10, (Q56 = 'Points-Table'!$A$11), 'Points-Table'!$C$11, (Q56 = 'Points-Table'!$A$12), 'Points-Table'!$C$12, (Q56 = 'Points-Table'!$A$13), 'Points-Table'!$C$13, true, 0 ) | S56: 0 | T56: =Ifs( (S56 = 'Points-Table'!$A$4), 'Points-Table'!$C$4, (S56 = 'Points-Table'!$A$5), 'Points-Table'!$C$5, (S56 = 'Points-Table'!$A$6), 'Points-Table'!$C$6, (S56 = 'Points-Table'!$A$7), 'Points-Table'!$C$7, (S56 = 'Points-Table'!$A$8), 'Points-Table'!$C$8, (S56 = 'Points-Table'!$A$9), 'Points-Table'!$C$9, (S56 = 'Points-Table'!$A$10), 'Points-Table'!$C$10, (S56 = 'Points-Table'!$A$11), 'Points-Table'!$C$11, (S56 = 'Points-Table'!$A$12), 'Points-Table'!$C$12, (S56 = 'Points-Table'!$A$13), 'Points-Table'!$C$13, true, 0 ) | U56: 0 | V56: =Ifs( (U56 = 'Points-Table'!$A$4), 'Points-Table'!$C$4, (U56 = 'Points-Table'!$A$5), 'Points-Table'!$C$5, (U56 = 'Points-Table'!$A$6), 'Points-Table'!$C$6, (U56 = 'Points-Table'!$A$7), 'Points-Table'!$C$7, (U56 = 'Points-Table'!$A$8), 'Points-Table'!$C$8, (U56 = 'Points-Table'!$A$9), 'Points-Table'!$C$9, (U56 = 'Points-Table'!$A$10), 'Points-Table'!$C$10, (U56 = 'Points-Table'!$A$11), 'Points-Table'!$C$11, (U56 = 'Points-Table'!$A$12), 'Points-Table'!$C$12, (U56 = 'Points-Table'!$A$13), 'Points-Table'!$C$13, true, 0 ) | W56: 34 | X56: =Ifs( (W56 = 'Points-Table'!$A$4), 'Points-Table'!$C$4, (W56 = 'Points-Table'!$A$5), 'Points-Table'!$C$5, (W56 = 'Points-Table'!$A$6), 'Points-Table'!$C$6, (W56 = 'Points-Table'!$A$7), 'Points-Table'!$C$7, (W56 = 'Points-Table'!$A$8), 'Points-Table'!$C$8, (W56 = 'Points-Table'!$A$9), 'Points-Table'!$C$9, (W56 = 'Points-Table'!$A$10), 'Points-Table'!$C$10, (W56 = 'Points-Table'!$A$11), 'Points-Table'!$C$11, (W56 = 'Points-Table'!$A$12), 'Points-Table'!$C$12, (W56 = 'Points-Table'!$A$13), 'Points-Table'!$C$13, true, 0 ) | Y56: 0 | Z56: =Ifs( (Y56 = 'Points-Table'!$A$4), 'Points-Table'!$C$4, (Y56 = 'Points-Table'!$A$5), 'Points-Table'!$C$5, (Y56 = 'Points-Table'!$A$6), 'Points-Table'!$C$6, (Y56 = 'Points-Table'!$A$7), 'Points-Table'!$C$7, (Y56 = 'Points-Table'!$A$8), 'Points-Table'!$C$8, (Y56 = 'Points-Table'!$A$9), 'Points-Table'!$C$9, (Y56 = 'Points-Table'!$A$10), 'Points-Table'!$C$10, (Y56 = 'Points-Table'!$A$11), 'Points-Table'!$C$11, (Y56 = 'Points-Table'!$A$12), 'Points-Table'!$C$12, (Y56 = 'Points-Table'!$A$13), 'Points-Table'!$C$13, true, 0 ) | AA56: =SUM(V56,X56,Z56) | AB56: =Ifs( ISBETWEEN(AA56, 0, 'Points-Table'!C$20, TRUE, False), 'Points-Table'!A$20, ISBETWEEN(AA56, 'Points-Table'!C$20, 'Points-Table'!C$21, TRUE, False), 'Points-Table'!A$21, ISBETWEEN(AA56, 'Points-Table'!C$22, 10000, TRUE, TRUE), 'Points-Table'!A$22, true, 0)
A57: Tab Responsive | K57: Simple | L57: Must Have | Q57: 13 | R57: =Ifs( (Q57 = 'Points-Table'!$A$4), 'Points-Table'!$C$4, (Q57 = 'Points-Table'!$A$5), 'Points-Table'!$C$5, (Q57 = 'Points-Table'!$A$6), 'Points-Table'!$C$6, (Q57 = 'Points-Table'!$A$7), 'Points-Table'!$C$7, (Q57 = 'Points-Table'!$A$8), 'Points-Table'!$C$8, (Q57 = 'Points-Table'!$A$9), 'Points-Table'!$C$9, (Q57 = 'Points-Table'!$A$10), 'Points-Table'!$C$10, (Q57 = 'Points-Table'!$A$11), 'Points-Table'!$C$11, (Q57 = 'Points-Table'!$A$12), 'Points-Table'!$C$12, (Q57 = 'Points-Table'!$A$13), 'Points-Table'!$C$13, true, 0 ) | S57: 34 | T57: =Ifs( (S57 = 'Points-Table'!$A$4), 'Points-Table'!$C$4, (S57 = 'Points-Table'!$A$5), 'Points-Table'!$C$5, (S57 = 'Points-Table'!$A$6), 'Points-Table'!$C$6, (S57 = 'Points-Table'!$A$7), 'Points-Table'!$C$7, (S57 = 'Points-Table'!$A$8), 'Points-Table'!$C$8, (S57 = 'Points-Table'!$A$9), 'Points-Table'!$C$9, (S57 = 'Points-Table'!$A$10), 'Points-Table'!$C$10, (S57 = 'Points-Table'!$A$11), 'Points-Table'!$C$11, (S57 = 'Points-Table'!$A$12), 'Points-Table'!$C$12, (S57 = 'Points-Table'!$A$13), 'Points-Table'!$C$13, true, 0 ) | U57: 21 | V57: =Ifs( (U57 = 'Points-Table'!$A$4), 'Points-Table'!$C$4, (U57 = 'Points-Table'!$A$5), 'Points-Table'!$C$5, (U57 = 'Points-Table'!$A$6), 'Points-Table'!$C$6, (U57 = 'Points-Table'!$A$7), 'Points-Table'!$C$7, (U57 = 'Points-Table'!$A$8), 'Points-Table'!$C$8, (U57 = 'Points-Table'!$A$9), 'Points-Table'!$C$9, (U57 = 'Points-Table'!$A$10), 'Points-Table'!$C$10, (U57 = 'Points-Table'!$A$11), 'Points-Table'!$C$11, (U57 = 'Points-Table'!$A$12), 'Points-Table'!$C$12, (U57 = 'Points-Table'!$A$13), 'Points-Table'!$C$13, true, 0 ) | W57: 0 | X57: =Ifs( (W57 = 'Points-Table'!$A$4), 'Points-Table'!$C$4, (W57 = 'Points-Table'!$A$5), 'Points-Table'!$C$5, (W57 = 'Points-Table'!$A$6), 'Points-Table'!$C$6, (W57 = 'Points-Table'!$A$7), 'Points-Table'!$C$7, (W57 = 'Points-Table'!$A$8), 'Points-Table'!$C$8, (W57 = 'Points-Table'!$A$9), 'Points-Table'!$C$9, (W57 = 'Points-Table'!$A$10), 'Points-Table'!$C$10, (W57 = 'Points-Table'!$A$11), 'Points-Table'!$C$11, (W57 = 'Points-Table'!$A$12), 'Points-Table'!$C$12, (W57 = 'Points-Table'!$A$13), 'Points-Table'!$C$13, true, 0 ) | Y57: 0 | Z57: =Ifs( (Y57 = 'Points-Table'!$A$4), 'Points-Table'!$C$4, (Y57 = 'Points-Table'!$A$5), 'Points-Table'!$C$5, (Y57 = 'Points-Table'!$A$6), 'Points-Table'!$C$6, (Y57 = 'Points-Table'!$A$7), 'Points-Table'!$C$7, (Y57 = 'Points-Table'!$A$8), 'Points-Table'!$C$8, (Y57 = 'Points-Table'!$A$9), 'Points-Table'!$C$9, (Y57 = 'Points-Table'!$A$10), 'Points-Table'!$C$10, (Y57 = 'Points-Table'!$A$11), 'Points-Table'!$C$11, (Y57 = 'Points-Table'!$A$12), 'Points-Table'!$C$12, (Y57 = 'Points-Table'!$A$13), 'Points-Table'!$C$13, true, 0 ) | AA57: =SUM(V57,X57,Z57) | AB57: =Ifs( ISBETWEEN(AA57, 0, 'Points-Table'!C$20, TRUE, False), 'Points-Table'!A$20, ISBETWEEN(AA57, 'Points-Table'!C$20, 'Points-Table'!C$21, TRUE, False), 'Points-Table'!A$21, ISBETWEEN(AA57, 'Points-Table'!C$22, 10000, TRUE, TRUE), 'Points-Table'!A$22, true, 0)
A58: Mobile Responsive | K58: Simple | L58: Must Have | Q58: 5 | R58: =Ifs( (Q58 = 'Points-Table'!$A$4), 'Points-Table'!$C$4, (Q58 = 'Points-Table'!$A$5), 'Points-Table'!$C$5, (Q58 = 'Points-Table'!$A$6), 'Points-Table'!$C$6, (Q58 = 'Points-Table'!$A$7), 'Points-Table'!$C$7, (Q58 = 'Points-Table'!$A$8), 'Points-Table'!$C$8, (Q58 = 'Points-Table'!$A$9), 'Points-Table'!$C$9, (Q58 = 'Points-Table'!$A$10), 'Points-Table'!$C$10, (Q58 = 'Points-Table'!$A$11), 'Points-Table'!$C$11, (Q58 = 'Points-Table'!$A$12), 'Points-Table'!$C$12, (Q58 = 'Points-Table'!$A$13), 'Points-Table'!$C$13, true, 0 ) | S58: 55 | T58: =Ifs( (S58 = 'Points-Table'!$A$4), 'Points-Table'!$C$4, (S58 = 'Points-Table'!$A$5), 'Points-Table'!$C$5, (S58 = 'Points-Table'!$A$6), 'Points-Table'!$C$6, (S58 = 'Points-Table'!$A$7), 'Points-Table'!$C$7, (S58 = 'Points-Table'!$A$8), 'Points-Table'!$C$8, (S58 = 'Points-Table'!$A$9), 'Points-Table'!$C$9, (S58 = 'Points-Table'!$A$10), 'Points-Table'!$C$10, (S58 = 'Points-Table'!$A$11), 'Points-Table'!$C$11, (S58 = 'Points-Table'!$A$12), 'Points-Table'!$C$12, (S58 = 'Points-Table'!$A$13), 'Points-Table'!$C$13, true, 0 ) | U58: 21 | V58: =Ifs( (U58 = 'Points-Table'!$A$4), 'Points-Table'!$C$4, (U58 = 'Points-Table'!$A$5), 'Points-Table'!$C$5, (U58 = 'Points-Table'!$A$6), 'Points-Table'!$C$6, (U58 = 'Points-Table'!$A$7), 'Points-Table'!$C$7, (U58 = 'Points-Table'!$A$8), 'Points-Table'!$C$8, (U58 = 'Points-Table'!$A$9), 'Points-Table'!$C$9, (U58 = 'Points-Table'!$A$10), 'Points-Table'!$C$10, (U58 = 'Points-Table'!$A$11), 'Points-Table'!$C$11, (U58 = 'Points-Table'!$A$12), 'Points-Table'!$C$12, (U58 = 'Points-Table'!$A$13), 'Points-Table'!$C$13, true, 0 ) | W58: 0 | X58: =Ifs( (W58 = 'Points-Table'!$A$4), 'Points-Table'!$C$4, (W58 = 'Points-Table'!$A$5), 'Points-Table'!$C$5, (W58 = 'Points-Table'!$A$6), 'Points-Table'!$C$6, (W58 = 'Points-Table'!$A$7), 'Points-Table'!$C$7, (W58 = 'Points-Table'!$A$8), 'Points-Table'!$C$8, (W58 = 'Points-Table'!$A$9), 'Points-Table'!$C$9, (W58 = 'Points-Table'!$A$10), 'Points-Table'!$C$10, (W58 = 'Points-Table'!$A$11), 'Points-Table'!$C$11, (W58 = 'Points-Table'!$A$12), 'Points-Table'!$C$12, (W58 = 'Points-Table'!$A$13), 'Points-Table'!$C$13, true, 0 ) | Y58: 0 | Z58: =Ifs( (Y58 = 'Points-Table'!$A$4), 'Points-Table'!$C$4, (Y58 = 'Points-Table'!$A$5), 'Points-Table'!$C$5, (Y58 = 'Points-Table'!$A$6), 'Points-Table'!$C$6, (Y58 = 'Points-Table'!$A$7), 'Points-Table'!$C$7, (Y58 = 'Points-Table'!$A$8), 'Points-Table'!$C$8, (Y58 = 'Points-Table'!$A$9), 'Points-Table'!$C$9, (Y58 = 'Points-Table'!$A$10), 'Points-Table'!$C$10, (Y58 = 'Points-Table'!$A$11), 'Points-Table'!$C$11, (Y58 = 'Points-Table'!$A$12), 'Points-Table'!$C$12, (Y58 = 'Points-Table'!$A$13), 'Points-Table'!$C$13, true, 0 ) | AA58: =SUM(V58,X58,Z58) | AB58: =Ifs( ISBETWEEN(AA58, 0, 'Points-Table'!C$20, TRUE, False), 'Points-Table'!A$20, ISBETWEEN(AA58, 'Points-Table'!C$20, 'Points-Table'!C$21, TRUE, False), 'Points-Table'!A$21, ISBETWEEN(AA58, 'Points-Table'!C$22, 10000, TRUE, TRUE), 'Points-Table'!A$22, true, 0)
A59: Join Waitlist for Sold-out rooms | K59: Simple | L59: Must Have | R59: =Ifs( (Q59 = 'Points-Table'!$A$4), 'Points-Table'!$C$4, (Q59 = 'Points-Table'!$A$5), 'Points-Table'!$C$5, (Q59 = 'Points-Table'!$A$6), 'Points-Table'!$C$6, (Q59 = 'Points-Table'!$A$7), 'Points-Table'!$C$7, (Q59 = 'Points-Table'!$A$8), 'Points-Table'!$C$8, (Q59 = 'Points-Table'!$A$9), 'Points-Table'!$C$9, (Q59 = 'Points-Table'!$A$10), 'Points-Table'!$C$10, (Q59 = 'Points-Table'!$A$11), 'Points-Table'!$C$11, (Q59 = 'Points-Table'!$A$12), 'Points-Table'!$C$12, (Q59 = 'Points-Table'!$A$13), 'Points-Table'!$C$13, true, 0 ) | T59: =Ifs( (S59 = 'Points-Table'!$A$4), 'Points-Table'!$C$4, (S59 = 'Points-Table'!$A$5), 'Points-Table'!$C$5, (S59 = 'Points-Table'!$A$6), 'Points-Table'!$C$6, (S59 = 'Points-Table'!$A$7), 'Points-Table'!$C$7, (S59 = 'Points-Table'!$A$8), 'Points-Table'!$C$8, (S59 = 'Points-Table'!$A$9), 'Points-Table'!$C$9, (S59 = 'Points-Table'!$A$10), 'Points-Table'!$C$10, (S59 = 'Points-Table'!$A$11), 'Points-Table'!$C$11, (S59 = 'Points-Table'!$A$12), 'Points-Table'!$C$12, (S59 = 'Points-Table'!$A$13), 'Points-Table'!$C$13, true, 0 ) | V59: =Ifs( (U59 = 'Points-Table'!$A$4), 'Points-Table'!$C$4, (U59 = 'Points-Table'!$A$5), 'Points-Table'!$C$5, (U59 = 'Points-Table'!$A$6), 'Points-Table'!$C$6, (U59 = 'Points-Table'!$A$7), 'Points-Table'!$C$7, (U59 = 'Points-Table'!$A$8), 'Points-Table'!$C$8, (U59 = 'Points-Table'!$A$9), 'Points-Table'!$C$9, (U59 = 'Points-Table'!$A$10), 'Points-Table'!$C$10, (U59 = 'Points-Table'!$A$11), 'Points-Table'!$C$11, (U59 = 'Points-Table'!$A$12), 'Points-Table'!$C$12, (U59 = 'Points-Table'!$A$13), 'Points-Table'!$C$13, true, 0 ) | X59: =Ifs( (W59 = 'Points-Table'!$A$4), 'Points-Table'!$C$4, (W59 = 'Points-Table'!$A$5), 'Points-Table'!$C$5, (W59 = 'Points-Table'!$A$6), 'Points-Table'!$C$6, (W59 = 'Points-Table'!$A$7), 'Points-Table'!$C$7, (W59 = 'Points-Table'!$A$8), 'Points-Table'!$C$8, (W59 = 'Points-Table'!$A$9), 'Points-Table'!$C$9, (W59 = 'Points-Table'!$A$10), 'Points-Table'!$C$10, (W59 = 'Points-Table'!$A$11), 'Points-Table'!$C$11, (W59 = 'Points-Table'!$A$12), 'Points-Table'!$C$12, (W59 = 'Points-Table'!$A$13), 'Points-Table'!$C$13, true, 0 ) | Z59: =Ifs( (Y59 = 'Points-Table'!$A$4), 'Points-Table'!$C$4, (Y59 = 'Points-Table'!$A$5), 'Points-Table'!$C$5, (Y59 = 'Points-Table'!$A$6), 'Points-Table'!$C$6, (Y59 = 'Points-Table'!$A$7), 'Points-Table'!$C$7, (Y59 = 'Points-Table'!$A$8), 'Points-Table'!$C$8, (Y59 = 'Points-Table'!$A$9), 'Points-Table'!$C$9, (Y59 = 'Points-Table'!$A$10), 'Points-Table'!$C$10, (Y59 = 'Points-Table'!$A$11), 'Points-Table'!$C$11, (Y59 = 'Points-Table'!$A$12), 'Points-Table'!$C$12, (Y59 = 'Points-Table'!$A$13), 'Points-Table'!$C$13, true, 0 ) | AA59: =SUM(V59,X59,Z59) | AB59: =Ifs( ISBETWEEN(AA59, 0, 'Points-Table'!C$20, TRUE, False), 'Points-Table'!A$20, ISBETWEEN(AA59, 'Points-Table'!C$20, 'Points-Table'!C$21, TRUE, False), 'Points-Table'!A$21, ISBETWEEN(AA59, 'Points-Table'!C$22, 10000, TRUE, TRUE), 'Points-Table'!A$22, true, 0)
A60: UX Process | B60: Competitive Analysis | K60: Simple | L60: Must Have | Q60: 21 | R60: =Ifs( (Q60 = 'Points-Table'!$A$4), 'Points-Table'!$C$4, (Q60 = 'Points-Table'!$A$5), 'Points-Table'!$C$5, (Q60 = 'Points-Table'!$A$6), 'Points-Table'!$C$6, (Q60 = 'Points-Table'!$A$7), 'Points-Table'!$C$7, (Q60 = 'Points-Table'!$A$8), 'Points-Table'!$C$8, (Q60 = 'Points-Table'!$A$9), 'Points-Table'!$C$9, (Q60 = 'Points-Table'!$A$10), 'Points-Table'!$C$10, (Q60 = 'Points-Table'!$A$11), 'Points-Table'!$C$11, (Q60 = 'Points-Table'!$A$12), 'Points-Table'!$C$12, (Q60 = 'Points-Table'!$A$13), 'Points-Table'!$C$13, true, 0 ) | T60: =Ifs( (S60 = 'Points-Table'!$A$4), 'Points-Table'!$C$4, (S60 = 'Points-Table'!$A$5), 'Points-Table'!$C$5, (S60 = 'Points-Table'!$A$6), 'Points-Table'!$C$6, (S60 = 'Points-Table'!$A$7), 'Points-Table'!$C$7, (S60 = 'Points-Table'!$A$8), 'Points-Table'!$C$8, (S60 = 'Points-Table'!$A$9), 'Points-Table'!$C$9, (S60 = 'Points-Table'!$A$10), 'Points-Table'!$C$10, (S60 = 'Points-Table'!$A$11), 'Points-Table'!$C$11, (S60 = 'Points-Table'!$A$12), 'Points-Table'!$C$12, (S60 = 'Points-Table'!$A$13), 'Points-Table'!$C$13, true, 0 ) | U60: 0 | V60: =Ifs( (U60 = 'Points-Table'!$A$4), 'Points-Table'!$C$4, (U60 = 'Points-Table'!$A$5), 'Points-Table'!$C$5, (U60 = 'Points-Table'!$A$6), 'Points-Table'!$C$6, (U60 = 'Points-Table'!$A$7), 'Points-Table'!$C$7, (U60 = 'Points-Table'!$A$8), 'Points-Table'!$C$8, (U60 = 'Points-Table'!$A$9), 'Points-Table'!$C$9, (U60 = 'Points-Table'!$A$10), 'Points-Table'!$C$10, (U60 = 'Points-Table'!$A$11), 'Points-Table'!$C$11, (U60 = 'Points-Table'!$A$12), 'Points-Table'!$C$12, (U60 = 'Points-Table'!$A$13), 'Points-Table'!$C$13, true, 0 ) | W60: 0 | X60: =Ifs( (W60 = 'Points-Table'!$A$4), 'Points-Table'!$C$4, (W60 = 'Points-Table'!$A$5), 'Points-Table'!$C$5, (W60 = 'Points-Table'!$A$6), 'Points-Table'!$C$6, (W60 = 'Points-Table'!$A$7), 'Points-Table'!$C$7, (W60 = 'Points-Table'!$A$8), 'Points-Table'!$C$8, (W60 = 'Points-Table'!$A$9), 'Points-Table'!$C$9, (W60 = 'Points-Table'!$A$10), 'Points-Table'!$C$10, (W60 = 'Points-Table'!$A$11), 'Points-Table'!$C$11, (W60 = 'Points-Table'!$A$12), 'Points-Table'!$C$12, (W60 = 'Points-Table'!$A$13), 'Points-Table'!$C$13, true, 0 ) | Y60: 0 | Z60: =Ifs( (Y60 = 'Points-Table'!$A$4), 'Points-Table'!$C$4, (Y60 = 'Points-Table'!$A$5), 'Points-Table'!$C$5, (Y60 = 'Points-Table'!$A$6), 'Points-Table'!$C$6, (Y60 = 'Points-Table'!$A$7), 'Points-Table'!$C$7, (Y60 = 'Points-Table'!$A$8), 'Points-Table'!$C$8, (Y60 = 'Points-Table'!$A$9), 'Points-Table'!$C$9, (Y60 = 'Points-Table'!$A$10), 'Points-Table'!$C$10, (Y60 = 'Points-Table'!$A$11), 'Points-Table'!$C$11, (Y60 = 'Points-Table'!$A$12), 'Points-Table'!$C$12, (Y60 = 'Points-Table'!$A$13), 'Points-Table'!$C$13, true, 0 ) | AA60: =SUM(V60,X60,Z60) | AB60: =Ifs( ISBETWEEN(AA60, 0, 'Points-Table'!C$20, TRUE, False), 'Points-Table'!A$20, ISBETWEEN(AA60, 'Points-Table'!C$20, 'Points-Table'!C$21, TRUE, False), 'Points-Table'!A$21, ISBETWEEN(AA60, 'Points-Table'!C$22, 10000, TRUE, TRUE), 'Points-Table'!A$22, true, 0)
A61: UX Process | B61: User Flow | K61: Simple | L61: Must Have | Q61: 21 | R61: =Ifs( (Q61 = 'Points-Table'!$A$4), 'Points-Table'!$C$4, (Q61 = 'Points-Table'!$A$5), 'Points-Table'!$C$5, (Q61 = 'Points-Table'!$A$6), 'Points-Table'!$C$6, (Q61 = 'Points-Table'!$A$7), 'Points-Table'!$C$7, (Q61 = 'Points-Table'!$A$8), 'Points-Table'!$C$8, (Q61 = 'Points-Table'!$A$9), 'Points-Table'!$C$9, (Q61 = 'Points-Table'!$A$10), 'Points-Table'!$C$10, (Q61 = 'Points-Table'!$A$11), 'Points-Table'!$C$11, (Q61 = 'Points-Table'!$A$12), 'Points-Table'!$C$12, (Q61 = 'Points-Table'!$A$13), 'Points-Table'!$C$13, true, 0 ) | T61: =Ifs( (S61 = 'Points-Table'!$A$4), 'Points-Table'!$C$4, (S61 = 'Points-Table'!$A$5), 'Points-Table'!$C$5, (S61 = 'Points-Table'!$A$6), 'Points-Table'!$C$6, (S61 = 'Points-Table'!$A$7), 'Points-Table'!$C$7, (S61 = 'Points-Table'!$A$8), 'Points-Table'!$C$8, (S61 = 'Points-Table'!$A$9), 'Points-Table'!$C$9, (S61 = 'Points-Table'!$A$10), 'Points-Table'!$C$10, (S61 = 'Points-Table'!$A$11), 'Points-Table'!$C$11, (S61 = 'Points-Table'!$A$12), 'Points-Table'!$C$12, (S61 = 'Points-Table'!$A$13), 'Points-Table'!$C$13, true, 0 ) | U61: 0 | V61: =Ifs( (U61 = 'Points-Table'!$A$4), 'Points-Table'!$C$4, (U61 = 'Points-Table'!$A$5), 'Points-Table'!$C$5, (U61 = 'Points-Table'!$A$6), 'Points-Table'!$C$6, (U61 = 'Points-Table'!$A$7), 'Points-Table'!$C$7, (U61 = 'Points-Table'!$A$8), 'Points-Table'!$C$8, (U61 = 'Points-Table'!$A$9), 'Points-Table'!$C$9, (U61 = 'Points-Table'!$A$10), 'Points-Table'!$C$10, (U61 = 'Points-Table'!$A$11), 'Points-Table'!$C$11, (U61 = 'Points-Table'!$A$12), 'Points-Table'!$C$12, (U61 = 'Points-Table'!$A$13), 'Points-Table'!$C$13, true, 0 ) | W61: 0 | X61: =Ifs( (W61 = 'Points-Table'!$A$4), 'Points-Table'!$C$4, (W61 = 'Points-Table'!$A$5), 'Points-Table'!$C$5, (W61 = 'Points-Table'!$A$6), 'Points-Table'!$C$6, (W61 = 'Points-Table'!$A$7), 'Points-Table'!$C$7, (W61 = 'Points-Table'!$A$8), 'Points-Table'!$C$8, (W61 = 'Points-Table'!$A$9), 'Points-Table'!$C$9, (W61 = 'Points-Table'!$A$10), 'Points-Table'!$C$10, (W61 = 'Points-Table'!$A$11), 'Points-Table'!$C$11, (W61 = 'Points-Table'!$A$12), 'Points-Table'!$C$12, (W61 = 'Points-Table'!$A$13), 'Points-Table'!$C$13, true, 0 ) | Y61: 0 | Z61: =Ifs( (Y61 = 'Points-Table'!$A$4), 'Points-Table'!$C$4, (Y61 = 'Points-Table'!$A$5), 'Points-Table'!$C$5, (Y61 = 'Points-Table'!$A$6), 'Points-Table'!$C$6, (Y61 = 'Points-Table'!$A$7), 'Points-Table'!$C$7, (Y61 = 'Points-Table'!$A$8), 'Points-Table'!$C$8, (Y61 = 'Points-Table'!$A$9), 'Points-Table'!$C$9, (Y61 = 'Points-Table'!$A$10), 'Points-Table'!$C$10, (Y61 = 'Points-Table'!$A$11), 'Points-Table'!$C$11, (Y61 = 'Points-Table'!$A$12), 'Points-Table'!$C$12, (Y61 = 'Points-Table'!$A$13), 'Points-Table'!$C$13, true, 0 ) | AA61: =SUM(V61,X61,Z61) | AB61: =Ifs( ISBETWEEN(AA61, 0, 'Points-Table'!C$20, TRUE, False), 'Points-Table'!A$20, ISBETWEEN(AA61, 'Points-Table'!C$20, 'Points-Table'!C$21, TRUE, False), 'Points-Table'!A$21, ISBETWEEN(AA61, 'Points-Table'!C$22, 10000, TRUE, TRUE), 'Points-Table'!A$22, true, 0)
A62: UX Process | B62: Brainstorming & Research | K62: Simple | L62: Must Have | Q62: 13 | R62: =Ifs( (Q62 = 'Points-Table'!$A$4), 'Points-Table'!$C$4, (Q62 = 'Points-Table'!$A$5), 'Points-Table'!$C$5, (Q62 = 'Points-Table'!$A$6), 'Points-Table'!$C$6, (Q62 = 'Points-Table'!$A$7), 'Points-Table'!$C$7, (Q62 = 'Points-Table'!$A$8), 'Points-Table'!$C$8, (Q62 = 'Points-Table'!$A$9), 'Points-Table'!$C$9, (Q62 = 'Points-Table'!$A$10), 'Points-Table'!$C$10, (Q62 = 'Points-Table'!$A$11), 'Points-Table'!$C$11, (Q62 = 'Points-Table'!$A$12), 'Points-Table'!$C$12, (Q62 = 'Points-Table'!$A$13), 'Points-Table'!$C$13, true, 0 ) | T62: =Ifs( (S62 = 'Points-Table'!$A$4), 'Points-Table'!$C$4, (S62 = 'Points-Table'!$A$5), 'Points-Table'!$C$5, (S62 = 'Points-Table'!$A$6), 'Points-Table'!$C$6, (S62 = 'Points-Table'!$A$7), 'Points-Table'!$C$7, (S62 = 'Points-Table'!$A$8), 'Points-Table'!$C$8, (S62 = 'Points-Table'!$A$9), 'Points-Table'!$C$9, (S62 = 'Points-Table'!$A$10), 'Points-Table'!$C$10, (S62 = 'Points-Table'!$A$11), 'Points-Table'!$C$11, (S62 = 'Points-Table'!$A$12), 'Points-Table'!$C$12, (S62 = 'Points-Table'!$A$13), 'Points-Table'!$C$13, true, 0 ) | U62: 0 | V62: =Ifs( (U62 = 'Points-Table'!$A$4), 'Points-Table'!$C$4, (U62 = 'Points-Table'!$A$5), 'Points-Table'!$C$5, (U62 = 'Points-Table'!$A$6), 'Points-Table'!$C$6, (U62 = 'Points-Table'!$A$7), 'Points-Table'!$C$7, (U62 = 'Points-Table'!$A$8), 'Points-Table'!$C$8, (U62 = 'Points-Table'!$A$9), 'Points-Table'!$C$9, (U62 = 'Points-Table'!$A$10), 'Points-Table'!$C$10, (U62 = 'Points-Table'!$A$11), 'Points-Table'!$C$11, (U62 = 'Points-Table'!$A$12), 'Points-Table'!$C$12, (U62 = 'Points-Table'!$A$13), 'Points-Table'!$C$13, true, 0 ) | W62: 0 | X62: =Ifs( (W62 = 'Points-Table'!$A$4), 'Points-Table'!$C$4, (W62 = 'Points-Table'!$A$5), 'Points-Table'!$C$5, (W62 = 'Points-Table'!$A$6), 'Points-Table'!$C$6, (W62 = 'Points-Table'!$A$7), 'Points-Table'!$C$7, (W62 = 'Points-Table'!$A$8), 'Points-Table'!$C$8, (W62 = 'Points-Table'!$A$9), 'Points-Table'!$C$9, (W62 = 'Points-Table'!$A$10), 'Points-Table'!$C$10, (W62 = 'Points-Table'!$A$11), 'Points-Table'!$C$11, (W62 = 'Points-Table'!$A$12), 'Points-Table'!$C$12, (W62 = 'Points-Table'!$A$13), 'Points-Table'!$C$13, true, 0 ) | Y62: 0 | Z62: =Ifs( (Y62 = 'Points-Table'!$A$4), 'Points-Table'!$C$4, (Y62 = 'Points-Table'!$A$5), 'Points-Table'!$C$5, (Y62 = 'Points-Table'!$A$6), 'Points-Table'!$C$6, (Y62 = 'Points-Table'!$A$7), 'Points-Table'!$C$7, (Y62 = 'Points-Table'!$A$8), 'Points-Table'!$C$8, (Y62 = 'Points-Table'!$A$9), 'Points-Table'!$C$9, (Y62 = 'Points-Table'!$A$10), 'Points-Table'!$C$10, (Y62 = 'Points-Table'!$A$11), 'Points-Table'!$C$11, (Y62 = 'Points-Table'!$A$12), 'Points-Table'!$C$12, (Y62 = 'Points-Table'!$A$13), 'Points-Table'!$C$13, true, 0 ) | AA62: =SUM(V62,X62,Z62) | AB62: =Ifs( ISBETWEEN(AA62, 0, 'Points-Table'!C$20, TRUE, False), 'Points-Table'!A$20, ISBETWEEN(AA62, 'Points-Table'!C$20, 'Points-Table'!C$21, TRUE, False), 'Points-Table'!A$21, ISBETWEEN(AA62, 'Points-Table'!C$22, 10000, TRUE, TRUE), 'Points-Table'!A$22, true, 0)
A63: UX Process | B63: Requirement Gathering | K63: Simple | L63: Must Have | Q63: 13 | R63: =Ifs( (Q63 = 'Points-Table'!$A$4), 'Points-Table'!$C$4, (Q63 = 'Points-Table'!$A$5), 'Points-Table'!$C$5, (Q63 = 'Points-Table'!$A$6), 'Points-Table'!$C$6, (Q63 = 'Points-Table'!$A$7), 'Points-Table'!$C$7, (Q63 = 'Points-Table'!$A$8), 'Points-Table'!$C$8, (Q63 = 'Points-Table'!$A$9), 'Points-Table'!$C$9, (Q63 = 'Points-Table'!$A$10), 'Points-Table'!$C$10, (Q63 = 'Points-Table'!$A$11), 'Points-Table'!$C$11, (Q63 = 'Points-Table'!$A$12), 'Points-Table'!$C$12, (Q63 = 'Points-Table'!$A$13), 'Points-Table'!$C$13, true, 0 ) | T63: =Ifs( (S63 = 'Points-Table'!$A$4), 'Points-Table'!$C$4, (S63 = 'Points-Table'!$A$5), 'Points-Table'!$C$5, (S63 = 'Points-Table'!$A$6), 'Points-Table'!$C$6, (S63 = 'Points-Table'!$A$7), 'Points-Table'!$C$7, (S63 = 'Points-Table'!$A$8), 'Points-Table'!$C$8, (S63 = 'Points-Table'!$A$9), 'Points-Table'!$C$9, (S63 = 'Points-Table'!$A$10), 'Points-Table'!$C$10, (S63 = 'Points-Table'!$A$11), 'Points-Table'!$C$11, (S63 = 'Points-Table'!$A$12), 'Points-Table'!$C$12, (S63 = 'Points-Table'!$A$13), 'Points-Table'!$C$13, true, 0 ) | U63: 0 | V63: =Ifs( (U63 = 'Points-Table'!$A$4), 'Points-Table'!$C$4, (U63 = 'Points-Table'!$A$5), 'Points-Table'!$C$5, (U63 = 'Points-Table'!$A$6), 'Points-Table'!$C$6, (U63 = 'Points-Table'!$A$7), 'Points-Table'!$C$7, (U63 = 'Points-Table'!$A$8), 'Points-Table'!$C$8, (U63 = 'Points-Table'!$A$9), 'Points-Table'!$C$9, (U63 = 'Points-Table'!$A$10), 'Points-Table'!$C$10, (U63 = 'Points-Table'!$A$11), 'Points-Table'!$C$11, (U63 = 'Points-Table'!$A$12), 'Points-Table'!$C$12, (U63 = 'Points-Table'!$A$13), 'Points-Table'!$C$13, true, 0 ) | W63: 0 | X63: =Ifs( (W63 = 'Points-Table'!$A$4), 'Points-Table'!$C$4, (W63 = 'Points-Table'!$A$5), 'Points-Table'!$C$5, (W63 = 'Points-Table'!$A$6), 'Points-Table'!$C$6, (W63 = 'Points-Table'!$A$7), 'Points-Table'!$C$7, (W63 = 'Points-Table'!$A$8), 'Points-Table'!$C$8, (W63 = 'Points-Table'!$A$9), 'Points-Table'!$C$9, (W63 = 'Points-Table'!$A$10), 'Points-Table'!$C$10, (W63 = 'Points-Table'!$A$11), 'Points-Table'!$C$11, (W63 = 'Points-Table'!$A$12), 'Points-Table'!$C$12, (W63 = 'Points-Table'!$A$13), 'Points-Table'!$C$13, true, 0 ) | Y63: 0 | Z63: =Ifs( (Y63 = 'Points-Table'!$A$4), 'Points-Table'!$C$4, (Y63 = 'Points-Table'!$A$5), 'Points-Table'!$C$5, (Y63 = 'Points-Table'!$A$6), 'Points-Table'!$C$6, (Y63 = 'Points-Table'!$A$7), 'Points-Table'!$C$7, (Y63 = 'Points-Table'!$A$8), 'Points-Table'!$C$8, (Y63 = 'Points-Table'!$A$9), 'Points-Table'!$C$9, (Y63 = 'Points-Table'!$A$10), 'Points-Table'!$C$10, (Y63 = 'Points-Table'!$A$11), 'Points-Table'!$C$11, (Y63 = 'Points-Table'!$A$12), 'Points-Table'!$C$12, (Y63 = 'Points-Table'!$A$13), 'Points-Table'!$C$13, true, 0 ) | AA63: =SUM(V63,X63,Z63) | AB63: =Ifs( ISBETWEEN(AA63, 0, 'Points-Table'!C$20, TRUE, False), 'Points-Table'!A$20, ISBETWEEN(AA63, 'Points-Table'!C$20, 'Points-Table'!C$21, TRUE, False), 'Points-Table'!A$21, ISBETWEEN(AA63, 'Points-Table'!C$22, 10000, TRUE, TRUE), 'Points-Table'!A$22, true, 0)
A64: Style Guide | K64: Simple | L64: Must Have | R64: =Ifs( (Q64 = 'Points-Table'!$A$4), 'Points-Table'!$C$4, (Q64 = 'Points-Table'!$A$5), 'Points-Table'!$C$5, (Q64 = 'Points-Table'!$A$6), 'Points-Table'!$C$6, (Q64 = 'Points-Table'!$A$7), 'Points-Table'!$C$7, (Q64 = 'Points-Table'!$A$8), 'Points-Table'!$C$8, (Q64 = 'Points-Table'!$A$9), 'Points-Table'!$C$9, (Q64 = 'Points-Table'!$A$10), 'Points-Table'!$C$10, (Q64 = 'Points-Table'!$A$11), 'Points-Table'!$C$11, (Q64 = 'Points-Table'!$A$12), 'Points-Table'!$C$12, (Q64 = 'Points-Table'!$A$13), 'Points-Table'!$C$13, true, 0 ) | S64: 13 | T64: =Ifs( (S64 = 'Points-Table'!$A$4), 'Points-Table'!$C$4, (S64 = 'Points-Table'!$A$5), 'Points-Table'!$C$5, (S64 = 'Points-Table'!$A$6), 'Points-Table'!$C$6, (S64 = 'Points-Table'!$A$7), 'Points-Table'!$C$7, (S64 = 'Points-Table'!$A$8), 'Points-Table'!$C$8, (S64 = 'Points-Table'!$A$9), 'Points-Table'!$C$9, (S64 = 'Points-Table'!$A$10), 'Points-Table'!$C$10, (S64 = 'Points-Table'!$A$11), 'Points-Table'!$C$11, (S64 = 'Points-Table'!$A$12), 'Points-Table'!$C$12, (S64 = 'Points-Table'!$A$13), 'Points-Table'!$C$13, true, 0 ) | U64: 0 | V64: =Ifs( (U64 = 'Points-Table'!$A$4), 'Points-Table'!$C$4, (U64 = 'Points-Table'!$A$5), 'Points-Table'!$C$5, (U64 = 'Points-Table'!$A$6), 'Points-Table'!$C$6, (U64 = 'Points-Table'!$A$7), 'Points-Table'!$C$7, (U64 = 'Points-Table'!$A$8), 'Points-Table'!$C$8, (U64 = 'Points-Table'!$A$9), 'Points-Table'!$C$9, (U64 = 'Points-Table'!$A$10), 'Points-Table'!$C$10, (U64 = 'Points-Table'!$A$11), 'Points-Table'!$C$11, (U64 = 'Points-Table'!$A$12), 'Points-Table'!$C$12, (U64 = 'Points-Table'!$A$13), 'Points-Table'!$C$13, true, 0 ) | W64: 0 | X64: =Ifs( (W64 = 'Points-Table'!$A$4), 'Points-Table'!$C$4, (W64 = 'Points-Table'!$A$5), 'Points-Table'!$C$5, (W64 = 'Points-Table'!$A$6), 'Points-Table'!$C$6, (W64 = 'Points-Table'!$A$7), 'Points-Table'!$C$7, (W64 = 'Points-Table'!$A$8), 'Points-Table'!$C$8, (W64 = 'Points-Table'!$A$9), 'Points-Table'!$C$9, (W64 = 'Points-Table'!$A$10), 'Points-Table'!$C$10, (W64 = 'Points-Table'!$A$11), 'Points-Table'!$C$11, (W64 = 'Points-Table'!$A$12), 'Points-Table'!$C$12, (W64 = 'Points-Table'!$A$13), 'Points-Table'!$C$13, true, 0 ) | Y64: 0 | Z64: =Ifs( (Y64 = 'Points-Table'!$A$4), 'Points-Table'!$C$4, (Y64 = 'Points-Table'!$A$5), 'Points-Table'!$C$5, (Y64 = 'Points-Table'!$A$6), 'Points-Table'!$C$6, (Y64 = 'Points-Table'!$A$7), 'Points-Table'!$C$7, (Y64 = 'Points-Table'!$A$8), 'Points-Table'!$C$8, (Y64 = 'Points-Table'!$A$9), 'Points-Table'!$C$9, (Y64 = 'Points-Table'!$A$10), 'Points-Table'!$C$10, (Y64 = 'Points-Table'!$A$11), 'Points-Table'!$C$11, (Y64 = 'Points-Table'!$A$12), 'Points-Table'!$C$12, (Y64 = 'Points-Table'!$A$13), 'Points-Table'!$C$13, true, 0 ) | AA64: =SUM(V64,X64,Z64) | AB64: =Ifs( ISBETWEEN(AA64, 0, 'Points-Table'!C$20, TRUE, False), 'Points-Table'!A$20, ISBETWEEN(AA64, 'Points-Table'!C$20, 'Points-Table'!C$21, TRUE, False), 'Points-Table'!A$21, ISBETWEEN(AA64, 'Points-Table'!C$22, 10000, TRUE, TRUE), 'Points-Table'!A$22, true, 0)
